Workbook
Name bn: 1000000000
Name GVKey: "104604-02w"
Name ra.B.TE: [1]ResultsA!$B$328:$AC$328
Name SPSet: "current"

Sheet #주가
A1: Refresh | B1: Last Update : 2026-05-20 17:20:49
A2: 0 | G2: 기준일 | H2: 46161
A3: Time Series (Company) | G3: 할증률 | H3: 0.1
A4: Frequency | B4: D | C4: D | D4: 0 | G4: 종목코드 | H4: A441270
A5: Period(From) | B5: =B6-50000 -> 20210519 | C5: Korean | D5: 0
A6: Period(To) | B6: =TEXT(H2,"yyyymmdd") -> 20260519 | D6: 0 | G6: 기준가격 산정 | H6: =MAX(AVERAGE(H7:H9),H9)*(1+H3) -> 11282.096
G7: 과거 1개월(A) | H7: =SUMIFS(D:D,A:A,">="&H2-30)/(1000*SUMIFS(C:C,A:A,">="&H2-30)) -> 10657.947
A8: Code | B8: =H4 -> A441270 | C8: =B8 -> A441270 | D8: =B8 -> A441270 | E8: =B8 -> A441270 | G8: 과거 1주일(B) | H8: =SUMIFS(D:D,A:A,">="&H2-7)/(1000*SUMIFS(C:C,A:A,">="&H2-7)) -> 10214.05
A9: Name | B9: 파인엠텍 | C9: 파인엠텍 | D9: 파인엠텍 | E9: 파인엠텍 | G9: 최근일(C) | H9: =SUMIFS(D:D,A:A,">="&H2)/(1000*SUMIFS(C:C,A:A,">="&H2)) -> 9897.3571
A10: Item Code | B10: S100300 | C10: S100900 | D10: S101200 | E10: S102100
A11: Unit | B11: Local/Shares | C11: Shares thou | D11: Local | E11: Local
A12: Base Date
A14: D A T E | B14: 수정주가 | C14: 거래량 | D14: 거래대금 | E14: 시가총액
A15: 46161 | B15: 9900 | C15: 435 | D15: 4305350335 | E15: 413138998800
A16: 46160 | B16: 9760 | C16: 253 | D16: 2435792150 | E16: 407296629120
A17: 46157 | B17: 9940 | C17: 606 | D17: 6041963970 | E17: 414808247280
A18: 46156 | B18: 10500 | C18: 313 | D18: 3288119880 | E18: 437783556000
A19: 46155 | B19: 10650 | C19: 884 | D19: 9410515365 | E19: 444037606800
A20: 46154 | B20: 10090 | C20: 465 | D20: 4710990595 | E20: 420689150480
A21: 46153 | B21: 10400 | C21: 356 | D21: 3669973690 | E21: 433614188800
A22: 46150 | B22: 10510 | C22: 236 | D22: 2451367805 | E22: 438200492720
A23: 46149 | B23: 10350 | C23: 531 | D23: 5511906205 | E23: 431529505200
A24: 46148 | B24: 10780 | C24: 370 | D24: 3961866950 | E24: 449457784160
A25: 46146 | B25: 10940 | C25: 486 | D25: 5346734045 | E25: 456128771680
A26: 46142 | B26: 10380 | C26: 345 | D26: 3633829530 | E26: 432780315360
... A896: 44841 | B896: 11100 | C896: 5886 | D896: 62077175120 | E896: 324889363200
A897: 44840
A898: 44839
A899: 44838
A900: 44834
A901: 44833
A902: 44832
A903: 44831
A904: 44830
A905: 44827
A906: 44826
A907: 44825
A908: 44824
... A1239: 44334

Sheet #보고서
B2: A200470 | C2: 에이팩트 | D2: 최근결산 | E2: 202506 | F2: 발행금액(억원) | G2: 200
B4: #별도 | P4: #연결
B6: 재무상태표 | C6: =Model_별도!J3 -> 2020 | D6: =Model_별도!K3 -> 2021 | E6: =Model_별도!L3 -> 2022 | F6: =Model_별도!M3 -> 2023 | G6: =Model_별도!N3 -> 2024 | H6: =RIGHT(Model_별도!O3,5) -> 24.2Q | I6: =RIGHT(Model_별도!P3,5) -> 25.2Q | J6: =Model_별도!Q21 -> 2025E | K6: =Model_별도!R21 -> 2026E | L6: =Model_별도!S21 -> 2027E | M6: =Model_별도!T21 -> 0 | N6: =Model_별도!U21 -> 0 | P6: 재무상태표 | Q6: =Model_연결!J21 -> 2020 | R6: =Model_연결!K21 -> 2021 | S6: =Model_연결!L21 -> 2022 | T6: =Model_연결!M21 -> 2023 | U6: =Model_연결!N21 -> 2024 | V6: =H6 -> 24.2Q | W6: =I6 -> 25.2Q | X6: =Model_연결!Q21 -> 2025E | Y6: =Model_연결!R21 -> 2026E | Z6: =Model_연결!S21 -> 2027E | AA6: =Model_연결!T21 -> 0 | AB6: =Model_연결!U21 -> 0
B7: 유동자산 | C7: =Model_별도!J81 -> 211.51 | D7: =Model_별도!K81 -> 212.39 | E7: =Model_별도!L81 -> 377.54 | F7: =Model_별도!M81 -> 343.34 | G7: =Model_별도!N81 -> 264.7 | H7: =Model_별도!O81 -> 344.16 | I7: =Model_별도!P81 -> 561.75 | J7: =Model_별도!Q81 -> 319.68 | ... N7: =Model_별도!U81 -> 0 | P7: 유동자산 | Q7: =Model_연결!J81 -> 0 | R7: =Model_연결!K81 -> 0 | S7: =Model_연결!L81 -> 0 | T7: =Model_연결!M81 -> 0 | U7: =Model_연결!N81 -> 0 | V7: =Model_연결!O81 -> 0 | W7: =Model_연결!P81 -> 0 | X7: =Model_연결!Q81 -> #DIV/0! | ... AB7: =Model_연결!U81 -> 0
B8: 현금및금융상품 | C8: =Model_별도!J62+Model_별도!J63 -> 176.06 | D8: =Model_별도!K62+Model_별도!K63 -> 185.83 | E8: =Model_별도!L62+Model_별도!L63 -> 182.06 | F8: =Model_별도!M62+Model_별도!M63 -> 217.37 | G8: =Model_별도!N62+Model_별도!N63 -> 141.6 | H8: =Model_별도!O62+Model_별도!O63 -> 240.75 | I8: =Model_별도!P62+Model_별도!P63 -> 82.32 | J8: =Model_별도!Q62+Model_별도!Q63 -> 314.84 | ... N8: =Model_별도!U62+Model_별도!U63 -> 0 | P8: 현금및금융상품 | Q8: =Model_연결!J62+Model_연결!J63 -> 0 | R8: =Model_연결!K62+Model_연결!K63 -> 0 | S8: =Model_연결!L62+Model_연결!L63 -> 0 | T8: =Model_연결!M62+Model_연결!M63 -> 0 | U8: =Model_연결!N62+Model_연결!N63 -> 0 | V8: =Model_연결!O62+Model_연결!O63 -> 0 | W8: =Model_연결!P62+Model_연결!P63 -> 0 | X8: =Model_연결!Q62+Model_연결!Q63 -> #DIV/0! | ... AB8: =Model_연결!U62+Model_연결!U63 -> 0
B9: 매출채권 | C9: =Model_별도!J72 -> 13.13 | D9: =Model_별도!K72 -> 22.68 | E9: =Model_별도!L72 -> 93.09 | F9: =Model_별도!M72 -> 59.66 | G9: =Model_별도!N72 -> 72.95 | H9: =Model_별도!O72 -> 63.62 | I9: =Model_별도!P72 -> 76.79 | J9: =Model_별도!Q72 -> 0 | ... N9: =Model_별도!U72 -> 0 | P9: 매출채권 | Q9: =Model_연결!J71 -> 0 | R9: =Model_연결!K71 -> 0 | S9: =Model_연결!L71 -> 0 | T9: =Model_연결!M71 -> 0 | U9: =Model_연결!N71 -> 0 | V9: =Model_연결!O71 -> 0 | W9: =Model_연결!P71 -> 0 | X9: =Model_연결!Q71 -> #DIV/0! | ... AB9: =Model_연결!U71 -> 0
B10: 재고자산 | C10: =Model_별도!J76 -> 0 | D10: =Model_별도!K76 -> 0 | E10: =Model_별도!L76 -> 83.17 | F10: =Model_별도!M76 -> 48.8 | G10: =Model_별도!N76 -> 35.83 | H10: =Model_별도!O76 -> 29.91 | I10: =Model_별도!P76 -> 40.11 | J10: =Model_별도!Q76 -> 0 | ... N10: =Model_별도!U76 -> 0 | P10: 재고자산 | Q10: =Model_연결!J77 -> 0 | R10: =Model_연결!K77 -> 0 | S10: =Model_연결!L77 -> 0 | T10: =Model_연결!M77 -> 0 | U10: =Model_연결!N77 -> 0 | V10: =Model_연결!O77 -> 0 | W10: =Model_연결!P77 -> 0 | X10: =Model_연결!Q77 -> #DIV/0! | ... AB10: =Model_연결!U77 -> 0
B11: 기타유동자산 | C11: =C7-SUM(C8:C10) -> 22.32 | D11: =D7-SUM(D8:D10) -> 3.88 | E11: =E7-SUM(E8:E10) -> 19.22 | F11: =F7-SUM(F8:F10) -> 17.51 | G11: =G7-SUM(G8:G10) -> 14.32 | H11: =H7-SUM(H8:H10) -> 9.88 | I11: =I7-SUM(I8:I10) -> 362.53 | J11: =J7-SUM(J8:J10) -> 4.84 | ... N11: =N7-SUM(N8:N10) -> 0 | P11: 기타유동자산 | Q11: =Q7-SUM(Q8:Q10) -> 0 | R11: =R7-SUM(R8:R10) -> 0 | S11: =S7-SUM(S8:S10) -> 0 | T11: =T7-SUM(T8:T10) -> 0 | U11: =U7-SUM(U8:U10) -> 0 | V11: =V7-SUM(V8:V10) -> 0 | W11: =W7-SUM(W8:W10) -> 0 | X11: =X7-SUM(X8:X10) -> #DIV/0! | ... AB11: =AB7-SUM(AB8:AB10) -> 0
B12: 비유동자산 | C12: =Model_별도!J96 -> 1092.73 | D12: =Model_별도!K96 -> 948.22 | E12: =Model_별도!L96 -> 1763.92 | F12: =Model_별도!M96 -> 1751.71 | G12: =Model_별도!N96 -> 1360.18 | H12: =Model_별도!O96 -> 1646.52 | I12: =Model_별도!P96 -> 988.13 | J12: =Model_별도!Q96 -> 1254.04 | ... N12: =Model_별도!U96 -> 0 | P12: 비유동자산 | Q12: =Model_연결!J96 -> 0 | R12: =Model_연결!K96 -> 0 | S12: =Model_연결!L96 -> 0 | T12: =Model_연결!M96 -> 0 | U12: =Model_연결!N96 -> 0 | V12: =Model_연결!O96 -> 0 | W12: =Model_연결!P96 -> 0 | X12: =Model_연결!Q96 -> #DIV/0! | ... AB12: =Model_연결!U96 -> 0
B13: 비유동기타금융자산 | C13: =Model_별도!J90 -> 1.73 | D13: =Model_별도!K90 -> 4.18 | E13: =Model_별도!L90 -> 14.13 | F13: =Model_별도!M90 -> 10.95 | G13: =Model_별도!N90 -> 0.6 | H13: =Model_별도!O90 -> 3.08 | I13: =Model_별도!P90 -> 0.42 | J13: =Model_별도!Q90 -> 0.6 | ... N13: =Model_별도!U90 -> 0 | P13: 비유동기타금융자산 | Q13: =Model_연결!J90 -> 0 | R13: =Model_연결!K90 -> 0 | S13: =Model_연결!L90 -> 0 | T13: =Model_연결!M90 -> 0 | U13: =Model_연결!N90 -> 0 | V13: =Model_연결!O90 -> 0 | W13: =Model_연결!P90 -> 0 | X13: =Model_연결!Q90 -> 0 | ... AA13: =Model_연결!T90 -> 0
B14: 유형자산(투자부동산 포함) | C14: =Model_별도!J86+Model_별도!J84+Model_별도!J85+Model_별도!J82 -> 1044.27 | D14: =Model_별도!K86+Model_별도!K84+Model_별도!K85+Model_별도!K82 -> 888.59 | E14: =Model_별도!L86+Model_별도!L84+Model_별도!L85+Model_별도!L82 -> 1621.29 | F14: =Model_별도!M86+Model_별도!M84+Model_별도!M85+Model_별도!M82 -> 1566.17 | G14: =Model_별도!N86+Model_별도!N84+Model_별도!N85+Model_별도!N82 -> 1218.93 | H14: =Model_별도!O86+Model_별도!O84+Model_별도!O85+Model_별도!O82 -> 1504.01 | I14: =Model_별도!P86+Model_별도!P84+Model_별도!P85+Model_별도!P82 -> 860.81 | J14: =Model_별도!Q86+Model_별도!Q84+Model_별도!Q85+Model_별도!Q82 -> 1112.79 | ... N14: =Model_별도!U86+Model_별도!U84+Model_별도!U85+Model_별도!U82 -> 0 | P14: 유형자산(투자부동산 포함) | Q14: =Model_연결!J86+Model_연결!J84+Model_연결!J82+Model_연결!J85 -> 0 | R14: =Model_연결!K86+Model_연결!K84+Model_연결!K82+Model_연결!K85 -> 0 | S14: =Model_연결!L86+Model_연결!L84+Model_연결!L82+Model_연결!L85 -> 0 | T14: =Model_연결!M86+Model_연결!M84+Model_연결!M82+Model_연결!M85 -> 0 | U14: =Model_연결!N86+Model_연결!N84+Model_연결!N82+Model_연결!N85 -> 0 | V14: =Model_연결!O86+Model_연결!O84+Model_연결!O82+Model_연결!O85 -> 0 | W14: =Model_연결!P86+Model_연결!P84+Model_연결!P82+Model_연결!P85 -> 0 | X14: =Model_연결!Q86+Model_연결!Q84+Model_연결!Q82+Model_연결!Q85 -> #DIV/0! | ... AB14: =Model_연결!U86+Model_연결!U84+Model_연결!U82+Model_연결!U85 -> 0
B15: 무형자산 | C15: =Model_별도!J88 -> 2.19 | D15: =Model_별도!K88 -> 7.73 | E15: =Model_별도!L88 -> 28.39 | F15: =Model_별도!M88 -> 21.37 | G15: =Model_별도!N88 -> 15.74 | H15: =Model_별도!O88 -> 19.23 | I15: =Model_별도!P88 -> 10.58 | J15: =Model_별도!Q88 -> 15.74 | ... N15: =Model_별도!U88 -> 0 | P15: 무형자산 | Q15: =Model_연결!J88 -> 0 | R15: =Model_연결!K88 -> 0 | S15: =Model_연결!L88 -> 0 | T15: =Model_연결!M88 -> 0 | U15: =Model_연결!N88 -> 0 | V15: =Model_연결!O88 -> 0 | W15: =Model_연결!P88 -> 0 | X15: =Model_연결!Q88 -> 0 | ... AB15: =Model_연결!U88 -> 0
B16: 관계기업등지분 | C16: =Model_별도!J83 -> 0 | D16: =Model_별도!K83 -> 0 | E16: =Model_별도!L83 -> 0 | F16: =Model_별도!M83 -> 0 | G16: =Model_별도!N83 -> 0 | H16: =Model_별도!O83 -> 0 | I16: =Model_별도!P83 -> 0 | J16: =Model_별도!Q83 -> 0 | ... N16: =Model_별도!U83 -> 0 | P16: 관계기업등지분 | Q16: =Model_연결!J83 -> 0 | R16: =Model_연결!K83 -> 0 | S16: =Model_연결!L83 -> 0 | T16: =Model_연결!M83 -> 0 | U16: =Model_연결!N83 -> 0 | V16: =Model_연결!O83 -> 0 | W16: =Model_연결!P83 -> 0 | X16: =Model_연결!Q83 -> 0 | ... AB16: =Model_연결!U83 -> 0
B17: 기타비유동자산 | C17: =C12-SUM(C13:C16) -> 44.54 | D17: =D12-SUM(D13:D16) -> 47.72 | E17: =E12-SUM(E13:E16) -> 100.11 | F17: =F12-SUM(F13:F16) -> 153.22 | G17: =G12-SUM(G13:G16) -> 124.91 | H17: =H12-SUM(H13:H16) -> 120.2 | I17: =I12-SUM(I13:I16) -> 116.32 | J17: =J12-SUM(J13:J16) -> 124.91 | ... N17: =N12-SUM(N13:N16) -> 0 | P17: 기타비유동자산 | Q17: =Q12-SUM(Q13:Q16) -> 0 | R17: =R12-SUM(R13:R16) -> 0 | S17: =S12-SUM(S13:S16) -> 0 | T17: =T12-SUM(T13:T16) -> 0 | U17: =U12-SUM(U13:U16) -> 0 | V17: =V12-SUM(V13:V16) -> 0 | W17: =W12-SUM(W13:W16) -> 0 | X17: =X12-SUM(X13:X16) -> #DIV/0! | ... AB17: =AB12-SUM(AB13:AB16) -> 0
B18: 자산총계 | C18: =C12+C7 -> 1304.24 | D18: =D12+D7 -> 1160.61 | E18: =E12+E7 -> 2141.46 | F18: =F12+F7 -> 2095.05 | G18: =G12+G7 -> 1624.88 | H18: =H12+H7 -> 1990.68 | I18: =I12+I7 -> 1549.88 | J18: =J12+J7 -> 1573.72 | ... N18: =N12+N7 -> 0 | P18: 자산총계 | Q18: =Q12+Q7 -> 0 | R18: =R12+R7 -> 0 | S18: =S12+S7 -> 0 | T18: =T12+T7 -> 0 | U18: =U12+U7 -> 0 | V18: =V12+V7 -> 0 | W18: =W12+W7 -> 0 | X18: =X12+X7 -> #DIV/0! | ... AB18: =AB12+AB7 -> 0
B19: 유동부채 | C19: =Model_별도!J113 -> 389.9 | D19: =Model_별도!K113 -> 275.2 | E19: =Model_별도!L113 -> 427.44 | F19: =Model_별도!M113 -> 806.17 | G19: =Model_별도!N113 -> 863.12 | H19: =Model_별도!O113 -> 842.63 | I19: =Model_별도!P113 -> 824.85 | J19: =Model_별도!Q113 -> 811.74 | ... N19: =Model_별도!U113 -> 0 | P19: 유동부채 | Q19: =Model_연결!J113 -> 0 | R19: =Model_연결!K113 -> 0 | S19: =Model_연결!L113 -> 0 | T19: =Model_연결!M113 -> 0 | U19: =Model_연결!N113 -> 0 | V19: =Model_연결!O113 -> 0 | W19: =Model_연결!P113 -> 0 | X19: =Model_연결!Q113 -> #DIV/0! | ... AB19: =Model_연결!U113 -> 0
B20: 매입채무 | C20: =Model_별도!J98 -> 0 | D20: =Model_별도!K98 -> 0 | E20: =Model_별도!L98 -> 68.85 | F20: =Model_별도!M98 -> 26.63 | G20: =Model_별도!N98 -> 51.38 | H20: =Model_별도!O98 -> 25.51 | I20: =Model_별도!P98 -> 56.12 | J20: =Model_별도!Q98 -> 0 | ... N20: =Model_별도!U98 -> 0 | P20: 매입채무 | Q20: =Model_연결!J98 -> 0 | R20: =Model_연결!K98 -> 0 | S20: =Model_연결!L98 -> 0 | T20: =Model_연결!M98 -> 0 | U20: =Model_연결!N98 -> 0 | V20: =Model_연결!O98 -> 0 | W20: =Model_연결!P98 -> 0 | X20: =Model_연결!Q98 -> #DIV/0! | ... AB20: =Model_연결!U98 -> 0
B21: 단기차입금 | C21: =Model_별도!J105 -> 320.7 | D21: =Model_별도!K105 -> 238.75 | E21: =Model_별도!L105 -> 185 | F21: =Model_별도!M105 -> 665 | G21: =Model_별도!N105 -> 719 | H21: =Model_별도!O105 -> 725 | I21: =Model_별도!P105 -> 677 | J21: =Model_별도!Q105 -> 719 | ... N21: =Model_별도!U105 -> 0 | P21: 단기차입금 | Q21: =Model_연결!J105 -> 0 | R21: =Model_연결!K105 -> 0 | S21: =Model_연결!L105 -> 0 | T21: =Model_연결!M105 -> 0 | U21: =Model_연결!N105 -> 0 | V21: =Model_연결!O105 -> 0 | W21: =Model_연결!P105 -> 0 | X21: =Model_연결!Q105 -> 0 | ... AB21: =Model_연결!U105 -> 0
B22: 기타유동부채 | C22: =C19-SUM(C20:C21) -> 69.2 | D22: =D19-SUM(D20:D21) -> 36.45 | E22: =E19-SUM(E20:E21) -> 173.59 | F22: =F19-SUM(F20:F21) -> 114.54 | G22: =G19-SUM(G20:G21) -> 92.74 | H22: =H19-SUM(H20:H21) -> 92.12 | I22: =I19-SUM(I20:I21) -> 91.73 | J22: =J19-SUM(J20:J21) -> 92.74 | ... N22: =N19-SUM(N20:N21) -> 0 | P22: 기타유동부채 | Q22: =Q19-SUM(Q20:Q21) -> 0 | R22: =R19-SUM(R20:R21) -> 0 | S22: =S19-SUM(S20:S21) -> 0 | T22: =T19-SUM(T20:T21) -> 0 | U22: =U19-SUM(U20:U21) -> 0 | V22: =V19-SUM(V20:V21) -> 0 | W22: =W19-SUM(W20:W21) -> 0 | X22: =X19-SUM(X20:X21) -> #DIV/0! | ... AB22: =AB19-SUM(AB20:AB21) -> 0
B23: 비유동부채 | C23: =Model_별도!J122 -> 241.85 | D23: =Model_별도!K122 -> 176.49 | E23: =Model_별도!L122 -> 566.28 | F23: =Model_별도!M122 -> 308.08 | G23: =Model_별도!N122 -> 209.4 | H23: =Model_별도!O122 -> 255.62 | I23: =Model_별도!P122 -> 215.46 | J23: =Model_별도!Q122 -> 209.4 | ... N23: =Model_별도!U122 -> 0 | P23: 비유동부채 | Q23: =Model_연결!J122 -> 0 | R23: =Model_연결!K122 -> 0 | S23: =Model_연결!L122 -> 0 | T23: =Model_연결!M122 -> 0 | U23: =Model_연결!N122 -> 0 | V23: =Model_연결!O122 -> 0 | W23: =Model_연결!P122 -> 0 | X23: =Model_연결!Q122 -> 200 | ... AB23: =Model_연결!U122 -> 0
B24: 장기차입금 | C24: =Model_별도!J114 -> 231.25 | D24: =Model_별도!K114 -> 175 | E24: =Model_별도!L114 -> 550 | F24: =Model_별도!M114 -> 300 | G24: =Model_별도!N114 -> 200 | H24: =Model_별도!O114 -> 250 | I24: =Model_별도!P114 -> 195 | J24: =Model_별도!Q114 -> 200 | ... N24: =Model_별도!U114 -> 0 | P24: 장기차입금 | Q24: =Model_연결!J114 -> 0 | R24: =Model_연결!K114 -> 0 | S24: =Model_연결!L114 -> 0 | T24: =Model_연결!M114 -> 0 | U24: =Model_연결!N114 -> 0 | V24: =Model_연결!O114 -> 0 | W24: =Model_연결!P114 -> 0 | X24: =Model_연결!Q114 -> 200 | ... AB24: =Model_연결!U114 -> 0
B25: 기타비유동부채 | C25: =C23-C24 -> 10.6 | D25: =D23-D24 -> 1.49 | E25: =E23-E24 -> 16.28 | F25: =F23-F24 -> 8.08 | G25: =G23-G24 -> 9.4 | H25: =H23-H24 -> 5.62 | I25: =I23-I24 -> 20.46 | J25: =J23-J24 -> 9.4 | ... N25: =N23-N24 -> 0 | P25: 기타비유동부채 | Q25: =Q23-Q24 -> 0 | R25: =R23-R24 -> 0 | S25: =S23-S24 -> 0 | T25: =T23-T24 -> 0 | U25: =U23-U24 -> 0 | V25: =V23-V24 -> 0 | W25: =W23-W24 -> 0 | X25: =X23-X24 -> 0 | ... AB25: =AB23-AB24 -> 0
B26: 부채총계 | C26: =C23+C19 -> 631.75 | D26: =D23+D19 -> 451.69 | E26: =E23+E19 -> 993.72 | F26: =F23+F19 -> 1114.25 | G26: =G23+G19 -> 1072.52 | H26: =H23+H19 -> 1098.25 | I26: =I23+I19 -> 1040.31 | J26: =J23+J19 -> 1021.14 | ... N26: =N23+N19 -> 0 | P26: 부채총계 | Q26: =Q23+Q19 -> 0 | R26: =R23+R19 -> 0 | S26: =S23+S19 -> 0 | T26: =T23+T19 -> 0 | U26: =U23+U19 -> 0 | V26: =V23+V19 -> 0 | W26: =W23+W19 -> 0 | X26: =X23+X19 -> #DIV/0! | ... AB26: =AB23+AB19 -> 0
B27: 자본금 | C27: =Model_별도!J124 -> 87.77 | D27: =Model_별도!K124 -> 92.38 | E27: =Model_별도!L124 -> 211.81 | F27: =Model_별도!M124 -> 211.81 | G27: =Model_별도!N124 -> 211.81 | H27: =Model_별도!O124 -> 211.81 | I27: =Model_별도!P124 -> 211.81 | J27: =Model_별도!Q124 -> 211.81 | ... N27: =Model_별도!U124 -> 0 | P27: 자본금 | Q27: =Model_연결!J124 -> 0 | R27: =Model_연결!K124 -> 0 | S27: =Model_연결!L124 -> 0 | T27: =Model_연결!M124 -> 0 | U27: =Model_연결!N124 -> 0 | V27: =Model_연결!O124 -> 0 | W27: =Model_연결!P124 -> 0 | X27: =Model_연결!Q124 -> 0 | ... AB27: =Model_연결!U124 -> 0
B28: 기타자본 | C28: =C30-C29-C27 -> 211.78 | D28: =D30-D29-D27 -> 215.16 | E28: =E30-E29-E27 -> 502.28 | F28: =F30-F29-F27 -> 502.25 | G28: =G30-G29-G27 -> 588.3 | H28: =H30-H29-H27 -> 588.3 | I28: =I30-I29-I27 -> 588.3 | J28: =J30-J29-J27 -> 588.3 | ... N28: =N30-N29-N27 -> 0 | P28: 기타자본 | Q28: =Q30-Q29-Q27 -> 0 | R28: =R30-R29-R27 -> 0 | S28: =S30-S29-S27 -> 0 | T28: =T30-T29-T27 -> 0 | U28: =U30-U29-U27 -> 0 | V28: =V30-V29-V27 -> 0 | W28: =W30-W29-W27 -> 0 | X28: =X30-X29-X27 -> #DIV/0! | ... AB28: =AB30-AB29-AB27 -> 0
B29: 이익잉여금 | C29: =Model_별도!J128 -> 372.94 | D29: =Model_별도!K128 -> 401.38 | E29: =Model_별도!L128 -> 433.64 | F29: =Model_별도!M128 -> 266.75 | G29: =Model_별도!N128 -> -247.75 | H29: =Model_별도!O128 -> 92.33 | I29: =Model_별도!P128 -> -290.54 | J29: =Model_별도!Q128 -> -247.53 | ... N29: =Model_별도!U128 -> 0 | P29: 이익잉여금 | Q29: =Model_연결!J128 -> 0 | R29: =Model_연결!K128 -> 0 | S29: =Model_연결!L128 -> 0 | T29: =Model_연결!M128 -> 0 | U29: =Model_연결!N128 -> 0 | V29: =Model_연결!O128 -> 0 | W29: =Model_연결!P128 -> 0 | X29: =Model_연결!Q128 -> #DIV/0! | ... AB29: =Model_연결!U128 -> 0
B30: 자본총계 | C30: =Model_별도!J131 -> 672.49 | D30: =Model_별도!K131 -> 708.92 | E30: =Model_별도!L131 -> 1147.73 | F30: =Model_별도!M131 -> 980.81 | G30: =Model_별도!N131 -> 552.36 | H30: =Model_별도!O131 -> 892.44 | I30: =Model_별도!P131 -> 509.57 | J30: =Model_별도!Q131 -> 552.58 | ... N30: =Model_별도!U131 -> 0 | P30: 자본총계 | Q30: =Model_연결!J131 -> 0 | R30: =Model_연결!K131 -> 0 | S30: =Model_연결!L131 -> 0 | T30: =Model_연결!M131 -> 0 | U30: =Model_연결!N131 -> 0 | V30: =Model_연결!O131 -> 0 | W30: =Model_연결!P131 -> 0 | X30: =Model_연결!Q131 -> #DIV/0! | ... AB30: =Model_연결!U131 -> 0
B31: 총차입금 | C31: =Model_별도!J13 -> 551.95 | D31: =Model_별도!K13 -> 413.75 | E31: =Model_별도!L13 -> 735 | F31: =Model_별도!M13 -> 965 | G31: =Model_별도!N13 -> 919 | H31: =Model_별도!O13 -> 975 | I31: =Model_별도!P13 -> 872 | J31: =Model_별도!Q13 -> 919 | ... N31: =Model_별도!U13 -> 0 | P31: 총차입금 | Q31: =Model_연결!J13 -> 0 | R31: =Model_연결!K13 -> 0 | S31: =Model_연결!L13 -> 0 | T31: =Model_연결!M13 -> 0 | U31: =Model_연결!N13 -> 0 | V31: =Model_연결!O13 -> 0 | W31: =Model_연결!P13 -> 0 | X31: =Model_연결!Q13 -> 200 | ... AB31: =Model_연결!U13 -> 0
B32: 현금 및 장단기금융자산 | C32: =C31-C33 -> 177.79 | D32: =D31-D33 -> 190.01 | E32: =E31-E33 -> 196.19 | F32: =F31-F33 -> 228.32 | G32: =G31-G33 -> 142.2 | H32: =H31-H33 -> 243.83 | I32: =I31-I33 -> 82.74 | J32: =J31-J33 -> 315.44 | ... N32: =N31-N33 -> 0 | P32: 현금 및 예금 | Q32: =Q31-Q33 -> 0 | R32: =R31-R33 -> 0 | S32: =S31-S33 -> 0 | T32: =T31-T33 -> 0 | U32: =U31-U33 -> 0 | V32: =V31-V33 -> 0 | W32: =W31-W33 -> 0 | X32: =X31-X33 -> #DIV/0! | ... AB32: =AB31-AB33 -> 0
B33: 순차입금 | C33: =Model_별도!J14 -> 374.16 | D33: =Model_별도!K14 -> 223.74 | E33: =Model_별도!L14 -> 538.81 | F33: =Model_별도!M14 -> 736.68 | G33: =Model_별도!N14 -> 776.8 | H33: =Model_별도!O14 -> 731.17 | I33: =Model_별도!P14 -> 789.26 | J33: =Model_별도!Q14 -> 603.56 | ... N33: =Model_별도!U14 -> 0 | P33: 순차입금 | Q33: =Model_연결!J14 -> 0 | R33: =Model_연결!K14 -> 0 | S33: =Model_연결!L14 -> 0 | T33: =Model_연결!M14 -> 0 | U33: =Model_연결!N14 -> 0 | V33: =Model_연결!O14 -> 0 | W33: =Model_연결!P14 -> 0 | X33: =Model_연결!Q14 -> #DIV/0! | ... AB33: =Model_연결!U14 -> 0
B34: 순차입금/EBITDA | C34: =Model_별도!J17 -> 1.8443338 | D34: =Model_별도!K17 -> 1.2649254 | E34: =Model_별도!L17 -> 2.8395784 | F34: =Model_별도!M17 -> -105.08987 | G34: =Model_별도!N17 -> 197.15736 | H34: =Model_별도!O17 -> -20.890571 | I34: =Model_별도!P17 -> 8.9464974 | J34: =Model_별도!Q17 -> 5.1843326 | ... N34: =Model_별도!U17 -> 0 | P34: 순차입금/EBITDA | Q34: =Model_연결!J17 -> #DIV/0! | R34: =Model_연결!K17 -> #DIV/0! | S34: =Model_연결!L17 -> #DIV/0! | T34: =Model_연결!M17 -> #DIV/0! | U34: =Model_연결!N17 -> #DIV/0! | V34: =Model_연결!O17 -> #DIV/0! | W34: =Model_연결!P17 -> #DIV/0! | X34: =Model_연결!Q17 -> #DIV/0! | ... AB34: =Model_연결!U17 -> 0
B35: 단기차입비중 | C35: =C21/C31 -> 0.58103089 | D35: =D21/D31 -> 0.57703927 | E35: =E21/E31 -> 0.25170068 | F35: =F21/F31 -> 0.68911917 | G35: =G21/G31 -> 0.78237214 | H35: =H21/H31 -> 0.74358974 | I35: =I21/I31 -> 0.77637615 | J35: =J21/J31 -> 0.78237214 | ... N35: =N21/N31 -> #DIV/0! | P35: 단기차입비중 | Q35: =Q21/Q31 -> #DIV/0! | R35: =R21/R31 -> #DIV/0! | S35: =S21/S31 -> #DIV/0! | T35: =T21/T31 -> #DIV/0! | U35: =U21/U31 -> #DIV/0! | V35: =V21/V31 -> #DIV/0! | W35: =W21/W31 -> #DIV/0! | X35: =X21/X31 -> 0 | ... AB35: =AB21/AB31 -> #DIV/0!
B36: 부채비율 | C36: =Model_별도!J18 -> 0.93941917 | D36: =Model_별도!K18 -> 0.63715229 | E36: =Model_별도!L18 -> 0.86581339 | F36: =Model_별도!M18 -> 1.1360508 | G36: =Model_별도!N18 -> 1.9417047 | H36: =Model_별도!O18 -> 1.2306149 | I36: =Model_별도!P18 -> 2.0415448 | J36: =Model_별도!Q18 -> 1.8479496 | ... N36: =Model_별도!U18 -> 0 | P36: 부채비율 | Q36: =Model_연결!J18 -> #DIV/0! | R36: =Model_연결!K18 -> #DIV/0! | S36: =Model_연결!L18 -> #DIV/0! | T36: =Model_연결!M18 -> #DIV/0! | U36: =Model_연결!N18 -> #DIV/0! | V36: =Model_연결!O18 -> #DIV/0! | W36: =Model_연결!P18 -> #DIV/0! | X36: =Model_연결!Q18 -> #DIV/0! | ... AB36: =Model_연결!U18 -> 0
B37: 차입금의존도 | C37: =Model_별도!J19 -> 0.42319665 | D37: =Model_별도!K19 -> 0.35649357 | E37: =Model_별도!L19 -> 0.34322378 | F37: =Model_별도!M19 -> 0.46060953 | G37: =Model_별도!N19 -> 0.56558023 | H37: =Model_별도!O19 -> 0.48978239 | I37: =Model_별도!P19 -> 0.5626242 | J37: =Model_별도!Q19 -> 0.58396665 | ... N37: =Model_별도!U19 -> 0 | P37: 차입금의존도 | Q37: =Model_연결!J19 -> #DIV/0! | R37: =Model_연결!K19 -> #DIV/0! | S37: =Model_연결!L19 -> #DIV/0! | T37: =Model_연결!M19 -> #DIV/0! | U37: =Model_연결!N19 -> #DIV/0! | V37: =Model_연결!O19 -> #DIV/0! | W37: =Model_연결!P19 -> #DIV/0! | X37: =Model_연결!Q19 -> #DIV/0! | ... AB37: =Model_연결!U19 -> 0
B39: 손익계산서 | C39: =C6 -> 2020 | D39: =D6 -> 2021 | E39: =E6 -> 2022 | F39: =F6 -> 2023 | G39: =G6 -> 2024 | H39: =V6 -> 24.2Q | I39: =W6 -> 25.2Q | J39: =J6 -> 2025E | K39: =K6 -> 2026E | L39: =L6 -> 2027E | M39: =M6 -> 0 | N39: =N6 -> 0 | P39: 손익계산서 | Q39: =Q6 -> 2020 | R39: =R6 -> 2021 | S39: =S6 -> 2022 | T39: =T6 -> 2023 | U39: =U6 -> 2024 | V39: =V6 -> 24.2Q | W39: =W6 -> 25.2Q | X39: =X6 -> 2025E | ... AB39: =AB6 -> 0
B40: 매출액 | C40: =Model_별도!J22 -> 496.3 | D40: =Model_별도!K22 -> 472.17 | E40: =Model_별도!L22 -> 736.46 | F40: =Model_별도!M22 -> 937.42 | G40: =Model_별도!N22 -> 867.23 | H40: =Model_별도!O22 -> 419.17 | I40: =Model_별도!P22 -> 500.61 | J40: =Model_별도!Q22 -> 0 | ... N40: =Model_별도!U22 -> 0 | P40: 매출액 | Q40: =Model_연결!J22 -> 0 | R40: =Model_연결!K22 -> 0 | S40: =Model_연결!L22 -> 0 | T40: =Model_연결!M22 -> 0 | U40: =Model_연결!N22 -> 0 | V40: =Model_연결!O22 -> 0 | W40: =Model_연결!P22 -> 0 | X40: =Model_연결!Q22 -> 1051 | ... AB40: =Model_연결!U22 -> 0
B41: 매출액증감률 | C41: =Model_별도!J23 -> 0.059541854 | D41: =Model_별도!K23 -> -0.048619786 | E41: =Model_별도!L23 -> 0.55973484 | F41: =Model_별도!M23 -> 0.27287293 | G41: =Model_별도!N23 -> -0.074875723 | H41: - | I41: =Model_별도!P23 -> 0.19428871 | J41: =Model_별도!Q23 -> -1 | K41: =Model_별도!R23 -> #DIV/0! | L41: =Model_별도!S23 -> #DIV/0! | M41: =Model_별도!T23 -> 0 | N41: =Model_별도!U23 -> 0 | P41: 매출액증감률 | Q41: =Model_연결!J23 -> #DIV/0! | R41: =Model_연결!K23 -> #DIV/0! | S41: =Model_연결!L23 -> #DIV/0! | T41: =Model_연결!M23 -> #DIV/0! | U41: =Model_연결!N23 -> #DIV/0! | V41: - | W41: =Model_연결!P23 -> #DIV/0! | X41: =Model_연결!Q23 -> #DIV/0! | Y41: =Model_연결!R23 -> -1 | Z41: =Model_연결!S23 -> #DIV/0! | AA41: =Model_연결!T23 -> 0 | AB41: =Model_연결!U23 -> 0
B42: 매출원가 | C42: =Model_별도!J24 -> 396.91 | D42: =Model_별도!K24 -> 399.21 | E42: =Model_별도!L24 -> 649.72 | F42: =Model_별도!M24 -> 1098.7 | G42: =Model_별도!N24 -> 1022.3 | H42: =Model_별도!O24 -> 520.12 | I42: =Model_별도!P24 -> 489.32 | J42: =Model_별도!Q24 -> 0 | ... N42: =Model_별도!U24 -> 0 | P42: 매출원가 | Q42: =Model_연결!J24 -> 0 | R42: =Model_연결!K24 -> 0 | S42: =Model_연결!L24 -> 0 | T42: =Model_연결!M24 -> 0 | U42: =Model_연결!N24 -> 0 | V42: =Model_연결!O24 -> 0 | W42: =Model_연결!P24 -> 0 | X42: =Model_연결!Q24 -> #DIV/0! | ... AB42: =Model_연결!U24 -> 0
B43: 매출총이익 | C43: =C40-C42 -> 99.39 | D43: =D40-D42 -> 72.96 | E43: =E40-E42 -> 86.74 | F43: =F40-F42 -> -161.28 | G43: =G40-G42 -> -155.07 | H43: =H40-H42 -> -100.95 | I43: =I40-I42 -> 11.29 | J43: =J40-J42 -> 0 | ... N43: =N40-N42 -> 0 | P43: 매출총이익 | Q43: =Q40-Q42 -> 0 | R43: =R40-R42 -> 0 | S43: =S40-S42 -> 0 | T43: =T40-T42 -> 0 | U43: =U40-U42 -> 0 | V43: =V40-V42 -> 0 | W43: =W40-W42 -> 0 | X43: =X40-X42 -> #DIV/0! | ... AB43: =AB40-AB42 -> 0
B44: 매출총이익률 | C44: =C43/C$40 -> 0.20026194 | D44: =D43/D$40 -> 0.15452062 | E44: =E43/E$40 -> 0.11777965 | F44: =F43/F$40 -> -0.17204668 | G44: =G43/G$40 -> -0.1788107 | H44: =H43/H$40 -> -0.24083307 | I44: =I43/I$40 -> 0.022552486 | J44: =J43/J$40 -> #DIV/0! | ... N44: =N43/N$40 -> #DIV/0! | P44: 매출총이익률 | Q44: =Q43/Q$40 -> #DIV/0! | R44: =R43/R$40 -> #DIV/0! | S44: =S43/S$40 -> #DIV/0! | T44: =T43/T$40 -> #DIV/0! | U44: =U43/U$40 -> #DIV/0! | V44: =V43/V$40 -> #DIV/0! | W44: =W43/W$40 -> #DIV/0! | X44: =X43/X$40 -> #DIV/0! | ... AB44: =AB43/AB$40 -> #DIV/0!
B45: 판매비와관리비 | C45: =C43-C46 -> 33.94 | D45: =D43-D46 -> 32.76 | E45: =E43-E46 -> 40.88 | F45: =F43-F46 -> 67.52 | G45: =G43-G46 -> 60.26 | H45: =H43-H46 -> 29.03 | I45: =I43-I46 -> 25.52 | J45: =J43-J46 -> 0 | ... N45: =N43-N46 -> 0 | P45: 판매비와관리비 | Q45: =Q43-Q46 -> 0 | R45: =R43-R46 -> 0 | S45: =S43-S46 -> 0 | T45: =T43-T46 -> 0 | U45: =U43-U46 -> 0 | V45: =V43-V46 -> 0 | W45: =W43-W46 -> 0 | X45: =X43-X46 -> #DIV/0! | ... AB45: =AB43-AB46 -> 0
B46: 영업이익 | C46: =Model_별도!J32 -> 65.45 | D46: =Model_별도!K32 -> 40.2 | E46: =Model_별도!L32 -> 45.86 | F46: =Model_별도!M32 -> -228.8 | G46: =Model_별도!N32 -> -215.33 | H46: =Model_별도!O32 -> -129.98 | I46: =Model_별도!P32 -> -14.23 | J46: =Model_별도!Q32 -> 0 | ... N46: =Model_별도!U32 -> 0 | P46: 영업이익 | Q46: =Model_연결!J32 -> 0 | R46: =Model_연결!K32 -> 0 | S46: =Model_연결!L32 -> 0 | T46: =Model_연결!M32 -> 0 | U46: =Model_연결!N32 -> 0 | V46: =Model_연결!O32 -> 0 | W46: =Model_연결!P32 -> 0 | X46: =Model_연결!Q32 -> 12 | ... AB46: =Model_연결!U32 -> 0
B47: 영업이익률 | C47: =C46/C$40 -> 0.13187588 | D47: =D46/D$40 -> 0.085138827 | E47: =E46/E$40 -> 0.062270863 | F47: =F46/F$40 -> -0.24407416 | G47: =G46/G$40 -> -0.2482963 | H47: =H46/H$40 -> -0.31008899 | I47: =I46/I$40 -> -0.028425321 | J47: =J46/J$40 -> #DIV/0! | ... N47: =N46/N$40 -> #DIV/0! | P47: 영업이익률 | Q47: =Q46/Q$40 -> #DIV/0! | R47: =R46/R$40 -> #DIV/0! | S47: =S46/S$40 -> #DIV/0! | T47: =T46/T$40 -> #DIV/0! | U47: =U46/U$40 -> #DIV/0! | V47: =V46/V$40 -> #DIV/0! | W47: =W46/W$40 -> #DIV/0! | X47: =X46/X$40 -> 0.011417697 | ... AB47: =AB46/AB$40 -> #DIV/0!
B48: 영업외손익 | C48: =Model_별도!J44-Model_별도!J32 -> 4.08 | D48: =Model_별도!K44-Model_별도!K32 -> -26.92 | E48: =Model_별도!L44-Model_별도!L32 -> -27.1 | F48: =Model_별도!M44-Model_별도!M32 -> 0.06 | G48: =Model_별도!N44-Model_별도!N32 -> -273.84 | H48: =Model_별도!O44-Model_별도!O32 -> -18.54 | I48: =Model_별도!P44-Model_별도!P32 -> -18.39 | J48: =Model_별도!Q44-Model_별도!Q32 -> 0 | ... N48: =Model_별도!U44-Model_별도!U32 -> 0 | P48: 영업외손익 | Q48: =Model_연결!J44-Model_연결!J32 -> 0 | R48: =Model_연결!K44-Model_연결!K32 -> 0 | S48: =Model_연결!L44-Model_연결!L32 -> 0 | T48: =Model_연결!M44-Model_연결!M32 -> 0 | U48: =Model_연결!N44-Model_연결!N32 -> 0 | V48: =Model_연결!O44-Model_연결!O32 -> 0 | W48: =Model_연결!P44-Model_연결!P32 -> 0 | X48: =Model_연결!Q44-Model_연결!Q32 -> #DIV/0! | ... AB48: =Model_연결!U44-Model_연결!U32 -> 0
B49: 법인세비용차감전순손익 | C49: =Model_별도!J44 -> 69.53 | D49: =Model_별도!K44 -> 13.28 | E49: =Model_별도!L44 -> 18.76 | F49: =Model_별도!M44 -> -228.74 | G49: =Model_별도!N44 -> -489.17 | H49: =Model_별도!O44 -> -148.52 | I49: =Model_별도!P44 -> -32.62 | J49: =Model_별도!Q44 -> 0 | ... N49: =Model_별도!U44 -> 0 | P49: 법인세차감전순손익 | Q49: =Model_연결!J44 -> 0 | R49: =Model_연결!K44 -> 0 | S49: =Model_연결!L44 -> 0 | T49: =Model_연결!M44 -> 0 | U49: =Model_연결!N44 -> 0 | V49: =Model_연결!O44 -> 0 | W49: =Model_연결!P44 -> 0 | X49: =Model_연결!Q44 -> #DIV/0! | ... AB49: =Model_연결!U44 -> 0
B50: 법인세비용 | C50: =Model_별도!J46 -> 2.93 | D50: =Model_별도!K46 -> -13.37 | E50: =Model_별도!L46 -> -12.14 | F50: =Model_별도!M46 -> -62.19 | G50: =Model_별도!N46 -> 18 | H50: =Model_별도!O46 -> 25.83 | I50: =Model_별도!P46 -> 7.53 | J50: =Model_별도!Q46 -> -0.22 | ... N50: =Model_별도!U46 -> 0 | P50: 법인세비용 | Q50: =Model_연결!J46 -> 0 | R50: =Model_연결!K46 -> 0 | S50: =Model_연결!L46 -> 0 | T50: =Model_연결!M46 -> 0 | U50: =Model_연결!N46 -> 0 | V50: =Model_연결!O46 -> 0 | W50: =Model_연결!P46 -> 0 | X50: =Model_연결!Q46 -> #DIV/0! | ... AB50: =Model_연결!U46 -> 0
B51: 당기순이익 | C51: =Model_별도!J48 -> 66.6 | D51: =Model_별도!K48 -> 26.65 | E51: =Model_별도!L48 -> 30.9 | F51: =Model_별도!M48 -> -166.55 | G51: =Model_별도!N48 -> -507.17 | H51: =Model_별도!O48 -> -174.34 | I51: =Model_별도!P48 -> -40.15 | J51: =Model_별도!Q48 -> 0.22 | ... N51: =Model_별도!U48 -> 0 | P51: 당기순이익(지배) | Q51: =Model_연결!J52 -> 0 | R51: =Model_연결!K52 -> 0 | S51: =Model_연결!L52 -> 0 | T51: =Model_연결!M52 -> 0 | U51: =Model_연결!N52 -> 0 | V51: =Model_연결!O52 -> 0 | W51: =Model_연결!P52 -> 0 | X51: =Model_연결!Q52 -> #DIV/0! | ... AB51: =Model_연결!U52 -> 0
B52: 당기순이익률 | C52: =C51/C$40 -> 0.13419303 | D52: =D51/D$40 -> 0.056441536 | E52: =E51/E$40 -> 0.041957472 | F52: =F51/F$40 -> -0.17766849 | G52: =G51/G$40 -> -0.58481602 | H52: =H51/H$40 -> -0.41591717 | I52: =I51/I$40 -> -0.080202153 | J52: =J51/J$40 -> #DIV/0! | ... N52: =N51/N$40 -> #DIV/0! | P52: 당기순이익률 | Q52: =Q51/Q$40 -> #DIV/0! | R52: =R51/R$40 -> #DIV/0! | S52: =S51/S$40 -> #DIV/0! | T52: =T51/T$40 -> #DIV/0! | U52: =U51/U$40 -> #DIV/0! | V52: =V51/V$40 -> #DIV/0! | W52: =W51/W$40 -> #DIV/0! | X52: =X51/X$40 -> #DIV/0! | ... AB52: =AB51/AB$40 -> #DIV/0!
B53: EBITDA | C53: =Model_별도!J9 -> 202.87 | D53: =Model_별도!K9 -> 176.88 | E53: =Model_별도!L9 -> 189.75 | F53: =Model_별도!M9 -> -7.01 | G53: =Model_별도!N9 -> 3.94 | H53: =Model_별도!O9 -> -17.5 | I53: =Model_별도!P9 -> 44.11 | J53: =Model_별도!Q9 -> 116.42 | ... N53: =Model_별도!U9 -> 0 | P53: EBITDA | Q53: =Model_연결!J9 -> 0 | R53: =Model_연결!K9 -> 0 | S53: =Model_연결!L9 -> 0 | T53: =Model_연결!M9 -> 0 | U53: =Model_연결!N9 -> 0 | V53: =Model_연결!O9 -> 0 | W53: =Model_연결!P9 -> 0 | X53: =Model_연결!Q9 -> #DIV/0! | ... AB53: =Model_연결!U9 -> 0
B54: EBITDA이익률 | C54: =C53/C$40 -> 0.40876486 | D54: =D53/D$40 -> 0.37461084 | E54: =E53/E$40 -> 0.25765147 | F54: =F53/F$40 -> -0.0074779715 | G54: =G53/G$40 -> 0.0045432008 | H54: =H53/H$40 -> -0.041749171 | I54: =I53/I$40 -> 0.088112503 | J54: =J53/J$40 -> #DIV/0! | ... N54: =N53/N$40 -> #DIV/0! | P54: EBITDA이익률 | Q54: =Q53/Q$40 -> #DIV/0! | R54: =R53/R$40 -> #DIV/0! | S54: =S53/S$40 -> #DIV/0! | T54: =T53/T$40 -> #DIV/0! | U54: =U53/U$40 -> #DIV/0! | V54: =V53/V$40 -> #DIV/0! | W54: =W53/W$40 -> #DIV/0! | X54: =X53/X$40 -> #DIV/0! | ... AB54: =AB53/AB$40 -> #DIV/0!
B56: 현금흐름표 | C56: =C6 -> 2020 | D56: =D6 -> 2021 | E56: =E6 -> 2022 | F56: =F6 -> 2023 | G56: =G6 -> 2024 | H56: =H6 -> 24.2Q | I56: =I6 -> 25.2Q | J56: =J6 -> 2025E | ... N56: =N6 -> 0 | P56: 현금흐름표 | Q56: =Q6 -> 2020 | R56: =R6 -> 2021 | S56: =S6 -> 2022 | T56: =T6 -> 2023 | U56: =U6 -> 2024 | V56: =V6 -> 24.2Q | W56: =W6 -> 25.2Q | X56: =X6 -> 2025E | ... AB56: =AB6 -> 0
B57: 당기순이익 | C57: =Model_별도!J152 -> 66.6 | D57: =Model_별도!K152 -> 26.65 | E57: =Model_별도!L152 -> 30.9 | F57: =Model_별도!M152 -> -166.55 | G57: =Model_별도!N152 -> -507.17 | H57: =Model_별도!O152 -> -174.34 | I57: =Model_별도!P152 -> -40.15 | J57: =Model_별도!Q152 -> 0 | ... N57: =Model_별도!U152 -> 0 | P57: 당기순이익 | Q57: =Model_연결!J152 -> 0 | R57: =Model_연결!K152 -> 0 | S57: =Model_연결!L152 -> 0 | T57: =Model_연결!M152 -> 0 | U57: =Model_연결!N152 -> 0 | V57: =Model_연결!O152 -> 0 | W57: =Model_연결!P152 -> 0 | X57: =Model_연결!Q152 -> 12 | ... AB57: =Model_연결!U152 -> 0
B58: 상각비 | C58: =Model_별도!J153 -> 137.42 | D58: =Model_별도!K153 -> 136.68 | E58: =Model_별도!L153 -> 143.89 | F58: =Model_별도!M153 -> 221.79 | G58: =Model_별도!N153 -> 219.27 | H58: =Model_별도!O153 -> 112.48 | I58: =Model_별도!P153 -> 58.34 | J58: =Model_별도!Q153 -> 116.42 | ... N58: =Model_별도!U153 -> 0 | P58: 상각비 | Q58: =Model_연결!J153 -> 0 | R58: =Model_연결!K153 -> 0 | S58: =Model_연결!L153 -> 0 | T58: =Model_연결!M153 -> 0 | U58: =Model_연결!N153 -> 0 | V58: =Model_연결!O153 -> 0 | W58: =Model_연결!P153 -> 0 | X58: =Model_연결!Q153 -> #DIV/0! | ... AB58: =Model_연결!U153 -> 0
B59: WC변동 | C59: =Model_별도!J157 -> 20.89 | D59: =Model_별도!K157 -> -33.38 | E59: =Model_별도!L157 -> -128.7 | F59: =Model_별도!M157 -> -19.69 | G59: =Model_별도!N157 -> 35.45 | H59: =Model_별도!O157 -> -7.78 | I59: =Model_별도!P157 -> -1.47 | J59: =Model_별도!Q157 -> 66.88 | ... N59: =Model_별도!U157 -> 0 | P59: WC변동 | Q59: =Model_연결!J157 -> 0 | R59: =Model_연결!K157 -> 0 | S59: =Model_연결!L157 -> 0 | T59: =Model_연결!M157 -> 0 | U59: =Model_연결!N157 -> 0 | V59: =Model_연결!O157 -> 0 | W59: =Model_연결!P157 -> 0 | X59: =Model_연결!Q157 -> #DIV/0! | ... AB59: =Model_연결!U157 -> 0
B60: 순이자지급 | C60: =Model_별도!J164+Model_별도!J163 -> -22 | D60: =Model_별도!K164+Model_별도!K163 -> -12.95 | E60: =Model_별도!L164+Model_별도!L163 -> -8.3 | F60: =Model_별도!M164+Model_별도!M163 -> -35.33 | G60: =Model_별도!N164+Model_별도!N163 -> -38.5 | H60: =Model_별도!O164+Model_별도!O163 -> -18.73 | I60: =Model_별도!P164+Model_별도!P163 -> -18.31 | J60: =Model_별도!Q164+Model_별도!Q163 -> 0 | ... N60: =Model_별도!U164+Model_별도!U163 -> 0 | P60: 순이자지급 | Q60: =Model_연결!J164+Model_연결!J163 -> 0 | R60: =Model_연결!K164+Model_연결!K163 -> 0 | S60: =Model_연결!L164+Model_연결!L163 -> 0 | T60: =Model_연결!M164+Model_연결!M163 -> 0 | U60: =Model_연결!N164+Model_연결!N163 -> 0 | V60: =Model_연결!O164+Model_연결!O163 -> 0 | W60: =Model_연결!P164+Model_연결!P163 -> 0 | X60: =Model_연결!Q164+Model_연결!Q163 -> #DIV/0! | ... AB60: =Model_연결!U164+Model_연결!U163 -> 0
B61: 법인세지급 | C61: =Model_별도!J167 -> -4.75 | D61: =Model_별도!K167 -> -3.26 | E61: =Model_별도!L167 -> 0 | F61: =Model_별도!M167 -> -0.39 | G61: =Model_별도!N167 -> -0.01 | H61: =Model_별도!O167 -> 0 | I61: =Model_별도!P167 -> -0.23 | J61: =Model_별도!Q167 -> 0.22 | ... N61: =Model_별도!U167 -> 0 | P61: 법인세지급 | Q61: =Model_연결!J167 -> 0 | R61: =Model_연결!K167 -> 0 | S61: =Model_연결!L167 -> 0 | T61: =Model_연결!M167 -> 0 | U61: =Model_연결!N167 -> 0 | V61: =Model_연결!O167 -> 0 | W61: =Model_연결!P167 -> 0 | X61: =Model_연결!Q167 -> #DIV/0! | ... AB61: =Model_연결!U167 -> 0
B62: 영업활동으로인한현금흐름 | C62: =Model_별도!J169 -> 206.06 | D62: =Model_별도!K169 -> 139.38 | E62: =Model_별도!L169 -> 69.33 | F62: =Model_별도!M169 -> -5.93 | G62: =Model_별도!N169 -> 5.74 | H62: =Model_별도!O169 -> -30.63 | I62: =Model_별도!P169 -> 30.26 | J62: =Model_별도!Q169 -> 183.52 | ... N62: =Model_별도!U169 -> 0 | P62: 영업CF | Q62: =Model_연결!J169 -> 0 | R62: =Model_연결!K169 -> 0 | S62: =Model_연결!L169 -> 0 | T62: =Model_연결!M169 -> 0 | U62: =Model_연결!N169 -> 0 | V62: =Model_연결!O169 -> 0 | W62: =Model_연결!P169 -> 0 | X62: =Model_연결!Q169 -> #DIV/0! | ... AB62: =Model_연결!U169 -> 0
B63: CapEx | C63: =Model_별도!J170+Model_별도!J171 -> -120.53 | D63: =Model_별도!K170+Model_별도!K171 -> -10.93 | E63: =Model_별도!L170+Model_별도!L171 -> -79.42 | F63: =Model_별도!M170+Model_별도!M171 -> -187.89 | G63: =Model_별도!N170+Model_별도!N171 -> -122.04 | H63: =Model_별도!O170+Model_별도!O171 -> -33.71 | I63: =Model_별도!P170+Model_별도!P171 -> -37.14 | J63: =Model_별도!Q170+Model_별도!Q171 -> -10.28 | ... N63: =Model_별도!U170+Model_별도!U171 -> 0 | P63: CapEx | Q63: =Model_연결!J170+Model_연결!J171 -> 0 | R63: =Model_연결!K170+Model_연결!K171 -> 0 | S63: =Model_연결!L170+Model_연결!L171 -> 0 | T63: =Model_연결!M170+Model_연결!M171 -> 0 | U63: =Model_연결!N170+Model_연결!N171 -> 0 | V63: =Model_연결!O170+Model_연결!O171 -> 0 | W63: =Model_연결!P170+Model_연결!P171 -> 0 | X63: =Model_연결!Q170+Model_연결!Q171 -> #DIV/0! | ... AB63: =Model_연결!U170+Model_연결!U171 -> 0
B64: 지분투자 | C64: =Model_별도!J172 -> 0 | D64: =Model_별도!K172 -> 0 | E64: =Model_별도!L172 -> 0 | F64: =Model_별도!M172 -> 0 | G64: =Model_별도!N172 -> 0 | H64: =Model_별도!O172 -> 0 | I64: =Model_별도!P172 -> 0 | J64: =Model_별도!Q172 -> 0 | ... N64: =Model_별도!U172 -> 0 | P64: 지분투자 | Q64: =Model_연결!J172 -> 0 | R64: =Model_연결!K172 -> 0 | S64: =Model_연결!L172 -> 0 | T64: =Model_연결!M172 -> 0 | U64: =Model_연결!N172 -> 0 | V64: =Model_연결!O172 -> 0 | W64: =Model_연결!P172 -> 0 | X64: =Model_연결!Q172 -> 0 | ... AB64: =Model_연결!U172 -> 0
B65: 투자활동으로인한현금흐름 | C65: =Model_별도!J174 -> -120.72 | D65: =Model_별도!K174 -> 7.57 | E65: =Model_별도!L174 -> -791.64 | F65: =Model_별도!M174 -> -173.31 | G65: =Model_별도!N174 -> -106.23 | H65: =Model_별도!O174 -> -34.17 | I65: =Model_별도!P174 -> -36.89 | J65: =Model_별도!Q174 -> -10.28 | ... N65: =Model_별도!U174 -> 0 | P65: 투자CF | Q65: =Model_연결!J174 -> 0 | R65: =Model_연결!K174 -> 0 | S65: =Model_연결!L174 -> 0 | T65: =Model_연결!M174 -> 0 | U65: =Model_연결!N174 -> 0 | V65: =Model_연결!O174 -> 0 | W65: =Model_연결!P174 -> 0 | X65: =Model_연결!Q174 -> #DIV/0! | ... AB65: =Model_연결!U174 -> 0
B66: 차입금순증 | C66: =Model_별도!J180 -> -50 | D66: =Model_별도!K180 -> -100 | E66: =Model_별도!L180 -> 321.25 | F66: =Model_별도!M180 -> 230 | G66: =Model_별도!N180 -> -46 | H66: =Model_별도!O180 -> 10 | I66: =Model_별도!P180 -> -47 | J66: =Model_별도!Q180 -> 0 | ... N66: =Model_별도!U180 -> 0 | P66: 차입금순증 | Q66: =Model_연결!J180 -> 0 | R66: =Model_연결!K180 -> 0 | S66: =Model_연결!L180 -> 0 | T66: =Model_연결!M180 -> 0 | U66: =Model_연결!N180 -> 0 | V66: =Model_연결!O180 -> 0 | W66: =Model_연결!P180 -> 0 | X66: =Model_연결!Q180 -> 200 | ... AB66: =Model_연결!U180 -> 0
B67: 재무활동으로인한현금흐름 | C67: =Model_별도!J198 -> -53.39 | D67: =Model_별도!K198 -> -136.88 | E67: =Model_별도!L198 -> 718.7 | F67: =Model_별도!M198 -> 214.55 | G67: =Model_별도!N198 -> 24.38 | H67: =Model_별도!O198 -> 88.19 | I67: =Model_별도!P198 -> -52.19 | J67: =Model_별도!Q198 -> 0 | ... N67: =Model_별도!U198 -> 0 | P67: 재무CF | Q67: =Model_연결!J198 -> 0 | R67: =Model_연결!K198 -> 0 | S67: =Model_연결!L198 -> 0 | T67: =Model_연결!M198 -> 0 | U67: =Model_연결!N198 -> 0 | V67: =Model_연결!O198 -> 0 | W67: =Model_연결!P198 -> 0 | X67: =Model_연결!Q198 -> 200 | ... AB67: =Model_연결!U198 -> 0
B68: 현금순증 | C68: =Model_별도!J202 -> 31.95 | D68: =Model_별도!K202 -> 10.07 | E68: =Model_별도!L202 -> -3.77 | F68: =Model_별도!M202 -> 35.31 | G68: =Model_별도!N202 -> -75.77 | H68: =Model_별도!O202 -> 23.39 | I68: =Model_별도!P202 -> -59.28 | J68: =Model_별도!Q202 -> 173.24 | ... N68: =Model_별도!U202 -> 0 | P68: 현금순증 | Q68: =Model_연결!J202 -> 0 | R68: =Model_연결!K202 -> 0 | S68: =Model_연결!L202 -> 0 | T68: =Model_연결!M202 -> 0 | U68: =Model_연결!N202 -> 0 | V68: =Model_연결!O202 -> 0 | W68: =Model_연결!P202 -> 0 | X68: =Model_연결!Q202 -> #DIV/0! | ... AB68: =Model_연결!U202 -> 0
B69: 기말현금및현금성자산 | C69: =Model_별도!J204 -> 175.76 | D69: =Model_별도!K204 -> 185.83 | E69: =Model_별도!L204 -> 182.06 | F69: =Model_별도!M204 -> 217.37 | G69: =Model_별도!N204 -> 141.6 | H69: =Model_별도!O204 -> 240.75 | I69: =Model_별도!P204 -> 82.32 | J69: =Model_별도!Q204 -> 314.84 | ... N69: =Model_별도!U204 -> 0 | P69: 기말현금 | Q69: =Model_연결!J204 -> 0 | R69: =Model_연결!K204 -> 0 | S69: =Model_연결!L204 -> 0 | T69: =Model_연결!M204 -> 0 | U69: =Model_연결!N204 -> 0 | V69: =Model_연결!O204 -> 0 | W69: =Model_연결!P204 -> 0 | X69: =Model_연결!Q204 -> #DIV/0! | ... AB69: =Model_연결!U204 -> 0

Sheet 총괄장표
B2: 1. 재무지표 | C2: 연결
G4: AAA | H4: AA | I4: A | J4: BBB | K4: BB | L4: BB↓
D5: 수치 | E5: 비중 | F5: 점수 | G5: 10 | H5: 9 | I5: 8 | J5: 7 | K5: 5 | L5: 3
B6: 규모 | C6: 매출액(3년 평균) | D6: =IF($C$2="연결",AVERAGE(Model_연결!L4:N4),AVERAGE(Model_별도!L4:N4)) -> 0 | E6: 0.15 | F6: =IF(D6>=15000,$G$5,IF(D6>=10000,$H$5,IF(D6>=5000,$I$5,IF(D6>=1000,$J$5,IF(D6>=500,$K$5,$L$5))))) -> 3 | G6: ≥15000 | H6: ≥10000 | I6: ≥5000 | J6: ≥1000 | K6: ≥500 | L6: <500
B7: 수익성지표 | C7: 영업이익률(3년 평균) | D7: =IF($C$2="연결",SUM(Model_연결!L6:N6)/SUM(Model_연결!L4:N4),SUM(Model_별도!L6:N6)/SUM(Model_별도!L4:N4)) -> #DIV/0! | E7: 0.15 | F7: =IF(D7>=0.12,$G$5,IF(D7>=0.08,$H$5,IF(D7>=0.05,$I$5,IF(D7>=0.03,$J$5,IF(D7>=0,$K$5,$L$5))))) -> #DIV/0! | G7: ≥12% | H7: ≥8% | I7: ≥5% | J7: ≥3% | K7: ≥0% | L7: <0%
C8: EBITDA마진율(3년 평균) | D8: =IF($C$2="연결",SUM(Model_연결!L9:N9)/SUM(Model_연결!L4:N4),SUM(Model_별도!L9:N9)/SUM(Model_별도!L4:N4)) -> #DIV/0! | E8: 0.15 | F8: =IF(D8>=0.2,$G$5,IF(D8>=0.15,$H$5,IF(D8>=0.08,$I$5,IF(D8>=0.06,$J$5,IF(D8>=0.02,$K$5,$L$5))))) -> #DIV/0! | G8: ≥20% | H8: ≥15% | I8: ≥8% | J8: ≥6% | K8: ≥2% | L8: <2%
B9: 안정성지표 | C9: 자본금(최신) | D9: =IF($C$2="연결",Model_연결!P131,Model_별도!P131) -> 0 | E9: 0.05 | F9: =IF(D9>=5000,$G$5,IF(D9>=3000,$H$5,IF(D9>=2000,$I$5,IF(D9>=1000,$J$5,IF(D9>=400,$K$5,$L$5))))) -> 3 | G9: ≥5000 | H9: ≥3000 | I9: ≥2000 | J9: ≥1000 | K9: ≥400 | L9: <400
C10: 부채비율(최신) | D10: =IF($C$2="연결",Model_연결!P18,Model_별도!P18) -> #DIV/0! | E10: 0.1 | F10: =IF(D10<0.4,$G$5,IF(D10<1,$H$5,IF(D10<1.4,$I$5,IF(D10<1.8,$J$5,IF(D10<2.5,$K$5,$L$5))))) -> #DIV/0! | G10: <40% | H10: <100% | I10: <140% | J10: <180% | K10: <250% | L10: ≥250%
C11: 총차입금의존도(최신) | D11: =IF($C$2="연결",Model_연결!P12/Model_연결!P11,Model_별도!P12/Model_별도!P11) -> #DIV/0! | E11: 0.1 | F11: =IF(D11<0.1,$G$5,IF(D11<0.2,$H$5,IF(D11<0.3,$I$5,IF(D11<0.4,$J$5,IF(D11<0.5,$K$5,$L$5))))) -> #DIV/0! | G11: <10% | H11: <20% | I11: <30% | J11: <40% | K11: <50% | L11: ≥50%
C12: 운전자산 회전기일(매출액, 3년 평균) | D12: =IF($C$2="연결",AVERAGE(Model_연결!L72:N72)+AVERAGE(Model_연결!L78:N78),AVERAGE(Model_별도!L72:N72)+AVERAGE(Model_별도!L78:N78)) -> #DIV/0! | E12: 0.1 | F12: =IF(D12<80,$G$5,IF(D12<120,$H$5,IF(D12<150,$I$5,IF(D12<180,$J$5,IF(D12<200,$K$5,$L$5))))) -> #DIV/0! | G12: <80 | H12: <120 | I12: <150 | J12: <180 | K12: <200 | L12: ≥200
C13: EBITDA/이자비용(3년 평균) | D13: =IF($C$2="연결",SUM(Model_연결!L9:N9)/SUM(Model_연결!L40:N40),SUM(Model_별도!L9:N9)/SUM(Model_별도!L40:N40)) -> #DIV/0! | E13: 0.1 | F13: =IF(D13>=10,$G$5,IF(D13>=8,$H$5,IF(D13>=6,$I$5,IF(D13>=4,$J$5,IF(D13>=2,$K$5,$L$5))))) -> #DIV/0! | G13: ≥10 | H13: ≥8 | I13: ≥6 | J13: ≥4 | K13: ≥2 | L13: <2
C14: 순차입금(최신)/EBITDA(3년 평균) | D14: =IF($C$2="연결",IF(AVERAGE(Model_연결!L9:N9)<0,"음(-)의 EBITDA",Model_연결!P14/AVERAGE(Model_연결!L9:N9)),IF(AVERAGE(Model_연결!L9:N9)<0,"음(-)의 EBITDA",Model_별도!P14/AVERAGE(Model_별도!L9:N9))) -> #DIV/0! | E14: 0.1 | F14: =IF(D14<0.5,$G$5,IF(D14<2,$H$5,IF(D14<4,$I$5,IF(D14<6,$J$5,IF(D14<8,$K$5,$L$5))))) -> #DIV/0! | G14: <0.5 | H14: <2 | I14: <4 | J14: <6 | K14: <8 | L14: ≥8
E15: =SUM(E6:E14) -> 1 | F15: =SUMPRODUCT(E6:E14,F6:F14) -> #DIV/0!
B16: 2. 시가총액 | D16: =PEER!E14 -> 2111.75
B18: 3. 최근 2개연도 영업손익 | D18: '23년 | E18: '24년
D19: =IF($C$2="연결",Model_연결!M6,Model_별도!M6) -> 0 | E19: =IF($C$2="연결",Model_연결!N6,Model_별도!N6) -> 0
B21: 4. 금회차 포함 주식연계채권 발행 규모와 비율 | D21: 200 | E21: =D21/D16 -> 0.09470818
B23: 5. 대주주 리스크 | D23: 강승모 대표가 최대주주로 지분율 33.3% (특관자 계 49.5%로 지배구조 안정적). 3년내 대주주 변경 없음
C25: 주가 | F25: =주가!D15 -> 4985
C26: 120일 일평균 거래대금(억원) | F26: =PEER!CZ14/100000000 -> 15.949113
C27: 1년 중 최고 주가 | F27: =PEER!CX14 -> 1710
C28: 1년 중 최저 주가 | F28: =PEER!CY14 -> 5820

Sheet Model_별도
B1: =B3&" Financial Statements" -> 별도 Financial Statements
B2: (억원, except per share data) | D2: 18 | E2: =D2+1 -> 19 | F2: =E2+1 -> 20 | G2: =F2+1 -> 21 | H2: =G2+1 -> 22 | I2: =H2+1 -> 23 | J2: =I2+1 -> 24 | K2: =J2+1 -> 25 | L2: =K2+1 -> 26 | ... N2: =M2+1 -> 28 | O2: 65 | P2: =O2+4 -> 69 | Q2: 지우지마시오 (Vlookup 열순서)
B3: 별도 | C3: 과목코드 | D3: 2014 | E3: =D3+1 -> 2015 | F3: =E3+1 -> 2016 | G3: =F3+1 -> 2017 | H3: =G3+1 -> 2018 | I3: =H3+1 -> 2019 | J3: =I3+1 -> 2020 | K3: =J3+1 -> 2021 | L3: =K3+1 -> 2022 | ... N3: =M3+1 -> 2024 | O3: 2024.2Q | P3: 2025.2Q | Q3: 2025E | R3: 2026E | S3: 2027E | T3: 2028E
B4: 매출액 | D4: =D22 -> 315.19 | E4: =E22 -> 216.49 | F4: =F22 -> 158.78 | G4: =G22 -> 226.43 | H4: =H22 -> 471.15 | I4: =I22 -> 468.41 | J4: =J22 -> 496.3 | K4: =K22 -> 472.17 | ... S4: =S22 -> 0
B5: 매출성장률 | E5: =E4/D4-1 -> -0.31314445 | F5: =F4/E4-1 -> -0.2665712 | G5: =G4/F4-1 -> 0.42606122 | H5: =H4/G4-1 -> 1.0807755 | I5: =I4/H4-1 -> -0.0058155577 | J5: =J4/I4-1 -> 0.059541854 | K5: =K4/J4-1 -> -0.048619786 | L5: =L4/K4-1 -> 0.55973484 | ... N5: =N4/M4-1 -> -0.074875723 | P5: =P4/O4-1 -> 0.19428871 | Q5: =Q4/N4-1 -> -1 | R5: =R4/Q4-1 -> #DIV/0! | S5: =S4/R4-1 -> #DIV/0!
B6: 영업이익 | D6: =D32 -> 23.15 | E6: =E32 -> -41.64 | F6: =F32 -> -34.39 | G6: =G32 -> 19.47 | H6: =H32 -> 159.82 | I6: =I32 -> 81.68 | J6: =J32 -> 65.45 | K6: =K32 -> 40.2 | ... S6: =S32 -> 0
B7: 영업이익률 | D7: =D6/D4 -> 0.073447762 | E7: =E6/E4 -> -0.19234145 | F7: =F6/F4 -> -0.21658899 | G7: =G6/G4 -> 0.085986839 | H7: =H6/H4 -> 0.33921257 | I7: =I6/I4 -> 0.17437715 | J7: =J6/J4 -> 0.13187588 | K7: =K6/K4 -> 0.085138827 | ... S7: =S6/S4 -> #DIV/0!
B8: 당기순이익 | D8: =D52 -> 29.61 | E8: =E52 -> -21.29 | F8: =F52 -> -36.84 | G8: =G52 -> 8.63 | H8: =H52 -> 148.18 | I8: =I52 -> 41.89 | J8: =J52 -> 66.6 | K8: =K52 -> 26.65 | ... S8: =S52 -> 0.22
B9: EBITDA | D9: =D250 -> 164.22 | E9: =E250 -> 63.16 | F9: =F250 -> 41.57 | G9: =G250 -> 87.18 | H9: =H250 -> 284.7 | I9: =I250 -> 221.91 | J9: =J250 -> 202.87 | K9: =K250 -> 176.88 | ... S9: =S250 -> 71.712538
B10: EBITDA/매출액 | D10: =D9/D4 -> 0.52101907 | E10: =E9/E4 -> 0.29174558 | F10: =F9/F4 -> 0.26180879 | G10: =G9/G4 -> 0.38501965 | H10: =H9/H4 -> 0.60426616 | I10: =I9/I4 -> 0.47375163 | J10: =J9/J4 -> 0.40876486 | K10: =K9/K4 -> 0.37461084 | ... S10: =S9/S4 -> #DIV/0!
B11: 자산총계 | D11: =D97 -> 638.62 | E11: =E97 -> 571.5 | F11: =F97 -> 494.14 | G11: =G97 -> 688.91 | H11: =H97 -> 1231.62 | I11: =I97 -> 1274.09 | J11: =J97 -> 1304.24 | K11: =K97 -> 1160.61 | ... S11: =S97 -> 1574.16
B12: 부동산(토지+건물) | D12: =D82+D84+D85 -> 179.17 | E12: =E82+E84+E85 -> 174.77 | F12: =F82+F84+F85 -> 170.37 | G12: =G82+G84+G85 -> 165.97 | H12: =H82+H84+H85 -> 191.11 | I12: =I82+I84+I85 -> 460.91 | J12: =J82+J84+J85 -> 447.86 | K12: =K82+K84+K85 -> 425.41 | ... S12: =S82+S84+S85 -> 665.73
B13: 총차입금 | D13: =D105+D114 -> 158 | E13: =E105+E114 -> 118.25 | F13: =F105+F114 -> 78.5 | G13: =G105+G114 -> 238.75 | H13: =H105+H114 -> 540.45 | I13: =I105+I114 -> 598.55 | J13: =J105+J114 -> 551.95 | K13: =K105+K114 -> 413.75 | ... S13: =S105+S114 -> 919
B14: 순차입금 | D14: =D105+D114-D62-D63-D90 -> -13.47 | E14: =E105+E114-E62-E63-E90 -> -64.05 | F14: =F105+F114-F62-F63-F90 -> -120.9 | G14: =G105+G114-G62-G63-G90 -> 24.78 | H14: =H105+H114-H62-H63-H90 -> 198.91 | I14: =I105+I114-I62-I63-I90 -> 447.22 | J14: =J105+J114-J62-J63-J90 -> 374.16 | K14: =K105+K114-K62-K63-K90 -> 223.74 | ... S14: =S105+S114-S62-S63-S90 -> 466.66796
B15: OCF | D15: =D169 -> 157.94 | E15: =E169 -> 53.7 | F15: =F169 -> 47.49 | G15: =G169 -> 71.17 | H15: =H169 -> 289.72 | I15: =I169 -> 160.69 | J15: =J169 -> 206.06 | K15: =K169 -> 139.38 | ... S15: =S169 -> 71.932538
B16: 유무형자산투자 | D16: =D170+D171 -> -20.59 | E16: =E170+E171 -> -31.16 | F16: =F170+F171 -> -2.02 | G16: =G170+G171 -> -228.33 | H16: =H170+H171 -> -496.7 | I16: =I170+I171 -> -396.35 | J16: =J170+J171 -> -120.53 | K16: =K170+K171 -> -10.93 | ... S16: =S170+S171 -> -10.28
B17: 순차입금/EBITDA | D17: =D14/D9 -> -0.082024114 | E17: =E14/E9 -> -1.0140912 | F17: =F14/F9 -> -2.9083474 | G17: =G14/G9 -> 0.2842395 | H17: =H14/H9 -> 0.69866526 | I17: =I14/I9 -> 2.0153215 | J17: =J14/J9 -> 1.8443338 | K17: =K14/K9 -> 1.2649254 | ... N17: =N14/N9 -> 197.15736 | O17: =O14/(O9*IF(RIGHT(O$3,2)="1Q",4,IF(RIGHT(O$3,2)="2Q",2,IF(RIGHT(O$3,2)="3Q",4/3,"0")))) -> -20.890571 | P17: =P14/(P9*IF(RIGHT(P$3,2)="1Q",4,IF(RIGHT(P$3,2)="2Q",2,IF(RIGHT(P$3,2)="3Q",4/3,"0")))) -> 8.9464974 | Q17: =Q14/Q9 -> 5.1843326 | R17: =R14/R9 -> 6.1937116 | S17: =S14/S9 -> 6.5074808
B18: 부채비율 | D18: =D123/D131 -> 0.38472213 | E18: =E123/E131 -> 0.30249783 | F18: =F123/F131 -> 0.22987705 | G18: =G123/G131 -> 0.68780165 | H18: =H123/H131 -> 1.1775845 | I18: =I123/I131 -> 1.0984255 | J18: =J123/J131 -> 0.93941917 | K18: =K123/K131 -> 0.63715229 | ... S18: =S123/S131 -> 1.8464793
B19: 차입금의존도 | D19: =(D105+D114)/D97 -> 0.24740847 | E19: =(E105+E114)/E97 -> 0.20691164 | F19: =(F105+F114)/F97 -> 0.15886186 | G19: =(G105+G114)/G97 -> 0.34656196 | H19: =(H105+H114)/H97 -> 0.4388123 | I19: =(I105+I114)/I97 -> 0.46978628 | J19: =(J105+J114)/J97 -> 0.42319665 | K19: =(K105+K114)/K97 -> 0.35649357 | ... S19: =(S105+S114)/S97 -> 0.58380343
B21: INCOME STATEMENT (억원) | D21: =D$3 -> 2014 | E21: =E$3 -> 2015 | F21: =F$3 -> 2016 | G21: =G$3 -> 2017 | H21: =H$3 -> 2018 | I21: =I$3 -> 2019 | J21: =J$3 -> 2020 | K21: =K$3 -> 2021 | ... S21: =S$3 -> 2027E
B22: 매출액(수익) | C22: A200000.IP | D22: =IFERROR(VLOOKUP($C22,FS_별도!$A:$AL,D$2,FALSE),0) -> 315.19 | E22: =IFERROR(VLOOKUP($C22,FS_별도!$A:$AL,E$2,FALSE),0) -> 216.49 | F22: =IFERROR(VLOOKUP($C22,FS_별도!$A:$AL,F$2,FALSE),0) -> 158.78 | G22: =IFERROR(VLOOKUP($C22,FS_별도!$A:$AL,G$2,FALSE),0) -> 226.43 | H22: =IFERROR(VLOOKUP($C22,FS_별도!$A:$AL,H$2,FALSE),0) -> 471.15 | I22: =IFERROR(VLOOKUP($C22,FS_별도!$A:$AL,I$2,FALSE),0) -> 468.41 | J22: =IFERROR(VLOOKUP($C22,FS_별도!$A:$AL,J$2,FALSE),0) -> 496.3 | K22: =IFERROR(VLOOKUP($C22,FS_별도!$A:$AL,K$2,FALSE),0) -> 472.17 | ... N22: =IFERROR(VLOOKUP($C22,FS_별도!$A:$AL,N$2,FALSE),0) -> 867.23 | O22: =IFERROR(VLOOKUP($C22,'FS_별도(분기누적)'!$A:$BS,O$2,FALSE),0) -> 419.17 | P22: =IFERROR(VLOOKUP($C22,'FS_별도(분기누적)'!$A:$BS,P$2,FALSE),0) -> 500.61
B23: Growth (%) | D23: - | E23: =E22/D22-1 -> -0.31314445 | F23: =F22/E22-1 -> -0.2665712 | G23: =G22/F22-1 -> 0.42606122 | H23: =H22/G22-1 -> 1.0807755 | I23: =I22/H22-1 -> -0.0058155577 | J23: =J22/I22-1 -> 0.059541854 | K23: =K22/J22-1 -> -0.048619786 | L23: =L22/K22-1 -> 0.55973484 | ... N23: =N22/M22-1 -> -0.074875723 | P23: =P22/O22-1 -> 0.19428871 | Q23: =Q22/N22-1 -> -1 | R23: =R22/Q22-1 -> #DIV/0! | S23: =S22/R22-1 -> #DIV/0!
B24: 매출원가 | C24: A200360.IP | D24: =IFERROR(VLOOKUP($C24,FS_별도!$A:$AL,D$2,FALSE),0) -> 267.65 | E24: =IFERROR(VLOOKUP($C24,FS_별도!$A:$AL,E$2,FALSE),0) -> 231.42 | F24: =IFERROR(VLOOKUP($C24,FS_별도!$A:$AL,F$2,FALSE),0) -> 172.73 | G24: =IFERROR(VLOOKUP($C24,FS_별도!$A:$AL,G$2,FALSE),0) -> 183.02 | H24: =IFERROR(VLOOKUP($C24,FS_별도!$A:$AL,H$2,FALSE),0) -> 281.35 | I24: =IFERROR(VLOOKUP($C24,FS_별도!$A:$AL,I$2,FALSE),0) -> 331.72 | J24: =IFERROR(VLOOKUP($C24,FS_별도!$A:$AL,J$2,FALSE),0) -> 396.91 | K24: =IFERROR(VLOOKUP($C24,FS_별도!$A:$AL,K$2,FALSE),0) -> 399.21 | ... N24: =IFERROR(VLOOKUP($C24,FS_별도!$A:$AL,N$2,FALSE),0) -> 1022.3 | O24: =IFERROR(VLOOKUP($C24,'FS_별도(분기누적)'!$A:$BS,O$2,FALSE),0) -> 520.12 | P24: =IFERROR(VLOOKUP($C24,'FS_별도(분기누적)'!$A:$BS,P$2,FALSE),0) -> 489.32 | Q24: =Q22-Q26 -> 0 | R24: =R22-R26 -> 0 | S24: =S22-S26 -> 0
B25: % of sales | D25: =D24/D22 -> 0.84917034 | E25: =E24/E22 -> 1.0689639 | F25: =F24/F22 -> 1.0878574 | G25: =G24/G22 -> 0.80828512 | H25: =H24/H22 -> 0.5971559 | I25: =I24/I22 -> 0.708183 | J25: =J24/J22 -> 0.79973806 | K25: =K24/K22 -> 0.84547938 | ... S25: =S24/S22 -> #DIV/0!
B26: 매출총이익 | D26: =D22-D24 -> 47.54 | E26: =E22-E24 -> -14.93 | F26: =F22-F24 -> -13.95 | G26: =G22-G24 -> 43.41 | H26: =H22-H24 -> 189.8 | I26: =I22-I24 -> 136.69 | J26: =J22-J24 -> 99.39 | K26: =K22-K24 -> 72.96 | ... P26: =P22-P24 -> 11.29 | Q26: =Q32+Q28+Q30 -> 0 | R26: =R32+R28+R30 -> 0 | S26: =S32+S28+S30 -> 0
B27: Gross margin (%) | D27: =D26/D22 -> 0.15082966 | E27: =E26/E22 -> -0.068963924 | F27: =F26/F22 -> -0.087857413 | G27: =G26/G22 -> 0.19171488 | H27: =H26/H22 -> 0.4028441 | I27: =I26/I22 -> 0.291817 | J27: =J26/J22 -> 0.20026194 | K27: =K26/K22 -> 0.15452062 | ... S27: =S26/S22 -> #DIV/0!
B28: 연구개발비 | C28: A201130.IP | D28: =IFERROR(VLOOKUP($C28,FS_별도!$A:$AL,D$2,FALSE),0) -> 0 | E28: =IFERROR(VLOOKUP($C28,FS_별도!$A:$AL,E$2,FALSE),0) -> 0 | F28: =IFERROR(VLOOKUP($C28,FS_별도!$A:$AL,F$2,FALSE),0) -> 0 | G28: =IFERROR(VLOOKUP($C28,FS_별도!$A:$AL,G$2,FALSE),0) -> 0 | H28: =IFERROR(VLOOKUP($C28,FS_별도!$A:$AL,H$2,FALSE),0) -> 0 | I28: =IFERROR(VLOOKUP($C28,FS_별도!$A:$AL,I$2,FALSE),0) -> 0 | J28: =IFERROR(VLOOKUP($C28,FS_별도!$A:$AL,J$2,FALSE),0) -> 0 | K28: =IFERROR(VLOOKUP($C28,FS_별도!$A:$AL,K$2,FALSE),0) -> 0 | ... N28: =IFERROR(VLOOKUP($C28,FS_별도!$A:$AL,N$2,FALSE),0) -> 0 | O28: =IFERROR(VLOOKUP($C28,'FS_별도(분기누적)'!$A:$BS,O$2,FALSE),0) -> 0 | P28: =IFERROR(VLOOKUP($C28,'FS_별도(분기누적)'!$A:$BS,P$2,FALSE),0) -> 0 | Q28: =Q29*Q22 -> 0 | R28: =R29*R22 -> 0 | S28: =S29*S22 -> 0
B29: % of sales | D29: =D28/D22 -> 0 | E29: =E28/E22 -> 0 | F29: =F28/F22 -> 0 | G29: =G28/G22 -> 0 | H29: =H28/H22 -> 0 | I29: =I28/I22 -> 0 | J29: =J28/J22 -> 0 | K29: =K28/K22 -> 0 | ... P29: =P28/P22 -> 0 | Q29: =N29 -> 0 | R29: =Q29 -> 0 | S29: =R29 -> 0
B30: 판매비와관리비(R&D제외) | D30: =D26-D28-D32 -> 24.39 | E30: =E26-E28-E32 -> 26.71 | F30: =F26-F28-F32 -> 20.44 | G30: =G26-G28-G32 -> 23.94 | H30: =H26-H28-H32 -> 29.98 | I30: =I26-I28-I32 -> 55.01 | J30: =J26-J28-J32 -> 33.94 | K30: =K26-K28-K32 -> 32.76 | ... P30: =P26-P28-P32 -> 25.52 | Q30: =Q31*Q22 -> 0 | R30: =R31*R22 -> 0 | S30: =S31*S22 -> 0
B31: % of sales | D31: =D30/D22 -> 0.077381897 | E31: =E30/E22 -> 0.12337752 | F31: =F30/F22 -> 0.12873158 | G31: =G30/G22 -> 0.10572804 | H31: =H30/H22 -> 0.06363154 | I31: =I30/I22 -> 0.11743985 | J31: =J30/J22 -> 0.068386057 | K31: =K30/K22 -> 0.06938179 | ... P31: =P30/P22 -> 0.050977807 | Q31: =N31 -> 0.069485604 | R31: 0.106 | S31: =O31 -> 0.06925591
B32: 영업이익 | C32: A201370.IP | D32: =IFERROR(VLOOKUP($C32,FS_별도!$A:$AL,D$2,FALSE),0) -> 23.15 | E32: =IFERROR(VLOOKUP($C32,FS_별도!$A:$AL,E$2,FALSE),0) -> -41.64 | F32: =IFERROR(VLOOKUP($C32,FS_별도!$A:$AL,F$2,FALSE),0) -> -34.39 | G32: =IFERROR(VLOOKUP($C32,FS_별도!$A:$AL,G$2,FALSE),0) -> 19.47 | H32: =IFERROR(VLOOKUP($C32,FS_별도!$A:$AL,H$2,FALSE),0) -> 159.82 | I32: =IFERROR(VLOOKUP($C32,FS_별도!$A:$AL,I$2,FALSE),0) -> 81.68 | J32: =IFERROR(VLOOKUP($C32,FS_별도!$A:$AL,J$2,FALSE),0) -> 65.45 | K32: =IFERROR(VLOOKUP($C32,FS_별도!$A:$AL,K$2,FALSE),0) -> 40.2 | ... N32: =IFERROR(VLOOKUP($C32,FS_별도!$A:$AL,N$2,FALSE),0) -> -215.33 | O32: =IFERROR(VLOOKUP($C32,'FS_별도(분기누적)'!$A:$BS,O$2,FALSE),0) -> -129.98 | P32: =IFERROR(VLOOKUP($C32,'FS_별도(분기누적)'!$A:$BS,P$2,FALSE),0) -> -14.23
B33: Operating profit margin (%) | D33: =D32/D22 -> 0.073447762 | E33: =E32/E22 -> -0.19234145 | F33: =F32/F22 -> -0.21658899 | G33: =G32/G22 -> 0.085986839 | H33: =H32/H22 -> 0.33921257 | I33: =I32/I22 -> 0.17437715 | J33: =J32/J22 -> 0.13187588 | K33: =K32/K22 -> 0.085138827 | ... P33: =P32/P22 -> -0.028425321
B34: 종속기업,공동지배기업및관계기업관련손익 | C34: A202880.IP | D34: =IFERROR(VLOOKUP($C34,FS_별도!$A:$AL,D$2,FALSE),0) -> 0 | E34: =IFERROR(VLOOKUP($C34,FS_별도!$A:$AL,E$2,FALSE),0) -> 0 | F34: =IFERROR(VLOOKUP($C34,FS_별도!$A:$AL,F$2,FALSE),0) -> 0 | G34: =IFERROR(VLOOKUP($C34,FS_별도!$A:$AL,G$2,FALSE),0) -> 0 | H34: =IFERROR(VLOOKUP($C34,FS_별도!$A:$AL,H$2,FALSE),0) -> 0 | I34: =IFERROR(VLOOKUP($C34,FS_별도!$A:$AL,I$2,FALSE),0) -> 0 | J34: =IFERROR(VLOOKUP($C34,FS_별도!$A:$AL,J$2,FALSE),0) -> 0 | K34: =IFERROR(VLOOKUP($C34,FS_별도!$A:$AL,K$2,FALSE),0) -> 0 | ... N34: =IFERROR(VLOOKUP($C34,FS_별도!$A:$AL,N$2,FALSE),0) -> 0 | O34: =IFERROR(VLOOKUP($C34,'FS_별도(분기누적)'!$A:$BS,O$2,FALSE),0) -> 0 | P34: =IFERROR(VLOOKUP($C34,'FS_별도(분기누적)'!$A:$BS,P$2,FALSE),0) -> 0
B35: 금융수익 | C35: A202210.IP | D35: =IFERROR(VLOOKUP($C35,FS_별도!$A:$AL,D$2,FALSE),0) -> 2.67 | E35: =IFERROR(VLOOKUP($C35,FS_별도!$A:$AL,E$2,FALSE),0) -> 3.24 | F35: =IFERROR(VLOOKUP($C35,FS_별도!$A:$AL,F$2,FALSE),0) -> 2.79 | G35: =IFERROR(VLOOKUP($C35,FS_별도!$A:$AL,G$2,FALSE),0) -> 2.95 | H35: =IFERROR(VLOOKUP($C35,FS_별도!$A:$AL,H$2,FALSE),0) -> 2.84 | I35: =IFERROR(VLOOKUP($C35,FS_별도!$A:$AL,I$2,FALSE),0) -> 8.41 | J35: =IFERROR(VLOOKUP($C35,FS_별도!$A:$AL,J$2,FALSE),0) -> 24.04 | K35: =IFERROR(VLOOKUP($C35,FS_별도!$A:$AL,K$2,FALSE),0) -> 0.89 | ... N35: =IFERROR(VLOOKUP($C35,FS_별도!$A:$AL,N$2,FALSE),0) -> 5.58 | O35: =IFERROR(VLOOKUP($C35,'FS_별도(분기누적)'!$A:$BS,O$2,FALSE),0) -> 3.18 | P35: =IFERROR(VLOOKUP($C35,'FS_별도(분기누적)'!$A:$BS,P$2,FALSE),0) -> 0.84 | Q35: =Q36+Q37+Q38 -> 0 | R35: =R36+R37+R38 -> 0 | S35: =S36+S37+S38 -> 0
B36: 이자수익 | C36: A202220.IP | D36: =IFERROR(VLOOKUP($C36,FS_별도!$A:$AL,D$2,FALSE),0) -> 2.67 | E36: =IFERROR(VLOOKUP($C36,FS_별도!$A:$AL,E$2,FALSE),0) -> 3.24 | F36: =IFERROR(VLOOKUP($C36,FS_별도!$A:$AL,F$2,FALSE),0) -> 2.79 | G36: =IFERROR(VLOOKUP($C36,FS_별도!$A:$AL,G$2,FALSE),0) -> 2.95 | H36: =IFERROR(VLOOKUP($C36,FS_별도!$A:$AL,H$2,FALSE),0) -> 2.84 | I36: =IFERROR(VLOOKUP($C36,FS_별도!$A:$AL,I$2,FALSE),0) -> 2.92 | J36: =IFERROR(VLOOKUP($C36,FS_별도!$A:$AL,J$2,FALSE),0) -> 1.01 | K36: =IFERROR(VLOOKUP($C36,FS_별도!$A:$AL,K$2,FALSE),0) -> 0.89 | ... N36: =IFERROR(VLOOKUP($C36,FS_별도!$A:$AL,N$2,FALSE),0) -> 5.58 | O36: =IFERROR(VLOOKUP($C36,'FS_별도(분기누적)'!$A:$BS,O$2,FALSE),0) -> 0 | P36: =IFERROR(VLOOKUP($C36,'FS_별도(분기누적)'!$A:$BS,P$2,FALSE),0) -> 0 | Q36: =Q226 -> 0 | R36: =R226 -> 0 | S36: =S226 -> 0
B37: 외환거래이익 | C37: A202240.IP | D37: =IFERROR(VLOOKUP($C37,FS_별도!$A:$AL,D$2,FALSE),0) -> 0 | E37: =IFERROR(VLOOKUP($C37,FS_별도!$A:$AL,E$2,FALSE),0) -> 0 | F37: =IFERROR(VLOOKUP($C37,FS_별도!$A:$AL,F$2,FALSE),0) -> 0 | G37: =IFERROR(VLOOKUP($C37,FS_별도!$A:$AL,G$2,FALSE),0) -> 0 | H37: =IFERROR(VLOOKUP($C37,FS_별도!$A:$AL,H$2,FALSE),0) -> 0 | I37: =IFERROR(VLOOKUP($C37,FS_별도!$A:$AL,I$2,FALSE),0) -> 0 | J37: =IFERROR(VLOOKUP($C37,FS_별도!$A:$AL,J$2,FALSE),0) -> 0 | K37: =IFERROR(VLOOKUP($C37,FS_별도!$A:$AL,K$2,FALSE),0) -> 0 | ... N37: =IFERROR(VLOOKUP($C37,FS_별도!$A:$AL,N$2,FALSE),0) -> 0 | O37: =IFERROR(VLOOKUP($C37,'FS_별도(분기누적)'!$A:$BS,O$2,FALSE),0) -> 0 | P37: =IFERROR(VLOOKUP($C37,'FS_별도(분기누적)'!$A:$BS,P$2,FALSE),0) -> 0
B38: 기타금융수익 | D38: =D35-D36-D37 -> 0 | E38: =E35-E36-E37 -> 0 | F38: =F35-F36-F37 -> 0 | G38: =G35-G36-G37 -> 0 | H38: =H35-H36-H37 -> 0 | I38: =I35-I36-I37 -> 5.49 | J38: =J35-J36-J37 -> 23.03 | K38: =K35-K36-K37 -> 0 | ... P38: =P35-P36-P37 -> 0.84 | Q38: 0 | R38: 0 | S38: 0
B39: 금융원가 | C39: A202550.IP | D39: =IFERROR(VLOOKUP($C39,FS_별도!$A:$AL,D$2,FALSE),0) -> 10.53 | E39: =IFERROR(VLOOKUP($C39,FS_별도!$A:$AL,E$2,FALSE),0) -> 5.06 | F39: =IFERROR(VLOOKUP($C39,FS_별도!$A:$AL,F$2,FALSE),0) -> 3.31 | G39: =IFERROR(VLOOKUP($C39,FS_별도!$A:$AL,G$2,FALSE),0) -> 4.67 | H39: =IFERROR(VLOOKUP($C39,FS_별도!$A:$AL,H$2,FALSE),0) -> 15.97 | I39: =IFERROR(VLOOKUP($C39,FS_별도!$A:$AL,I$2,FALSE),0) -> 22.35 | J39: =IFERROR(VLOOKUP($C39,FS_별도!$A:$AL,J$2,FALSE),0) -> 22.49 | K39: =IFERROR(VLOOKUP($C39,FS_별도!$A:$AL,K$2,FALSE),0) -> 30.86 | ... N39: =IFERROR(VLOOKUP($C39,FS_별도!$A:$AL,N$2,FALSE),0) -> 42.59 | O39: =IFERROR(VLOOKUP($C39,'FS_별도(분기누적)'!$A:$BS,O$2,FALSE),0) -> 21.08 | P39: =IFERROR(VLOOKUP($C39,'FS_별도(분기누적)'!$A:$BS,P$2,FALSE),0) -> 19 | Q39: =Q40+Q41+Q42 -> 0 | R39: =R40+R41+R42 -> 0 | S39: =S40+S41+S42 -> 0
B40: 이자비용 | C40: A202560.IP | D40: =IFERROR(VLOOKUP($C40,FS_별도!$A:$AL,D$2,FALSE),0) -> 10.53 | E40: =IFERROR(VLOOKUP($C40,FS_별도!$A:$AL,E$2,FALSE),0) -> 5.06 | F40: =IFERROR(VLOOKUP($C40,FS_별도!$A:$AL,F$2,FALSE),0) -> 3.31 | G40: =IFERROR(VLOOKUP($C40,FS_별도!$A:$AL,G$2,FALSE),0) -> 4.67 | H40: =IFERROR(VLOOKUP($C40,FS_별도!$A:$AL,H$2,FALSE),0) -> 12.09 | I40: =IFERROR(VLOOKUP($C40,FS_별도!$A:$AL,I$2,FALSE),0) -> 22.35 | J40: =IFERROR(VLOOKUP($C40,FS_별도!$A:$AL,J$2,FALSE),0) -> 22.49 | K40: =IFERROR(VLOOKUP($C40,FS_별도!$A:$AL,K$2,FALSE),0) -> 16.44 | ... N40: =IFERROR(VLOOKUP($C40,FS_별도!$A:$AL,N$2,FALSE),0) -> 42.59 | O40: =IFERROR(VLOOKUP($C40,'FS_별도(분기누적)'!$A:$BS,O$2,FALSE),0) -> 0 | P40: =IFERROR(VLOOKUP($C40,'FS_별도(분기누적)'!$A:$BS,P$2,FALSE),0) -> 0 | Q40: =Q232 -> 0 | R40: =R232 -> 0 | S40: =S232 -> 0
B41: 외환거래손실 | C41: A202570.IP | D41: =IFERROR(VLOOKUP($C41,FS_별도!$A:$AL,D$2,FALSE),0) -> 0 | E41: =IFERROR(VLOOKUP($C41,FS_별도!$A:$AL,E$2,FALSE),0) -> 0 | F41: =IFERROR(VLOOKUP($C41,FS_별도!$A:$AL,F$2,FALSE),0) -> 0 | G41: =IFERROR(VLOOKUP($C41,FS_별도!$A:$AL,G$2,FALSE),0) -> 0 | H41: =IFERROR(VLOOKUP($C41,FS_별도!$A:$AL,H$2,FALSE),0) -> 0 | I41: =IFERROR(VLOOKUP($C41,FS_별도!$A:$AL,I$2,FALSE),0) -> 0 | J41: =IFERROR(VLOOKUP($C41,FS_별도!$A:$AL,J$2,FALSE),0) -> 0 | K41: =IFERROR(VLOOKUP($C41,FS_별도!$A:$AL,K$2,FALSE),0) -> 0 | ... N41: =IFERROR(VLOOKUP($C41,FS_별도!$A:$AL,N$2,FALSE),0) -> 0 | O41: =IFERROR(VLOOKUP($C41,'FS_별도(분기누적)'!$A:$BS,O$2,FALSE),0) -> 0 | P41: =IFERROR(VLOOKUP($C41,'FS_별도(분기누적)'!$A:$BS,P$2,FALSE),0) -> 0
B42: 기타금융원가 | D42: =D39-D40-D41 -> 0 | E42: =E39-E40-E41 -> 0 | F42: =F39-F40-F41 -> 0 | G42: =G39-G40-G41 -> 0 | H42: =H39-H40-H41 -> 3.88 | I42: =I39-I40-I41 -> 0 | J42: =J39-J40-J41 -> 0 | K42: =K39-K40-K41 -> 14.42 | ... P42: =P39-P40-P41 -> 19 | Q42: 0 | R42: 0 | S42: 0
B43: 기타영업외손익 | C43: A204410.IP | D43: =IFERROR(VLOOKUP($C43,FS_별도!$A:$AL,D$2,FALSE),0) -> 18.45 | E43: =IFERROR(VLOOKUP($C43,FS_별도!$A:$AL,E$2,FALSE),0) -> 26.49 | F43: =IFERROR(VLOOKUP($C43,FS_별도!$A:$AL,F$2,FALSE),0) -> 3.69 | G43: =IFERROR(VLOOKUP($C43,FS_별도!$A:$AL,G$2,FALSE),0) -> -7.45 | H43: =IFERROR(VLOOKUP($C43,FS_별도!$A:$AL,H$2,FALSE),0) -> 5.39 | I43: =IFERROR(VLOOKUP($C43,FS_별도!$A:$AL,I$2,FALSE),0) -> -30.33 | J43: =IFERROR(VLOOKUP($C43,FS_별도!$A:$AL,J$2,FALSE),0) -> 2.53 | K43: =IFERROR(VLOOKUP($C43,FS_별도!$A:$AL,K$2,FALSE),0) -> 3.06 | ... N43: =IFERROR(VLOOKUP($C43,FS_별도!$A:$AL,N$2,FALSE),0) -> -236.83 | O43: =IFERROR(VLOOKUP($C43,'FS_별도(분기누적)'!$A:$BS,O$2,FALSE),0) -> -0.64 | P43: =IFERROR(VLOOKUP($C43,'FS_별도(분기누적)'!$A:$BS,P$2,FALSE),0) -> -0.24
B44: 법인세비용차감전계속사업이익 | C44: A203120.IP | D44: =IFERROR(VLOOKUP($C44,FS_별도!$A:$AL,D$2,FALSE),0) -> 33.74 | E44: =IFERROR(VLOOKUP($C44,FS_별도!$A:$AL,E$2,FALSE),0) -> -16.97 | F44: =IFERROR(VLOOKUP($C44,FS_별도!$A:$AL,F$2,FALSE),0) -> -31.23 | G44: =IFERROR(VLOOKUP($C44,FS_별도!$A:$AL,G$2,FALSE),0) -> 10.3 | H44: =IFERROR(VLOOKUP($C44,FS_별도!$A:$AL,H$2,FALSE),0) -> 152.09 | I44: =IFERROR(VLOOKUP($C44,FS_별도!$A:$AL,I$2,FALSE),0) -> 37.4 | J44: =IFERROR(VLOOKUP($C44,FS_별도!$A:$AL,J$2,FALSE),0) -> 69.53 | K44: =IFERROR(VLOOKUP($C44,FS_별도!$A:$AL,K$2,FALSE),0) -> 13.28 | ... N44: =IFERROR(VLOOKUP($C44,FS_별도!$A:$AL,N$2,FALSE),0) -> -489.17 | O44: =IFERROR(VLOOKUP($C44,'FS_별도(분기누적)'!$A:$BS,O$2,FALSE),0) -> -148.52 | P44: =IFERROR(VLOOKUP($C44,'FS_별도(분기누적)'!$A:$BS,P$2,FALSE),0) -> -32.62 | Q44: =Q32+Q34+Q35-Q39+Q43 -> 0 | R44: =R32+R34+R35-R39+R43 -> 0 | S44: =S32+S34+S35-S39+S43 -> 0
B45: Pretax margin (%) | D45: =D44/D22 -> 0.10704654 | E45: =E44/E22 -> -0.078386992 | F45: =F44/F22 -> -0.19668724 | G45: =G44/G22 -> 0.045488672 | H45: =H44/H22 -> 0.3228059 | I45: =I44/I22 -> 0.079844581 | J45: =J44/J22 -> 0.14009672 | K45: =K44/K22 -> 0.028125463 | ... S45: =S44/S22 -> #DIV/0!
B46: 법인세비용 | C46: A203130.IP | D46: =IFERROR(VLOOKUP($C46,FS_별도!$A:$AL,D$2,FALSE),0) -> 4.13 | E46: =IFERROR(VLOOKUP($C46,FS_별도!$A:$AL,E$2,FALSE),0) -> 4.32 | F46: =IFERROR(VLOOKUP($C46,FS_별도!$A:$AL,F$2,FALSE),0) -> 5.61 | G46: =IFERROR(VLOOKUP($C46,FS_별도!$A:$AL,G$2,FALSE),0) -> 1.67 | H46: =IFERROR(VLOOKUP($C46,FS_별도!$A:$AL,H$2,FALSE),0) -> 3.91 | I46: =IFERROR(VLOOKUP($C46,FS_별도!$A:$AL,I$2,FALSE),0) -> -4.49 | J46: =IFERROR(VLOOKUP($C46,FS_별도!$A:$AL,J$2,FALSE),0) -> 2.93 | K46: =IFERROR(VLOOKUP($C46,FS_별도!$A:$AL,K$2,FALSE),0) -> -13.37 | ... N46: =IFERROR(VLOOKUP($C46,FS_별도!$A:$AL,N$2,FALSE),0) -> 18 | O46: =IFERROR(VLOOKUP($C46,'FS_별도(분기누적)'!$A:$BS,O$2,FALSE),0) -> 25.83 | P46: =IFERROR(VLOOKUP($C46,'FS_별도(분기누적)'!$A:$BS,P$2,FALSE),0) -> 7.53 | Q46: =IF(Q44<0,0,IF(Q44>200,2*$X$48+(200-2)*$X$49+(Q44-200)*$X$50,2*$X$48+(Q44-2)*$X$49)) -> -0.22 | R46: =IF(R44<0,0,IF(R44>200,2*$X$48+(200-2)*$X$49+(R44-200)*$X$50,2*$X$48+(R44-2)*$X$49)) -> -0.22 | S46: =IF(S44<0,0,IF(S44>200,2*$X$48+(200-2)*$X$49+(S44-200)*$X$50,2*$X$48+(S44-2)*$X$49)) -> -0.22
B47: Tax rate (%) | D47: =D46/D44 -> 0.12240664 | E47: =E46/E44 -> -0.25456688 | F47: =F46/F44 -> -0.17963497 | G47: =G46/G44 -> 0.16213592 | H47: =H46/H44 -> 0.025708462 | I47: =I46/I44 -> -0.12005348 | J47: =J46/J44 -> 0.042140083 | K47: =K46/K44 -> -1.0067771 | ... S47: =S46/S44 -> #DIV/0! | W47: 과세표준 | X47: 적용세율
B48: 계속사업이익 | C48: A203140.IP | D48: =IFERROR(VLOOKUP($C48,FS_별도!$A:$AL,D$2,FALSE),0) -> 29.61 | E48: =IFERROR(VLOOKUP($C48,FS_별도!$A:$AL,E$2,FALSE),0) -> -21.29 | F48: =IFERROR(VLOOKUP($C48,FS_별도!$A:$AL,F$2,FALSE),0) -> -36.84 | G48: =IFERROR(VLOOKUP($C48,FS_별도!$A:$AL,G$2,FALSE),0) -> 8.63 | H48: =IFERROR(VLOOKUP($C48,FS_별도!$A:$AL,H$2,FALSE),0) -> 148.18 | I48: =IFERROR(VLOOKUP($C48,FS_별도!$A:$AL,I$2,FALSE),0) -> 41.89 | J48: =IFERROR(VLOOKUP($C48,FS_별도!$A:$AL,J$2,FALSE),0) -> 66.6 | K48: =IFERROR(VLOOKUP($C48,FS_별도!$A:$AL,K$2,FALSE),0) -> 26.65 | ... N48: =IFERROR(VLOOKUP($C48,FS_별도!$A:$AL,N$2,FALSE),0) -> -507.17 | O48: =IFERROR(VLOOKUP($C48,'FS_별도(분기누적)'!$A:$BS,O$2,FALSE),0) -> -174.34 | P48: =IFERROR(VLOOKUP($C48,'FS_별도(분기누적)'!$A:$BS,P$2,FALSE),0) -> -40.15 | Q48: =Q44-Q46 -> 0.22 | R48: =R44-R46 -> 0.22 | S48: =S44-S46 -> 0.22 | W48: 2억원 이하 | X48: 0.11
B49: Net profit margin (%) | D49: =D48/D22 -> 0.093943336 | E49: =E48/E22 -> -0.098341725 | F49: =F48/F22 -> -0.23201915 | G49: =G48/G22 -> 0.038113324 | H49: =H48/H22 -> 0.31450706 | I49: =I48/I22 -> 0.0894302 | J49: =J48/J22 -> 0.13419303 | K49: =K48/K22 -> 0.056441536 | ... S49: =S48/S22 -> #DIV/0! | W49: 2~200억원 | X49: 0.22
C50: A203190.IP | D50: =IFERROR(VLOOKUP($C50,FS_별도!$A:$AL,D$2,FALSE),0) -> 0 | E50: =IFERROR(VLOOKUP($C50,FS_별도!$A:$AL,E$2,FALSE),0) -> 0 | F50: =IFERROR(VLOOKUP($C50,FS_별도!$A:$AL,F$2,FALSE),0) -> 0 | G50: =IFERROR(VLOOKUP($C50,FS_별도!$A:$AL,G$2,FALSE),0) -> 0 | H50: =IFERROR(VLOOKUP($C50,FS_별도!$A:$AL,H$2,FALSE),0) -> 0 | I50: =IFERROR(VLOOKUP($C50,FS_별도!$A:$AL,I$2,FALSE),0) -> 0 | J50: =IFERROR(VLOOKUP($C50,FS_별도!$A:$AL,J$2,FALSE),0) -> 0 | K50: =IFERROR(VLOOKUP($C50,FS_별도!$A:$AL,K$2,FALSE),0) -> 0 | ... N50: =IFERROR(VLOOKUP($C50,FS_별도!$A:$AL,N$2,FALSE),0) -> 0 | O50: =IFERROR(VLOOKUP($C50,'FS_별도(분기누적)'!$A:$BS,O$2,FALSE),0) -> 0 | P50: =IFERROR(VLOOKUP($C50,'FS_별도(분기누적)'!$A:$BS,P$2,FALSE),0) -> 0 | Q50: =Q48*Q51 -> 0 | R50: =R48*R51 -> 0 | S50: =S48*S51 -> 0 | W50: 200~3000억원 | X50: 0.242
B51: % of Net profit | D51: =D50/D48 -> 0 | E51: =E50/E48 -> 0 | F51: =F50/F48 -> 0 | G51: =G50/G48 -> 0 | H51: =H50/H48 -> 0 | I51: =I50/I48 -> 0 | J51: =J50/J48 -> 0 | K51: =K50/K48 -> 0 | ... P51: =P50/P48 -> 0 | Q51: 0 | R51: 0 | S51: 0 | W51: 3000억원 초과분 | X51: 0.275
B52: 당기순이익 | C52: A203180.IP | D52: =IFERROR(VLOOKUP($C52,FS_별도!$A:$AL,D$2,FALSE),0) -> 29.61 | E52: =IFERROR(VLOOKUP($C52,FS_별도!$A:$AL,E$2,FALSE),0) -> -21.29 | F52: =IFERROR(VLOOKUP($C52,FS_별도!$A:$AL,F$2,FALSE),0) -> -36.84 | G52: =IFERROR(VLOOKUP($C52,FS_별도!$A:$AL,G$2,FALSE),0) -> 8.63 | H52: =IFERROR(VLOOKUP($C52,FS_별도!$A:$AL,H$2,FALSE),0) -> 148.18 | I52: =IFERROR(VLOOKUP($C52,FS_별도!$A:$AL,I$2,FALSE),0) -> 41.89 | J52: =IFERROR(VLOOKUP($C52,FS_별도!$A:$AL,J$2,FALSE),0) -> 66.6 | K52: =IFERROR(VLOOKUP($C52,FS_별도!$A:$AL,K$2,FALSE),0) -> 26.65 | ... N52: =IFERROR(VLOOKUP($C52,FS_별도!$A:$AL,N$2,FALSE),0) -> -507.17 | O52: =IFERROR(VLOOKUP($C52,'FS_별도(분기누적)'!$A:$BS,O$2,FALSE),0) -> -174.34 | P52: =IFERROR(VLOOKUP($C52,'FS_별도(분기누적)'!$A:$BS,P$2,FALSE),0) -> -40.15 | Q52: =Q48-Q50 -> 0.22 | R52: =R48-R50 -> 0.22 | S52: =S48-S50 -> 0.22
B54: # Shares outstanding (mn) | D54: =D55+D56 -> 17.554 | E54: =E55+E56 -> 17.554 | F54: =F55+F56 -> 17.554 | G54: =G55+G56 -> 17.554 | H54: =H55+H56 -> 17.554 | I54: =I55+I56 -> 17.554 | J54: =J55+J56 -> 17.554 | K54: =K55+K56 -> 18.476 | ... S54: =S55+S56 -> 42.362
B55: Common | C55: A120680.IP | D55: =IFERROR(VLOOKUP($C55,FS_별도!$A:$AL,D$2,FALSE)/1000,0) -> 17.554 | E55: =IFERROR(VLOOKUP($C55,FS_별도!$A:$AL,E$2,FALSE)/1000,0) -> 17.554 | F55: =IFERROR(VLOOKUP($C55,FS_별도!$A:$AL,F$2,FALSE)/1000,0) -> 17.554 | G55: =IFERROR(VLOOKUP($C55,FS_별도!$A:$AL,G$2,FALSE)/1000,0) -> 17.554 | H55: =IFERROR(VLOOKUP($C55,FS_별도!$A:$AL,H$2,FALSE)/1000,0) -> 17.554 | I55: =IFERROR(VLOOKUP($C55,FS_별도!$A:$AL,I$2,FALSE)/1000,0) -> 17.554 | J55: =IFERROR(VLOOKUP($C55,FS_별도!$A:$AL,J$2,FALSE)/1000,0) -> 17.554 | K55: =IFERROR(VLOOKUP($C55,FS_별도!$A:$AL,K$2,FALSE)/1000,0) -> 18.476 | ... N55: =IFERROR(VLOOKUP($C55,FS_별도!$A:$AL,N$2,FALSE)/1000,0) -> 42.362 | O55: =IFERROR(VLOOKUP($C55,'FS_별도(분기누적)'!$A:$BS,O$2,FALSE)/1000,0) -> 42.362 | P55: =IFERROR(VLOOKUP($C55,'FS_별도(분기누적)'!$A:$BS,P$2,FALSE)/1000,0) -> 42.362 | Q55: =N55 -> 42.362 | R55: =Q55 -> 42.362 | S55: =R55 -> 42.362
B56: Preferred | C56: A120690.IP | D56: =IFERROR(VLOOKUP($C56,FS_별도!$A:$AL,D$2,FALSE)/1000,0) -> 0 | E56: =IFERROR(VLOOKUP($C56,FS_별도!$A:$AL,E$2,FALSE)/1000,0) -> 0 | F56: =IFERROR(VLOOKUP($C56,FS_별도!$A:$AL,F$2,FALSE)/1000,0) -> 0 | G56: =IFERROR(VLOOKUP($C56,FS_별도!$A:$AL,G$2,FALSE)/1000,0) -> 0 | H56: =IFERROR(VLOOKUP($C56,FS_별도!$A:$AL,H$2,FALSE)/1000,0) -> 0 | I56: =IFERROR(VLOOKUP($C56,FS_별도!$A:$AL,I$2,FALSE)/1000,0) -> 0 | J56: =IFERROR(VLOOKUP($C56,FS_별도!$A:$AL,J$2,FALSE)/1000,0) -> 0 | K56: =IFERROR(VLOOKUP($C56,FS_별도!$A:$AL,K$2,FALSE)/1000,0) -> 0 | ... N56: =IFERROR(VLOOKUP($C56,FS_별도!$A:$AL,N$2,FALSE)/1000,0) -> 0 | O56: =IFERROR(VLOOKUP($C56,'FS_별도(분기누적)'!$A:$BS,O$2,FALSE)/1000,0) -> 0 | P56: =IFERROR(VLOOKUP($C56,'FS_별도(분기누적)'!$A:$BS,P$2,FALSE)/1000,0) -> 0 | Q56: =N56 -> 0 | R56: =Q56 -> 0 | S56: =R56 -> 0
B57: EPS | D57: =(D52-D141)*100/D55 -> 168.6795 | E57: =(E52-E141)*100/E55 -> -121.2829 | F57: =(F52-F141)*100/F55 -> -209.8667 | G57: =(G52-G141)*100/G55 -> 49.162584 | H57: =(H52-H141)*100/H55 -> 844.13809 | I57: =(I52-I141)*100/I55 -> 238.63507 | J57: =(J52-J141)*100/J55 -> 379.40071 | K57: =(K52-K141)*100/K55 -> 144.24118 | ... S57: =(S52-S141)*100/S55 -> 0.51933336
B58: Yoy growth (%) | K58: =K57/D57-1 -> -0.14488023 | L58: =L57/K57-1 -> -0.49430022 | M58: =M57/L57-1 -> -6.3899676 | N58: =N57/M57-1 -> 2.0451516 | O58: =O57/N57-1 -> -0.65624938 | P58: =P57/O57-1 -> -0.76970288 | Q58: =Q57/N57-1 -> -1.0004338 | R58: =R57/Q57-1 -> 0 | S58: =S57/R57-1 -> 0
B60: BALANCE SHEET (억원) | D60: =D$3 -> 2014 | E60: =E$3 -> 2015 | F60: =F$3 -> 2016 | G60: =G$3 -> 2017 | H60: =H$3 -> 2018 | I60: =I$3 -> 2019 | J60: =J$3 -> 2020 | K60: =K$3 -> 2021 | ... S60: =S$3 -> 2027E | W60: 구 분 (단위: 억원) | X60: 발행 전 | Y60: 메자닌 발행 | Z60: 발행 후
W61: 자산총계 | X61: =P97 -> 1549.88 | Y61: =Y62 -> 500 | Z61: =SUM(X61:Y61) -> 2049.88
B62: 현금및현금성자산 | C62: A190650.IP | D62: =IFERROR(VLOOKUP($C62,FS_별도!$A:$AL,D$2,FALSE),0) -> 170.91 | E62: =IFERROR(VLOOKUP($C62,FS_별도!$A:$AL,E$2,FALSE),0) -> 21.5 | F62: =IFERROR(VLOOKUP($C62,FS_별도!$A:$AL,F$2,FALSE),0) -> 38.36 | G62: =IFERROR(VLOOKUP($C62,FS_별도!$A:$AL,G$2,FALSE),0) -> 155.6 | H62: =IFERROR(VLOOKUP($C62,FS_별도!$A:$AL,H$2,FALSE),0) -> 328.49 | I62: =IFERROR(VLOOKUP($C62,FS_별도!$A:$AL,I$2,FALSE),0) -> 143.81 | J62: =IFERROR(VLOOKUP($C62,FS_별도!$A:$AL,J$2,FALSE),0) -> 175.76 | K62: =IFERROR(VLOOKUP($C62,FS_별도!$A:$AL,K$2,FALSE),0) -> 185.83 | ... N62: =IFERROR(VLOOKUP($C62,FS_별도!$A:$AL,N$2,FALSE),0) -> 141.6 | O62: =IFERROR(VLOOKUP($C62,'FS_별도(분기누적)'!$A:$BS,O$2,FALSE),0) -> 240.75 | P62: =IFERROR(VLOOKUP($C62,'FS_별도(분기누적)'!$A:$BS,P$2,FALSE),0) -> 82.32 | Q62: =Q204 -> 314.84 | R62: =R204 -> 390.0795 | S62: =S204 -> 451.73204 | W62: 부채총계 | X62: =P123 -> 1040.31 | Y62: 500 | Z62: =SUM(X62:Y62) -> 1540.31
B63: 단기금융자산 | D63: =SUM(D64:D71) -> 0 | E63: =SUM(E64:E71) -> 160 | F63: =SUM(F64:F71) -> 160 | G63: =SUM(G64:G71) -> 50 | H63: =SUM(H64:H71) -> 0 | I63: =SUM(I64:I71) -> 0 | J63: =SUM(J64:J71) -> 0.3 | K63: =SUM(K64:K71) -> 0 | ... S63: =SUM(S64:S71) -> 0 | W63: 자본총계 | X63: =P131 -> 509.57 | Z63: =SUM(X63:Y63) -> 509.57
B64: 당기손익-공정가치측정금융자산 | C64: A114490.IP | D64: =IFERROR(VLOOKUP($C64,FS_별도!$A:$AL,D$2,FALSE),0) -> 0 | E64: =IFERROR(VLOOKUP($C64,FS_별도!$A:$AL,E$2,FALSE),0) -> 0 | F64: =IFERROR(VLOOKUP($C64,FS_별도!$A:$AL,F$2,FALSE),0) -> 0 | G64: =IFERROR(VLOOKUP($C64,FS_별도!$A:$AL,G$2,FALSE),0) -> 0 | H64: =IFERROR(VLOOKUP($C64,FS_별도!$A:$AL,H$2,FALSE),0) -> 0 | I64: =IFERROR(VLOOKUP($C64,FS_별도!$A:$AL,I$2,FALSE),0) -> 0 | J64: =IFERROR(VLOOKUP($C64,FS_별도!$A:$AL,J$2,FALSE),0) -> 0 | K64: =IFERROR(VLOOKUP($C64,FS_별도!$A:$AL,K$2,FALSE),0) -> 0 | ... N64: =IFERROR(VLOOKUP($C64,FS_별도!$A:$AL,N$2,FALSE),0) -> 0 | O64: =IFERROR(VLOOKUP($C64,'FS_별도(분기누적)'!$A:$BS,O$2,FALSE),0) -> 0 | P64: =IFERROR(VLOOKUP($C64,'FS_별도(분기누적)'!$A:$BS,P$2,FALSE),0) -> 0 | Q64: =N64 -> 0 | R64: =Q64 -> 0 | S64: =R64 -> 0 | W64: 부채비율 | X64: =X62/X63 -> 2.0415448 | Y64: - | Z64: =Z62/Z63 -> 3.0227643
B65: 상각후원가측정유가증권 | C65: A114530.IP | D65: =IFERROR(VLOOKUP($C65,FS_별도!$A:$AL,D$2,FALSE),0) -> 0 | E65: =IFERROR(VLOOKUP($C65,FS_별도!$A:$AL,E$2,FALSE),0) -> 0 | F65: =IFERROR(VLOOKUP($C65,FS_별도!$A:$AL,F$2,FALSE),0) -> 0 | G65: =IFERROR(VLOOKUP($C65,FS_별도!$A:$AL,G$2,FALSE),0) -> 0 | H65: =IFERROR(VLOOKUP($C65,FS_별도!$A:$AL,H$2,FALSE),0) -> 0 | I65: =IFERROR(VLOOKUP($C65,FS_별도!$A:$AL,I$2,FALSE),0) -> 0 | J65: =IFERROR(VLOOKUP($C65,FS_별도!$A:$AL,J$2,FALSE),0) -> 0 | K65: =IFERROR(VLOOKUP($C65,FS_별도!$A:$AL,K$2,FALSE),0) -> 0 | ... N65: =IFERROR(VLOOKUP($C65,FS_별도!$A:$AL,N$2,FALSE),0) -> 0 | O65: =IFERROR(VLOOKUP($C65,'FS_별도(분기누적)'!$A:$BS,O$2,FALSE),0) -> 0 | P65: =IFERROR(VLOOKUP($C65,'FS_별도(분기누적)'!$A:$BS,P$2,FALSE),0) -> 0 | Q65: =N65 -> 0 | R65: =Q65 -> 0 | S65: =R65 -> 0
B66: 상각후원가측정금융자산 | C66: A114540.IP | D66: =IFERROR(VLOOKUP($C66,FS_별도!$A:$AL,D$2,FALSE),0) -> 0 | E66: =IFERROR(VLOOKUP($C66,FS_별도!$A:$AL,E$2,FALSE),0) -> 0 | F66: =IFERROR(VLOOKUP($C66,FS_별도!$A:$AL,F$2,FALSE),0) -> 0 | G66: =IFERROR(VLOOKUP($C66,FS_별도!$A:$AL,G$2,FALSE),0) -> 0 | H66: =IFERROR(VLOOKUP($C66,FS_별도!$A:$AL,H$2,FALSE),0) -> 0 | I66: =IFERROR(VLOOKUP($C66,FS_별도!$A:$AL,I$2,FALSE),0) -> 0 | J66: =IFERROR(VLOOKUP($C66,FS_별도!$A:$AL,J$2,FALSE),0) -> 0 | K66: =IFERROR(VLOOKUP($C66,FS_별도!$A:$AL,K$2,FALSE),0) -> 0 | ... N66: =IFERROR(VLOOKUP($C66,FS_별도!$A:$AL,N$2,FALSE),0) -> 0 | O66: =IFERROR(VLOOKUP($C66,'FS_별도(분기누적)'!$A:$BS,O$2,FALSE),0) -> 0 | P66: =IFERROR(VLOOKUP($C66,'FS_별도(분기누적)'!$A:$BS,P$2,FALSE),0) -> 0 | Q66: =N66 -> 0 | R66: =Q66 -> 0 | S66: =R66 -> 0 | W66: 유동비율 | X66: =P81/P113*100 -> 68.103292
B67: 기타포괄손익-공정가치측정금융자산 | C67: A115020.IP | D67: =IFERROR(VLOOKUP($C67,FS_별도!$A:$AL,D$2,FALSE),0) -> 0 | E67: =IFERROR(VLOOKUP($C67,FS_별도!$A:$AL,E$2,FALSE),0) -> 0 | F67: =IFERROR(VLOOKUP($C67,FS_별도!$A:$AL,F$2,FALSE),0) -> 0 | G67: =IFERROR(VLOOKUP($C67,FS_별도!$A:$AL,G$2,FALSE),0) -> 0 | H67: =IFERROR(VLOOKUP($C67,FS_별도!$A:$AL,H$2,FALSE),0) -> 0 | I67: =IFERROR(VLOOKUP($C67,FS_별도!$A:$AL,I$2,FALSE),0) -> 0 | J67: =IFERROR(VLOOKUP($C67,FS_별도!$A:$AL,J$2,FALSE),0) -> 0 | K67: =IFERROR(VLOOKUP($C67,FS_별도!$A:$AL,K$2,FALSE),0) -> 0 | ... N67: =IFERROR(VLOOKUP($C67,FS_별도!$A:$AL,N$2,FALSE),0) -> 0 | O67: =IFERROR(VLOOKUP($C67,'FS_별도(분기누적)'!$A:$BS,O$2,FALSE),0) -> 0 | P67: =IFERROR(VLOOKUP($C67,'FS_별도(분기누적)'!$A:$BS,P$2,FALSE),0) -> 0 | Q67: =N67 -> 0 | R67: =Q67 -> 0 | S67: =R67 -> 0
B68: 단기매매금융자산 | C68: A113100.IP | D68: =IFERROR(VLOOKUP($C68,FS_별도!$A:$AL,D$2,FALSE),0) -> 0 | E68: =IFERROR(VLOOKUP($C68,FS_별도!$A:$AL,E$2,FALSE),0) -> 0 | F68: =IFERROR(VLOOKUP($C68,FS_별도!$A:$AL,F$2,FALSE),0) -> 0 | G68: =IFERROR(VLOOKUP($C68,FS_별도!$A:$AL,G$2,FALSE),0) -> 0 | H68: =IFERROR(VLOOKUP($C68,FS_별도!$A:$AL,H$2,FALSE),0) -> 0 | I68: =IFERROR(VLOOKUP($C68,FS_별도!$A:$AL,I$2,FALSE),0) -> 0 | J68: =IFERROR(VLOOKUP($C68,FS_별도!$A:$AL,J$2,FALSE),0) -> 0 | K68: =IFERROR(VLOOKUP($C68,FS_별도!$A:$AL,K$2,FALSE),0) -> 0 | ... N68: =IFERROR(VLOOKUP($C68,FS_별도!$A:$AL,N$2,FALSE),0) -> 0 | O68: =IFERROR(VLOOKUP($C68,'FS_별도(분기누적)'!$A:$BS,O$2,FALSE),0) -> 0 | P68: =IFERROR(VLOOKUP($C68,'FS_별도(분기누적)'!$A:$BS,P$2,FALSE),0) -> 0 | Q68: =N68 -> 0 | R68: =Q68 -> 0 | S68: =R68 -> 0
B69: 단기금융상품 | C69: A113120.IP | D69: =IFERROR(VLOOKUP($C69,FS_별도!$A:$AL,D$2,FALSE),0) -> 0 | E69: =IFERROR(VLOOKUP($C69,FS_별도!$A:$AL,E$2,FALSE),0) -> 160 | F69: =IFERROR(VLOOKUP($C69,FS_별도!$A:$AL,F$2,FALSE),0) -> 160 | G69: =IFERROR(VLOOKUP($C69,FS_별도!$A:$AL,G$2,FALSE),0) -> 50 | H69: =IFERROR(VLOOKUP($C69,FS_별도!$A:$AL,H$2,FALSE),0) -> 0 | I69: =IFERROR(VLOOKUP($C69,FS_별도!$A:$AL,I$2,FALSE),0) -> 0 | J69: =IFERROR(VLOOKUP($C69,FS_별도!$A:$AL,J$2,FALSE),0) -> 0.3 | K69: =IFERROR(VLOOKUP($C69,FS_별도!$A:$AL,K$2,FALSE),0) -> 0 | ... N69: =IFERROR(VLOOKUP($C69,FS_별도!$A:$AL,N$2,FALSE),0) -> 0 | O69: =IFERROR(VLOOKUP($C69,'FS_별도(분기누적)'!$A:$BS,O$2,FALSE),0) -> 0 | P69: =IFERROR(VLOOKUP($C69,'FS_별도(분기누적)'!$A:$BS,P$2,FALSE),0) -> 0 | Q69: =N69 -> 0 | R69: =Q69 -> 0 | S69: =R69 -> 0
B70: 단기매도가능금융자산 | C70: A113240.IP | D70: =IFERROR(VLOOKUP($C70,FS_별도!$A:$AL,D$2,FALSE),0) -> 0 | E70: =IFERROR(VLOOKUP($C70,FS_별도!$A:$AL,E$2,FALSE),0) -> 0 | F70: =IFERROR(VLOOKUP($C70,FS_별도!$A:$AL,F$2,FALSE),0) -> 0 | G70: =IFERROR(VLOOKUP($C70,FS_별도!$A:$AL,G$2,FALSE),0) -> 0 | H70: =IFERROR(VLOOKUP($C70,FS_별도!$A:$AL,H$2,FALSE),0) -> 0 | I70: =IFERROR(VLOOKUP($C70,FS_별도!$A:$AL,I$2,FALSE),0) -> 0 | J70: =IFERROR(VLOOKUP($C70,FS_별도!$A:$AL,J$2,FALSE),0) -> 0 | K70: =IFERROR(VLOOKUP($C70,FS_별도!$A:$AL,K$2,FALSE),0) -> 0 | ... N70: =IFERROR(VLOOKUP($C70,FS_별도!$A:$AL,N$2,FALSE),0) -> 0 | O70: =IFERROR(VLOOKUP($C70,'FS_별도(분기누적)'!$A:$BS,O$2,FALSE),0) -> 0 | P70: =IFERROR(VLOOKUP($C70,'FS_별도(분기누적)'!$A:$BS,P$2,FALSE),0) -> 0 | Q70: =N70 -> 0 | R70: =Q70 -> 0 | S70: =R70 -> 0
B71: 단기만기보유금융자산 | C71: A113250.IP | D71: =IFERROR(VLOOKUP($C71,FS_별도!$A:$AL,D$2,FALSE),0) -> 0 | E71: =IFERROR(VLOOKUP($C71,FS_별도!$A:$AL,E$2,FALSE),0) -> 0 | F71: =IFERROR(VLOOKUP($C71,FS_별도!$A:$AL,F$2,FALSE),0) -> 0 | G71: =IFERROR(VLOOKUP($C71,FS_별도!$A:$AL,G$2,FALSE),0) -> 0 | H71: =IFERROR(VLOOKUP($C71,FS_별도!$A:$AL,H$2,FALSE),0) -> 0 | I71: =IFERROR(VLOOKUP($C71,FS_별도!$A:$AL,I$2,FALSE),0) -> 0 | J71: =IFERROR(VLOOKUP($C71,FS_별도!$A:$AL,J$2,FALSE),0) -> 0 | K71: =IFERROR(VLOOKUP($C71,FS_별도!$A:$AL,K$2,FALSE),0) -> 0 | ... N71: =IFERROR(VLOOKUP($C71,FS_별도!$A:$AL,N$2,FALSE),0) -> 0 | O71: =IFERROR(VLOOKUP($C71,'FS_별도(분기누적)'!$A:$BS,O$2,FALSE),0) -> 0 | P71: =IFERROR(VLOOKUP($C71,'FS_별도(분기누적)'!$A:$BS,P$2,FALSE),0) -> 0 | Q71: =N71 -> 0 | R71: =Q71 -> 0 | S71: =R71 -> 0
B72: 매출채권 | C72: A190560.IP | D72: =IFERROR(VLOOKUP($C72,FS_별도!$A:$AL,D$2,FALSE),0) -> 10.84 | E72: =IFERROR(VLOOKUP($C72,FS_별도!$A:$AL,E$2,FALSE),0) -> 9.53 | F72: =IFERROR(VLOOKUP($C72,FS_별도!$A:$AL,F$2,FALSE),0) -> 9.06 | G72: =IFERROR(VLOOKUP($C72,FS_별도!$A:$AL,G$2,FALSE),0) -> 11.33 | H72: =IFERROR(VLOOKUP($C72,FS_별도!$A:$AL,H$2,FALSE),0) -> 17.74 | I72: =IFERROR(VLOOKUP($C72,FS_별도!$A:$AL,I$2,FALSE),0) -> 17.77 | J72: =IFERROR(VLOOKUP($C72,FS_별도!$A:$AL,J$2,FALSE),0) -> 13.13 | K72: =IFERROR(VLOOKUP($C72,FS_별도!$A:$AL,K$2,FALSE),0) -> 22.68 | ... N72: =IFERROR(VLOOKUP($C72,FS_별도!$A:$AL,N$2,FALSE),0) -> 72.95 | O72: =IFERROR(VLOOKUP($C72,'FS_별도(분기누적)'!$A:$BS,O$2,FALSE),0) -> 63.62 | P72: =IFERROR(VLOOKUP($C72,'FS_별도(분기누적)'!$A:$BS,P$2,FALSE),0) -> 76.79 | Q72: =Q73*Q22/365 -> 0 | R72: =R73*R22/365 -> 0 | S72: =S73*S22/365 -> 0
B73: 회전기일 (매출액) | E73: =AVERAGE(E72,D72)/E22*365 -> 17.171809 | F73: =AVERAGE(F72,E72)/F22*365 -> 21.367143 | G73: =AVERAGE(G72,F72)/G22*365 -> 16.434108 | H73: =AVERAGE(H72,G72)/H22*365 -> 11.260267 | I73: =AVERAGE(I72,H72)/I22*365 -> 13.835262 | J73: =AVERAGE(J72,I72)/J22*365 -> 11.362583 | K73: =AVERAGE(K72,J72)/K22*365 -> 13.841042 | L73: =AVERAGE(L72,K72)/L22*365 -> 28.688625 | ... N73: =AVERAGE(N72,M72)/N22*365 -> 27.906467 | O73: =AVERAGE(O72,M72)/(O22*IF(RIGHT(O$3,2)="1Q",4,IF(RIGHT(O$3,2)="2Q",2,IF(RIGHT(O$3,2)="3Q",4/3,"0"))))*365 -> 26.837083 | P73: =AVERAGE(P72,N72)/(P22*IF(RIGHT(P$3,2)="1Q",4,IF(RIGHT(P$3,2)="2Q",2,IF(RIGHT(P$3,2)="3Q",4/3,"0"))))*365 -> 27.294251 | Q73: =AVERAGE(J73:N73) -> 22.307318 | R73: =Q73 -> 22.307318 | S73: =R73 -> 22.307318 | V73: 과거 평균
B74: 미수금 | C74: A190570.IP | D74: =IFERROR(VLOOKUP($C74,FS_별도!$A:$AL,D$2,FALSE),0) -> 3.39 | E74: =IFERROR(VLOOKUP($C74,FS_별도!$A:$AL,E$2,FALSE),0) -> 1.1 | F74: =IFERROR(VLOOKUP($C74,FS_별도!$A:$AL,F$2,FALSE),0) -> 0 | G74: =IFERROR(VLOOKUP($C74,FS_별도!$A:$AL,G$2,FALSE),0) -> 0 | H74: =IFERROR(VLOOKUP($C74,FS_별도!$A:$AL,H$2,FALSE),0) -> 0 | I74: =IFERROR(VLOOKUP($C74,FS_별도!$A:$AL,I$2,FALSE),0) -> 0 | J74: =IFERROR(VLOOKUP($C74,FS_별도!$A:$AL,J$2,FALSE),0) -> 0 | K74: =IFERROR(VLOOKUP($C74,FS_별도!$A:$AL,K$2,FALSE),0) -> 0 | ... N74: =IFERROR(VLOOKUP($C74,FS_별도!$A:$AL,N$2,FALSE),0) -> 4.89 | O74: =IFERROR(VLOOKUP($C74,'FS_별도(분기누적)'!$A:$BS,O$2,FALSE),0) -> 0.01 | P74: =IFERROR(VLOOKUP($C74,'FS_별도(분기누적)'!$A:$BS,P$2,FALSE),0) -> 0.06 | Q74: =Q75*Q22/365 -> 0 | R74: =R75*R22/365 -> 0 | S74: =S75*S22/365 -> 0
B75: 회전기일 (매출액) | E75: =AVERAGE(E74,D74)/E24*365 -> 3.5408565 | F75: =AVERAGE(F74,E74)/F24*365 -> 1.1622185 | G75: =AVERAGE(G74,F74)/G24*365 -> 0 | H75: =AVERAGE(H74,G74)/H24*365 -> 0 | I75: =AVERAGE(I74,H74)/I24*365 -> 0 | J75: =AVERAGE(J74,I74)/J24*365 -> 0 | K75: =AVERAGE(K74,J74)/K24*365 -> 0 | L75: =AVERAGE(L74,K74)/L24*365 -> 0.0028089023 | ... N75: =AVERAGE(N74,M74)/N24*365 -> 0.87474323 | O75: =AVERAGE(O74,M74)/(O24*IF(RIGHT(O$3,2)="1Q",4,IF(RIGHT(O$3,2)="2Q",2,IF(RIGHT(O$3,2)="3Q",4/3,"0"))))*365 -> 0.0035088057 | P75: =AVERAGE(P74,N74)/(P24*IF(RIGHT(P$3,2)="1Q",4,IF(RIGHT(P$3,2)="2Q",2,IF(RIGHT(P$3,2)="3Q",4/3,"0"))))*365 -> 0.92309225 | Q75: =AVERAGE(J75:N75) -> 0.17617485 | R75: =Q75 -> 0.17617485 | S75: =R75 -> 0.17617485
B76: 재고자산 | C76: A112840.IP | D76: =IFERROR(VLOOKUP($C76,FS_별도!$A:$AL,D$2,FALSE),0) -> 0 | E76: =IFERROR(VLOOKUP($C76,FS_별도!$A:$AL,E$2,FALSE),0) -> 4.2 | F76: =IFERROR(VLOOKUP($C76,FS_별도!$A:$AL,F$2,FALSE),0) -> 0 | G76: =IFERROR(VLOOKUP($C76,FS_별도!$A:$AL,G$2,FALSE),0) -> 0 | H76: =IFERROR(VLOOKUP($C76,FS_별도!$A:$AL,H$2,FALSE),0) -> 0 | I76: =IFERROR(VLOOKUP($C76,FS_별도!$A:$AL,I$2,FALSE),0) -> 0 | J76: =IFERROR(VLOOKUP($C76,FS_별도!$A:$AL,J$2,FALSE),0) -> 0 | K76: =IFERROR(VLOOKUP($C76,FS_별도!$A:$AL,K$2,FALSE),0) -> 0 | ... N76: =IFERROR(VLOOKUP($C76,FS_별도!$A:$AL,N$2,FALSE),0) -> 35.83 | O76: =IFERROR(VLOOKUP($C76,'FS_별도(분기누적)'!$A:$BS,O$2,FALSE),0) -> 29.91 | P76: =IFERROR(VLOOKUP($C76,'FS_별도(분기누적)'!$A:$BS,P$2,FALSE),0) -> 40.11 | Q76: =Q77*Q24/365 -> 0 | R76: =R77*R24/365 -> 0 | S76: =S77*S24/365 -> 0
B77: 회전기일 (매출액) | E77: =AVERAGE(E76,D76)/E22*365 -> 3.5405792 | F77: =AVERAGE(F76,E76)/F22*365 -> 4.8274342 | G77: =AVERAGE(G76,F76)/G22*365 -> 0 | H77: =AVERAGE(H76,G76)/H22*365 -> 0 | I77: =AVERAGE(I76,H76)/I22*365 -> 0 | J77: =AVERAGE(J76,I76)/J22*365 -> 0 | K77: =AVERAGE(K76,J76)/K22*365 -> 0 | L77: =AVERAGE(L76,K76)/L22*365 -> 20.610115 | ... N77: =AVERAGE(N76,M76)/N22*365 -> 17.809549 | O77: =AVERAGE(O76,M76)/(O22*IF(RIGHT(O$3,2)="1Q",4,IF(RIGHT(O$3,2)="2Q",2,IF(RIGHT(O$3,2)="3Q",4/3,"0"))))*365 -> 17.134546 | P77: =AVERAGE(P76,N76)/(P22*IF(RIGHT(P$3,2)="1Q",4,IF(RIGHT(P$3,2)="2Q",2,IF(RIGHT(P$3,2)="3Q",4/3,"0"))))*365 -> 13.842163 | Q77: =AVERAGE(J77:N77) -> 12.822403 | R77: =Q77 -> 12.822403 | S77: =R77 -> 12.822403 | V77: 과거 평균
B78: 선급금등 | C78: A190610.IP | D78: =IFERROR(VLOOKUP($C78,FS_별도!$A:$AL,D$2,FALSE),0) -> 0 | E78: =IFERROR(VLOOKUP($C78,FS_별도!$A:$AL,E$2,FALSE),0) -> 0.11 | F78: =IFERROR(VLOOKUP($C78,FS_별도!$A:$AL,F$2,FALSE),0) -> 0.22 | G78: =IFERROR(VLOOKUP($C78,FS_별도!$A:$AL,G$2,FALSE),0) -> 0 | H78: =IFERROR(VLOOKUP($C78,FS_별도!$A:$AL,H$2,FALSE),0) -> 0 | I78: =IFERROR(VLOOKUP($C78,FS_별도!$A:$AL,I$2,FALSE),0) -> 0 | J78: =IFERROR(VLOOKUP($C78,FS_별도!$A:$AL,J$2,FALSE),0) -> 0 | K78: =IFERROR(VLOOKUP($C78,FS_별도!$A:$AL,K$2,FALSE),0) -> 0 | ... N78: =IFERROR(VLOOKUP($C78,FS_별도!$A:$AL,N$2,FALSE),0) -> 4.84 | O78: =IFERROR(VLOOKUP($C78,'FS_별도(분기누적)'!$A:$BS,O$2,FALSE),0) -> 0.37 | P78: =IFERROR(VLOOKUP($C78,'FS_별도(분기누적)'!$A:$BS,P$2,FALSE),0) -> 3.46 | Q78: =N78 -> 4.84 | R78: =Q78 -> 4.84 | S78: =R78 -> 4.84
B79: Others | D79: =D81-D62-D63-D72-D76-D78 -> 6.01 | E79: =E81-E62-E63-E72-E76-E78 -> 7.07 | F79: =F81-F62-F63-F72-F76-F78 -> 1.96 | G79: =G81-G62-G63-G72-G76-G78 -> 11.61 | H79: =H81-H62-H63-H72-H76-H78 -> 8.33 | I79: =I81-I62-I63-I72-I76-I78 -> 6.91 | J79: =J81-J62-J63-J72-J76-J78 -> 22.32 | K79: =K81-K62-K63-K72-K76-K78 -> 3.88 | ... P79: =P81-P62-P63-P72-P76-P78 -> 359.07 | Q79: =Q80*Q22/365 -> 0 | R79: =R80*R22/365 -> 0 | S79: =S80*S22/365 -> 0
B80: 회전기일 (매출액) | E80: =AVERAGE(E79,D79)/E22*365 -> 11.026375 | F80: =AVERAGE(F79,E79)/F22*365 -> 10.378983 | G80: =AVERAGE(G79,F79)/G22*365 -> 10.937265 | H80: =AVERAGE(H79,G79)/H22*365 -> 7.723761 | I80: =AVERAGE(I79,H79)/I22*365 -> 5.9377468 | J80: =AVERAGE(J79,I79)/J22*365 -> 10.748489 | K80: =AVERAGE(K79,J79)/K22*365 -> 10.126649 | L80: =AVERAGE(L79,K79)/L22*365 -> 4.6414266 | ... N80: =AVERAGE(N79,M79)/N22*365 -> 5.5956032 | O80: =AVERAGE(O79,M79)/(O22*IF(RIGHT(O$3,2)="1Q",4,IF(RIGHT(O$3,2)="2Q",2,IF(RIGHT(O$3,2)="3Q",4/3,"0"))))*365 -> 5.7949639 | P80: =AVERAGE(P79,N79)/(P22*IF(RIGHT(P$3,2)="1Q",4,IF(RIGHT(P$3,2)="2Q",2,IF(RIGHT(P$3,2)="3Q",4/3,"0"))))*365 -> 67.178417 | Q80: =AVERAGE(J80:N80) -> 7.4668491 | R80: =Q80 -> 7.4668491 | S80: =R80 -> 7.4668491 | V80: 과거 평균
B81: 유동자산 | C81: A112830.IP | D81: =IFERROR(VLOOKUP($C81,FS_별도!$A:$AL,D$2,FALSE),0) -> 187.76 | E81: =IFERROR(VLOOKUP($C81,FS_별도!$A:$AL,E$2,FALSE),0) -> 202.41 | F81: =IFERROR(VLOOKUP($C81,FS_별도!$A:$AL,F$2,FALSE),0) -> 209.6 | G81: =IFERROR(VLOOKUP($C81,FS_별도!$A:$AL,G$2,FALSE),0) -> 228.54 | H81: =IFERROR(VLOOKUP($C81,FS_별도!$A:$AL,H$2,FALSE),0) -> 354.56 | I81: =IFERROR(VLOOKUP($C81,FS_별도!$A:$AL,I$2,FALSE),0) -> 168.49 | J81: =IFERROR(VLOOKUP($C81,FS_별도!$A:$AL,J$2,FALSE),0) -> 211.51 | K81: =IFERROR(VLOOKUP($C81,FS_별도!$A:$AL,K$2,FALSE),0) -> 212.39 | ... N81: =IFERROR(VLOOKUP($C81,FS_별도!$A:$AL,N$2,FALSE),0) -> 264.7 | O81: =IFERROR(VLOOKUP($C81,'FS_별도(분기누적)'!$A:$BS,O$2,FALSE),0) -> 344.16 | P81: =IFERROR(VLOOKUP($C81,'FS_별도(분기누적)'!$A:$BS,P$2,FALSE),0) -> 561.75 | Q81: =Q62+Q63+Q72+Q76+Q79+Q78+Q74 -> 319.68 | R81: =R62+R63+R72+R76+R79+R78+R74 -> 394.9195 | S81: =S62+S63+S72+S76+S79+S78+S74 -> 456.57204
B82: 투자부동산 | C82: A111330.IP | D82: =IFERROR(VLOOKUP($C82,FS_별도!$A:$AL,D$2,FALSE),0) -> 0 | E82: =IFERROR(VLOOKUP($C82,FS_별도!$A:$AL,E$2,FALSE),0) -> 0 | F82: =IFERROR(VLOOKUP($C82,FS_별도!$A:$AL,F$2,FALSE),0) -> 0 | G82: =IFERROR(VLOOKUP($C82,FS_별도!$A:$AL,G$2,FALSE),0) -> 0 | H82: =IFERROR(VLOOKUP($C82,FS_별도!$A:$AL,H$2,FALSE),0) -> 0 | I82: =IFERROR(VLOOKUP($C82,FS_별도!$A:$AL,I$2,FALSE),0) -> 0 | J82: =IFERROR(VLOOKUP($C82,FS_별도!$A:$AL,J$2,FALSE),0) -> 0 | K82: =IFERROR(VLOOKUP($C82,FS_별도!$A:$AL,K$2,FALSE),0) -> 0 | ... N82: =IFERROR(VLOOKUP($C82,FS_별도!$A:$AL,N$2,FALSE),0) -> 0 | O82: =IFERROR(VLOOKUP($C82,'FS_별도(분기누적)'!$A:$BS,O$2,FALSE),0) -> 0 | P82: =IFERROR(VLOOKUP($C82,'FS_별도(분기누적)'!$A:$BS,P$2,FALSE),0) -> 0 | Q82: =N82 -> 0 | R82: =Q82 -> 0 | S82: =R82 -> 0
B83: 관계기업등지분관련투자자산 | C83: A111450.IP | D83: =IFERROR(VLOOKUP($C83,FS_별도!$A:$AL,D$2,FALSE),0) -> 0 | E83: =IFERROR(VLOOKUP($C83,FS_별도!$A:$AL,E$2,FALSE),0) -> 0 | F83: =IFERROR(VLOOKUP($C83,FS_별도!$A:$AL,F$2,FALSE),0) -> 0 | G83: =IFERROR(VLOOKUP($C83,FS_별도!$A:$AL,G$2,FALSE),0) -> 0 | H83: =IFERROR(VLOOKUP($C83,FS_별도!$A:$AL,H$2,FALSE),0) -> 0 | I83: =IFERROR(VLOOKUP($C83,FS_별도!$A:$AL,I$2,FALSE),0) -> 0 | J83: =IFERROR(VLOOKUP($C83,FS_별도!$A:$AL,J$2,FALSE),0) -> 0 | K83: =IFERROR(VLOOKUP($C83,FS_별도!$A:$AL,K$2,FALSE),0) -> 0 | ... N83: =IFERROR(VLOOKUP($C83,FS_별도!$A:$AL,N$2,FALSE),0) -> 0 | O83: =IFERROR(VLOOKUP($C83,'FS_별도(분기누적)'!$A:$BS,O$2,FALSE),0) -> 0 | P83: =IFERROR(VLOOKUP($C83,'FS_별도(분기누적)'!$A:$BS,P$2,FALSE),0) -> 0 | Q83: =N83-Q172 -> 0 | R83: =Q83-R172 -> 0 | S83: =R83-S172 -> 0
B84: 유형자산 (토지) | C84: A190010.IP | D84: =IFERROR(VLOOKUP($C84,FS_별도!$A:$AL,D$2,FALSE),0) -> 63.35 | E84: =IFERROR(VLOOKUP($C84,FS_별도!$A:$AL,E$2,FALSE),0) -> 63.35 | F84: =IFERROR(VLOOKUP($C84,FS_별도!$A:$AL,F$2,FALSE),0) -> 63.35 | G84: =IFERROR(VLOOKUP($C84,FS_별도!$A:$AL,G$2,FALSE),0) -> 63.35 | H84: =IFERROR(VLOOKUP($C84,FS_별도!$A:$AL,H$2,FALSE),0) -> 92.9 | I84: =IFERROR(VLOOKUP($C84,FS_별도!$A:$AL,I$2,FALSE),0) -> 92.9 | J84: =IFERROR(VLOOKUP($C84,FS_별도!$A:$AL,J$2,FALSE),0) -> 92.9 | K84: =IFERROR(VLOOKUP($C84,FS_별도!$A:$AL,K$2,FALSE),0) -> 92.9 | ... N84: =IFERROR(VLOOKUP($C84,FS_별도!$A:$AL,N$2,FALSE),0) -> 171.58 | O84: =IFERROR(VLOOKUP($C84,'FS_별도(분기누적)'!$A:$BS,O$2,FALSE),0) -> 171.58 | P84: =IFERROR(VLOOKUP($C84,'FS_별도(분기누적)'!$A:$BS,P$2,FALSE),0) -> 142.03 | Q84: =N84 -> 171.58 | R84: =Q84 -> 171.58 | S84: =R84 -> 171.58
B85: 유형자산 (건물) | C85: A190030.IP | D85: =IFERROR(VLOOKUP($C85,FS_별도!$A:$AL,D$2,FALSE),0) -> 115.82 | E85: =IFERROR(VLOOKUP($C85,FS_별도!$A:$AL,E$2,FALSE),0) -> 111.42 | F85: =IFERROR(VLOOKUP($C85,FS_별도!$A:$AL,F$2,FALSE),0) -> 107.02 | G85: =IFERROR(VLOOKUP($C85,FS_별도!$A:$AL,G$2,FALSE),0) -> 102.62 | H85: =IFERROR(VLOOKUP($C85,FS_별도!$A:$AL,H$2,FALSE),0) -> 98.21 | I85: =IFERROR(VLOOKUP($C85,FS_별도!$A:$AL,I$2,FALSE),0) -> 368.01 | J85: =IFERROR(VLOOKUP($C85,FS_별도!$A:$AL,J$2,FALSE),0) -> 354.96 | K85: =IFERROR(VLOOKUP($C85,FS_별도!$A:$AL,K$2,FALSE),0) -> 332.51 | ... N85: =IFERROR(VLOOKUP($C85,FS_별도!$A:$AL,N$2,FALSE),0) -> 494.15 | O85: =IFERROR(VLOOKUP($C85,'FS_별도(분기누적)'!$A:$BS,O$2,FALSE),0) -> 504.36 | P85: =IFERROR(VLOOKUP($C85,'FS_별도(분기누적)'!$A:$BS,P$2,FALSE),0) -> 265.33 | Q85: =N85 -> 494.15 | R85: =Q85 -> 494.15 | S85: =R85 -> 494.15
B86: 유형자산 (토지,건물제외) | C86: A110020.IP | D86: =IFERROR(VLOOKUP($C86,FS_별도!$A:$AL,D$2,FALSE),0)-D84-D85 -> 250.4 | E86: =IFERROR(VLOOKUP($C86,FS_별도!$A:$AL,E$2,FALSE),0)-E84-E85 -> 176.22 | F86: =IFERROR(VLOOKUP($C86,FS_별도!$A:$AL,F$2,FALSE),0)-F84-F85 -> 101.77 | G86: =IFERROR(VLOOKUP($C86,FS_별도!$A:$AL,G$2,FALSE),0)-G84-G85 -> 275.9 | H86: =IFERROR(VLOOKUP($C86,FS_별도!$A:$AL,H$2,FALSE),0)-H84-H85 -> 654.12 | I86: =IFERROR(VLOOKUP($C86,FS_별도!$A:$AL,I$2,FALSE),0)-I84-I85 -> 603.29 | J86: =IFERROR(VLOOKUP($C86,FS_별도!$A:$AL,J$2,FALSE),0)-J84-J85 -> 596.41 | K86: =IFERROR(VLOOKUP($C86,FS_별도!$A:$AL,K$2,FALSE),0)-K84-K85 -> 463.18 | ... N86: =IFERROR(VLOOKUP($C86,FS_별도!$A:$AL,N$2,FALSE),0)-N84-N85 -> 553.2 | O86: =IFERROR(VLOOKUP($C86,'FS_별도(분기누적)'!$A:$BS,O$2,FALSE),0)-O84-O85 -> 828.07 | P86: =IFERROR(VLOOKUP($C86,'FS_별도(분기누적)'!$A:$BS,P$2,FALSE),0)-P84-P85 -> 453.45 | Q86: =Q216 -> 447.06 | R86: =R216 -> 372.0405 | S86: =S216 -> 310.60796
B87: 리스(사용권)자산 | C87: A112370.IP | D87: =IFERROR(VLOOKUP($C87,FS_별도!$A:$AL,D$2,FALSE),0) -> 0 | E87: =IFERROR(VLOOKUP($C87,FS_별도!$A:$AL,E$2,FALSE),0) -> 0 | F87: =IFERROR(VLOOKUP($C87,FS_별도!$A:$AL,F$2,FALSE),0) -> 0 | G87: =IFERROR(VLOOKUP($C87,FS_별도!$A:$AL,G$2,FALSE),0) -> 0 | H87: =IFERROR(VLOOKUP($C87,FS_별도!$A:$AL,H$2,FALSE),0) -> 0 | I87: =IFERROR(VLOOKUP($C87,FS_별도!$A:$AL,I$2,FALSE),0) -> 2.67 | J87: =IFERROR(VLOOKUP($C87,FS_별도!$A:$AL,J$2,FALSE),0) -> 12.55 | K87: =IFERROR(VLOOKUP($C87,FS_별도!$A:$AL,K$2,FALSE),0) -> 5.26 | ... N87: =IFERROR(VLOOKUP($C87,FS_별도!$A:$AL,N$2,FALSE),0) -> 6.8 | O87: =IFERROR(VLOOKUP($C87,'FS_별도(분기누적)'!$A:$BS,O$2,FALSE),0) -> 10.59 | P87: =IFERROR(VLOOKUP($C87,'FS_별도(분기누적)'!$A:$BS,P$2,FALSE),0) -> 3.88 | Q87: =N87 -> 6.8 | R87: =Q87 -> 6.8 | S87: =R87 -> 6.8
B88: 무형자산 | C88: A110610.IP | D88: =IFERROR(VLOOKUP($C88,FS_별도!$A:$AL,D$2,FALSE),0) -> 1.08 | E88: =IFERROR(VLOOKUP($C88,FS_별도!$A:$AL,E$2,FALSE),0) -> 1.41 | F88: =IFERROR(VLOOKUP($C88,FS_별도!$A:$AL,F$2,FALSE),0) -> 1.04 | G88: =IFERROR(VLOOKUP($C88,FS_별도!$A:$AL,G$2,FALSE),0) -> 0.85 | H88: =IFERROR(VLOOKUP($C88,FS_별도!$A:$AL,H$2,FALSE),0) -> 4.19 | I88: =IFERROR(VLOOKUP($C88,FS_별도!$A:$AL,I$2,FALSE),0) -> 3.56 | J88: =IFERROR(VLOOKUP($C88,FS_별도!$A:$AL,J$2,FALSE),0) -> 2.19 | K88: =IFERROR(VLOOKUP($C88,FS_별도!$A:$AL,K$2,FALSE),0) -> 7.73 | ... N88: =IFERROR(VLOOKUP($C88,FS_별도!$A:$AL,N$2,FALSE),0) -> 15.74 | O88: =IFERROR(VLOOKUP($C88,'FS_별도(분기누적)'!$A:$BS,O$2,FALSE),0) -> 19.23 | P88: =IFERROR(VLOOKUP($C88,'FS_별도(분기누적)'!$A:$BS,P$2,FALSE),0) -> 10.58 | Q88: =N88-Q155-Q156-Q171 -> 15.74 | R88: =Q88-R155-R156-R171 -> 15.74 | S88: =R88-S155-S156-S171 -> 15.74
B89: 이연법인세자산 | C89: A112340.IP | D89: =IFERROR(VLOOKUP($C89,FS_별도!$A:$AL,D$2,FALSE),0) -> 19.49 | E89: =IFERROR(VLOOKUP($C89,FS_별도!$A:$AL,E$2,FALSE),0) -> 15.46 | F89: =IFERROR(VLOOKUP($C89,FS_별도!$A:$AL,F$2,FALSE),0) -> 9.9 | G89: =IFERROR(VLOOKUP($C89,FS_별도!$A:$AL,G$2,FALSE),0) -> 8.77 | H89: =IFERROR(VLOOKUP($C89,FS_별도!$A:$AL,H$2,FALSE),0) -> 13.65 | I89: =IFERROR(VLOOKUP($C89,FS_별도!$A:$AL,I$2,FALSE),0) -> 25.1 | J89: =IFERROR(VLOOKUP($C89,FS_별도!$A:$AL,J$2,FALSE),0) -> 26.42 | K89: =IFERROR(VLOOKUP($C89,FS_별도!$A:$AL,K$2,FALSE),0) -> 39.8 | ... N89: =IFERROR(VLOOKUP($C89,FS_별도!$A:$AL,N$2,FALSE),0) -> 115.09 | O89: =IFERROR(VLOOKUP($C89,'FS_별도(분기누적)'!$A:$BS,O$2,FALSE),0) -> 105.34 | P89: =IFERROR(VLOOKUP($C89,'FS_별도(분기누적)'!$A:$BS,P$2,FALSE),0) -> 108.79 | Q89: =N89 -> 115.09 | R89: =Q89 -> 115.09 | S89: =R89 -> 115.09
B90: 비유동기타금융자산 | D90: =SUM(D91:D93) -> 0.56 | E90: =SUM(E91:E93) -> 0.8 | F90: =SUM(F91:F93) -> 1.04 | G90: =SUM(G91:G93) -> 8.37 | H90: =SUM(H91:H93) -> 13.05 | I90: =SUM(I91:I93) -> 7.52 | J90: =SUM(J91:J93) -> 1.73 | K90: =SUM(K91:K93) -> 4.18 | ... S90: =SUM(S91:S93) -> 0.6
B91: 기타금융자산 | C91: A111640.IP | D91: =IFERROR(VLOOKUP($C91,FS_별도!$A:$AL,D$2,FALSE),0) -> 0.56 | E91: =IFERROR(VLOOKUP($C91,FS_별도!$A:$AL,E$2,FALSE),0) -> 0.8 | F91: =IFERROR(VLOOKUP($C91,FS_별도!$A:$AL,F$2,FALSE),0) -> 1.04 | G91: =IFERROR(VLOOKUP($C91,FS_별도!$A:$AL,G$2,FALSE),0) -> 8.37 | H91: =IFERROR(VLOOKUP($C91,FS_별도!$A:$AL,H$2,FALSE),0) -> 13.05 | I91: =IFERROR(VLOOKUP($C91,FS_별도!$A:$AL,I$2,FALSE),0) -> 7.52 | J91: =IFERROR(VLOOKUP($C91,FS_별도!$A:$AL,J$2,FALSE),0) -> 1.73 | K91: =IFERROR(VLOOKUP($C91,FS_별도!$A:$AL,K$2,FALSE),0) -> 4.18 | ... N91: =IFERROR(VLOOKUP($C91,FS_별도!$A:$AL,N$2,FALSE),0) -> 0.6 | O91: =IFERROR(VLOOKUP($C91,'FS_별도(분기누적)'!$A:$BS,O$2,FALSE),0) -> 3.08 | P91: =IFERROR(VLOOKUP($C91,'FS_별도(분기누적)'!$A:$BS,P$2,FALSE),0) -> 0.42 | Q91: =N91 -> 0.6 | R91: =Q91 -> 0.6 | S91: =R91 -> 0.6
B92: 당기손익-공정가치측정금융자산 | C92: A115010.IP | D92: =IFERROR(VLOOKUP($C92,FS_별도!$A:$AL,D$2,FALSE),0) -> 0 | E92: =IFERROR(VLOOKUP($C92,FS_별도!$A:$AL,E$2,FALSE),0) -> 0 | F92: =IFERROR(VLOOKUP($C92,FS_별도!$A:$AL,F$2,FALSE),0) -> 0 | G92: =IFERROR(VLOOKUP($C92,FS_별도!$A:$AL,G$2,FALSE),0) -> 0 | H92: =IFERROR(VLOOKUP($C92,FS_별도!$A:$AL,H$2,FALSE),0) -> 0 | I92: =IFERROR(VLOOKUP($C92,FS_별도!$A:$AL,I$2,FALSE),0) -> 0 | J92: =IFERROR(VLOOKUP($C92,FS_별도!$A:$AL,J$2,FALSE),0) -> 0 | K92: =IFERROR(VLOOKUP($C92,FS_별도!$A:$AL,K$2,FALSE),0) -> 0 | ... N92: =IFERROR(VLOOKUP($C92,FS_별도!$A:$AL,N$2,FALSE),0) -> 0 | O92: =IFERROR(VLOOKUP($C92,'FS_별도(분기누적)'!$A:$BS,O$2,FALSE),0) -> 0 | P92: =IFERROR(VLOOKUP($C92,'FS_별도(분기누적)'!$A:$BS,P$2,FALSE),0) -> 0 | Q92: =N92 -> 0 | R92: =Q92 -> 0 | S92: =R92 -> 0
B93: 기타포괄손익-공정가치측정금융자산 | C93: A115020.IP | D93: =IFERROR(VLOOKUP($C93,FS_별도!$A:$AL,D$2,FALSE),0) -> 0 | E93: =IFERROR(VLOOKUP($C93,FS_별도!$A:$AL,E$2,FALSE),0) -> 0 | F93: =IFERROR(VLOOKUP($C93,FS_별도!$A:$AL,F$2,FALSE),0) -> 0 | G93: =IFERROR(VLOOKUP($C93,FS_별도!$A:$AL,G$2,FALSE),0) -> 0 | H93: =IFERROR(VLOOKUP($C93,FS_별도!$A:$AL,H$2,FALSE),0) -> 0 | I93: =IFERROR(VLOOKUP($C93,FS_별도!$A:$AL,I$2,FALSE),0) -> 0 | J93: =IFERROR(VLOOKUP($C93,FS_별도!$A:$AL,J$2,FALSE),0) -> 0 | K93: =IFERROR(VLOOKUP($C93,FS_별도!$A:$AL,K$2,FALSE),0) -> 0 | ... N93: =IFERROR(VLOOKUP($C93,FS_별도!$A:$AL,N$2,FALSE),0) -> 0 | O93: =IFERROR(VLOOKUP($C93,'FS_별도(분기누적)'!$A:$BS,O$2,FALSE),0) -> 0 | P93: =IFERROR(VLOOKUP($C93,'FS_별도(분기누적)'!$A:$BS,P$2,FALSE),0) -> 0 | Q93: =N93 -> 0 | R93: =Q93 -> 0 | S93: =R93 -> 0
B94: 장기매출채권및기타채권 | C94: A111930.IP | D94: =IFERROR(VLOOKUP($C94,FS_별도!$A:$AL,D$2,FALSE),0) -> 0.16 | E94: =IFERROR(VLOOKUP($C94,FS_별도!$A:$AL,E$2,FALSE),0) -> 0.43 | F94: =IFERROR(VLOOKUP($C94,FS_별도!$A:$AL,F$2,FALSE),0) -> 0.42 | G94: =IFERROR(VLOOKUP($C94,FS_별도!$A:$AL,G$2,FALSE),0) -> 0.5 | H94: =IFERROR(VLOOKUP($C94,FS_별도!$A:$AL,H$2,FALSE),0) -> 0.38 | I94: =IFERROR(VLOOKUP($C94,FS_별도!$A:$AL,I$2,FALSE),0) -> 1.99 | J94: =IFERROR(VLOOKUP($C94,FS_별도!$A:$AL,J$2,FALSE),0) -> 3.09 | K94: =IFERROR(VLOOKUP($C94,FS_별도!$A:$AL,K$2,FALSE),0) -> 2.48 | ... N94: =IFERROR(VLOOKUP($C94,FS_별도!$A:$AL,N$2,FALSE),0) -> 2.62 | O94: =IFERROR(VLOOKUP($C94,'FS_별도(분기누적)'!$A:$BS,O$2,FALSE),0) -> 3.72 | P94: =IFERROR(VLOOKUP($C94,'FS_별도(분기누적)'!$A:$BS,P$2,FALSE),0) -> 2.64 | Q94: =N94 -> 2.62 | R94: =Q94 -> 2.62 | S94: =R94 -> 2.62
B95: Others | D95: =D96-SUM(D82:D90)-D94 -> 8.1851192e-14 | E95: =E96-SUM(E82:E90)-E94 -> -5.0015547e-14 | F95: =F96-SUM(F82:F90)-F94 -> 1.59317e-14 | G95: =G96-SUM(G82:G90)-G94 -> 0.01 | H95: =H96-SUM(H82:H90)-H94 -> 0.56 | I95: =I96-SUM(I82:I90)-I94 -> 0.56 | J95: =J96-SUM(J82:J90)-J94 -> 2.48 | K95: =K96-SUM(K82:K90)-K94 -> 0.18 | ... P95: =P96-SUM(P82:P90)-P94 -> 1.01 | Q95: =N95 -> 0.4 | R95: =Q95 -> 0.4 | S95: =R95 -> 0.4
B96: 비유동자산 | C96: A110010.IP | D96: =IFERROR(VLOOKUP($C96,FS_별도!$A:$AL,D$2,FALSE),0) -> 450.86 | E96: =IFERROR(VLOOKUP($C96,FS_별도!$A:$AL,E$2,FALSE),0) -> 369.09 | F96: =IFERROR(VLOOKUP($C96,FS_별도!$A:$AL,F$2,FALSE),0) -> 284.54 | G96: =IFERROR(VLOOKUP($C96,FS_별도!$A:$AL,G$2,FALSE),0) -> 460.37 | H96: =IFERROR(VLOOKUP($C96,FS_별도!$A:$AL,H$2,FALSE),0) -> 877.06 | I96: =IFERROR(VLOOKUP($C96,FS_별도!$A:$AL,I$2,FALSE),0) -> 1105.6 | J96: =IFERROR(VLOOKUP($C96,FS_별도!$A:$AL,J$2,FALSE),0) -> 1092.73 | K96: =IFERROR(VLOOKUP($C96,FS_별도!$A:$AL,K$2,FALSE),0) -> 948.22 | ... N96: =IFERROR(VLOOKUP($C96,FS_별도!$A:$AL,N$2,FALSE),0) -> 1360.18 | O96: =IFERROR(VLOOKUP($C96,'FS_별도(분기누적)'!$A:$BS,O$2,FALSE),0) -> 1646.52 | P96: =IFERROR(VLOOKUP($C96,'FS_별도(분기누적)'!$A:$BS,P$2,FALSE),0) -> 988.13 | Q96: =Q82+Q83+Q86+Q88+Q89+Q95+Q90+Q84+Q85+Q87+Q94 -> 1254.04 | R96: =R82+R83+R86+R88+R89+R95+R90+R84+R85+R87+R94 -> 1179.0205 | S96: =S82+S83+S86+S88+S89+S95+S90+S84+S85+S87+S94 -> 1117.588
B97: 자산총계 | C97: A110000.IP | D97: =D81+D96 -> 638.62 | E97: =E81+E96 -> 571.5 | F97: =F81+F96 -> 494.14 | G97: =G81+G96 -> 688.91 | H97: =H81+H96 -> 1231.62 | I97: =I81+I96 -> 1274.09 | J97: =J81+J96 -> 1304.24 | K97: =K81+K96 -> 1160.61 | ... S97: =S81+S96 -> 1574.16
B98: 매입채무 | C98: A132010.IP | D98: =IFERROR(VLOOKUP($C98,FS_별도!$A:$AL,D$2,FALSE),0) -> 0 | E98: =IFERROR(VLOOKUP($C98,FS_별도!$A:$AL,E$2,FALSE),0) -> 0 | F98: =IFERROR(VLOOKUP($C98,FS_별도!$A:$AL,F$2,FALSE),0) -> 0 | G98: =IFERROR(VLOOKUP($C98,FS_별도!$A:$AL,G$2,FALSE),0) -> 0 | H98: =IFERROR(VLOOKUP($C98,FS_별도!$A:$AL,H$2,FALSE),0) -> 0 | I98: =IFERROR(VLOOKUP($C98,FS_별도!$A:$AL,I$2,FALSE),0) -> 0 | J98: =IFERROR(VLOOKUP($C98,FS_별도!$A:$AL,J$2,FALSE),0) -> 0 | K98: =IFERROR(VLOOKUP($C98,FS_별도!$A:$AL,K$2,FALSE),0) -> 0 | ... N98: =IFERROR(VLOOKUP($C98,FS_별도!$A:$AL,N$2,FALSE),0) -> 51.38 | O98: =IFERROR(VLOOKUP($C98,'FS_별도(분기누적)'!$A:$BS,O$2,FALSE),0) -> 25.51 | P98: =IFERROR(VLOOKUP($C98,'FS_별도(분기누적)'!$A:$BS,P$2,FALSE),0) -> 56.12 | Q98: =Q99*Q24/365 -> 0 | R98: =R99*R24/365 -> 0 | S98: =S99*S24/365 -> 0
B99: 회전기일 (매출액) | E99: =AVERAGE(E98,D98)/E22*365 -> 0 | F99: =AVERAGE(F98,E98)/F22*365 -> 0 | G99: =AVERAGE(G98,F98)/G22*365 -> 0 | H99: =AVERAGE(H98,G98)/H22*365 -> 0 | I99: =AVERAGE(I98,H98)/I22*365 -> 0 | J99: =AVERAGE(J98,I98)/J22*365 -> 0 | K99: =AVERAGE(K98,J98)/K22*365 -> 0 | L99: =AVERAGE(L98,K98)/L22*365 -> 17.061517 | ... N99: =AVERAGE(N98,M98)/N22*365 -> 16.416435 | O99: =AVERAGE(O98,M98)/(O22*IF(RIGHT(O$3,2)="1Q",4,IF(RIGHT(O$3,2)="2Q",2,IF(RIGHT(O$3,2)="3Q",4/3,"0"))))*365 -> 11.350466 | P99: =AVERAGE(P98,N98)/(P22*IF(RIGHT(P$3,2)="1Q",4,IF(RIGHT(P$3,2)="2Q",2,IF(RIGHT(P$3,2)="3Q",4/3,"0"))))*365 -> 19.594844 | Q99: =AVERAGE(J99:N99) -> 10.413262 | R99: =Q99 -> 10.413262 | S99: =R99 -> 10.413262 | V99: 과거 평균
B100: 유동계약부채 | C100: A115270.IP | D100: =IFERROR(VLOOKUP($C100,FS_별도!$A:$AL,D$2,FALSE),0) -> 0 | E100: =IFERROR(VLOOKUP($C100,FS_별도!$A:$AL,E$2,FALSE),0) -> 0 | F100: =IFERROR(VLOOKUP($C100,FS_별도!$A:$AL,F$2,FALSE),0) -> 0 | G100: =IFERROR(VLOOKUP($C100,FS_별도!$A:$AL,G$2,FALSE),0) -> 0 | H100: =IFERROR(VLOOKUP($C100,FS_별도!$A:$AL,H$2,FALSE),0) -> 0 | I100: =IFERROR(VLOOKUP($C100,FS_별도!$A:$AL,I$2,FALSE),0) -> 0 | J100: =IFERROR(VLOOKUP($C100,FS_별도!$A:$AL,J$2,FALSE),0) -> 0 | K100: =IFERROR(VLOOKUP($C100,FS_별도!$A:$AL,K$2,FALSE),0) -> 0 | ... N100: =IFERROR(VLOOKUP($C100,FS_별도!$A:$AL,N$2,FALSE),0) -> 0 | O100: =IFERROR(VLOOKUP($C100,'FS_별도(분기누적)'!$A:$BS,O$2,FALSE),0) -> 0 | P100: =IFERROR(VLOOKUP($C100,'FS_별도(분기누적)'!$A:$BS,P$2,FALSE),0) -> 0 | Q100: =N100 -> 0 | R100: =Q100 -> 0 | S100: =R100 -> 0
B101: 미지급금 | C101: A132070.IP | D101: =IFERROR(VLOOKUP($C101,FS_별도!$A:$AL,D$2,FALSE),0) -> 7.83 | E101: =IFERROR(VLOOKUP($C101,FS_별도!$A:$AL,E$2,FALSE),0) -> 5.83 | F101: =IFERROR(VLOOKUP($C101,FS_별도!$A:$AL,F$2,FALSE),0) -> 6.44 | G101: =IFERROR(VLOOKUP($C101,FS_별도!$A:$AL,G$2,FALSE),0) -> 33.23 | H101: =IFERROR(VLOOKUP($C101,FS_별도!$A:$AL,H$2,FALSE),0) -> 71.77 | I101: =IFERROR(VLOOKUP($C101,FS_별도!$A:$AL,I$2,FALSE),0) -> 24.95 | J101: =IFERROR(VLOOKUP($C101,FS_별도!$A:$AL,J$2,FALSE),0) -> 23.44 | K101: =IFERROR(VLOOKUP($C101,FS_별도!$A:$AL,K$2,FALSE),0) -> 11.44 | ... N101: =IFERROR(VLOOKUP($C101,FS_별도!$A:$AL,N$2,FALSE),0) -> 64.79 | O101: =IFERROR(VLOOKUP($C101,'FS_별도(분기누적)'!$A:$BS,O$2,FALSE),0) -> 64.73 | P101: =IFERROR(VLOOKUP($C101,'FS_별도(분기누적)'!$A:$BS,P$2,FALSE),0) -> 66.33 | Q101: =N101 -> 64.79 | R101: =Q101 -> 64.79 | S101: =R101 -> 64.79
B102: 선수금 | C102: A132350.IP | D102: =IFERROR(VLOOKUP($C102,FS_별도!$A:$AL,D$2,FALSE),0) -> 0 | E102: =IFERROR(VLOOKUP($C102,FS_별도!$A:$AL,E$2,FALSE),0) -> 0.17 | F102: =IFERROR(VLOOKUP($C102,FS_별도!$A:$AL,F$2,FALSE),0) -> 0 | G102: =IFERROR(VLOOKUP($C102,FS_별도!$A:$AL,G$2,FALSE),0) -> 0 | H102: =IFERROR(VLOOKUP($C102,FS_별도!$A:$AL,H$2,FALSE),0) -> 0 | I102: =IFERROR(VLOOKUP($C102,FS_별도!$A:$AL,I$2,FALSE),0) -> 0 | J102: =IFERROR(VLOOKUP($C102,FS_별도!$A:$AL,J$2,FALSE),0) -> 0 | K102: =IFERROR(VLOOKUP($C102,FS_별도!$A:$AL,K$2,FALSE),0) -> 0 | ... N102: =IFERROR(VLOOKUP($C102,FS_별도!$A:$AL,N$2,FALSE),0) -> 0.5 | O102: =IFERROR(VLOOKUP($C102,'FS_별도(분기누적)'!$A:$BS,O$2,FALSE),0) -> 0.2 | P102: =IFERROR(VLOOKUP($C102,'FS_별도(분기누적)'!$A:$BS,P$2,FALSE),0) -> 0.5 | Q102: =N102 -> 0.5 | R102: =Q102 -> 0.5 | S102: =R102 -> 0.5
B103: 기타(초과청구공사) | C103: A190970.IP | D103: =IFERROR(VLOOKUP($C103,FS_별도!$A:$AL,D$2,FALSE),0) -> 0 | E103: =IFERROR(VLOOKUP($C103,FS_별도!$A:$AL,E$2,FALSE),0) -> 0 | F103: =IFERROR(VLOOKUP($C103,FS_별도!$A:$AL,F$2,FALSE),0) -> 0 | G103: =IFERROR(VLOOKUP($C103,FS_별도!$A:$AL,G$2,FALSE),0) -> 0 | H103: =IFERROR(VLOOKUP($C103,FS_별도!$A:$AL,H$2,FALSE),0) -> 0 | I103: =IFERROR(VLOOKUP($C103,FS_별도!$A:$AL,I$2,FALSE),0) -> 0 | J103: =IFERROR(VLOOKUP($C103,FS_별도!$A:$AL,J$2,FALSE),0) -> 0 | K103: =IFERROR(VLOOKUP($C103,FS_별도!$A:$AL,K$2,FALSE),0) -> 0 | ... N103: =IFERROR(VLOOKUP($C103,FS_별도!$A:$AL,N$2,FALSE),0) -> 0 | O103: =IFERROR(VLOOKUP($C103,'FS_별도(분기누적)'!$A:$BS,O$2,FALSE),0) -> 0 | P103: =IFERROR(VLOOKUP($C103,'FS_별도(분기누적)'!$A:$BS,P$2,FALSE),0) -> 0 | Q103: =N103 -> 0 | R103: =Q103 -> 0 | S103: =R103 -> 0
...

Sheet Model_연결
B1: =B3&" Financial Statements" -> 연결 Financial Statements
B2: (억원, except per share data) | D2: =Model_별도!D2 -> 18 | E2: =Model_별도!E2 -> 19 | F2: =Model_별도!F2 -> 20 | G2: =Model_별도!G2 -> 21 | H2: =Model_별도!H2 -> 22 | I2: =Model_별도!I2 -> 23 | J2: =Model_별도!J2 -> 24 | K2: =Model_별도!K2 -> 25 | ... P2: =Model_별도!P2 -> 69 | Q2: 지우지마시오 (Vlookup 열순서)
B3: 연결 | C3: 과목코드 | D3: =Model_별도!D3 -> 2014 | E3: =Model_별도!E3 -> 2015 | F3: =Model_별도!F3 -> 2016 | G3: =Model_별도!G3 -> 2017 | H3: =Model_별도!H3 -> 2018 | I3: =Model_별도!I3 -> 2019 | J3: =Model_별도!J3 -> 2020 | K3: =Model_별도!K3 -> 2021 | ... S3: =Model_별도!S3 -> 2027E | W3: 연도 | X3: 매출액 | Y3: 영업이익 | Z3: 순이익 | AA3: 순부채비율
B4: 매출액 | D4: =D22 -> 0 | E4: =E22 -> 0 | F4: =F22 -> 0 | G4: =G22 -> 0 | H4: =H22 -> 0 | I4: =I22 -> 0 | J4: =J22 -> 0 | K4: =K22 -> 0 | ... S4: =S22 -> 0 | W4: '21 | X4: =L4 -> 0 | Y4: =N6 -> 0 | Z4: =N52 -> 0 | AA4: =N14/N131 -> #DIV/0!
B5: 매출성장률 | E5: =E4/D4-1 -> #DIV/0! | F5: =F4/E4-1 -> #DIV/0! | G5: =G4/F4-1 -> #DIV/0! | H5: =H4/G4-1 -> #DIV/0! | I5: =I4/H4-1 -> #DIV/0! | J5: =J4/I4-1 -> #DIV/0! | K5: =K4/J4-1 -> #DIV/0! | L5: =L4/K4-1 -> #DIV/0! | ... N5: =N4/M4-1 -> #DIV/0! | P5: =P4/O4-1 -> #DIV/0! | Q5: =Q4/N4-1 -> #DIV/0! | R5: =R4/Q4-1 -> -1 | S5: =S4/R4-1 -> #DIV/0!
B6: 영업이익 | D6: =D32 -> 0 | E6: =E32 -> 0 | F6: =F32 -> 0 | G6: =G32 -> 0 | H6: =H32 -> 0 | I6: =I32 -> 0 | J6: =J32 -> 0 | K6: =K32 -> 0 | ... S6: =S32 -> 0 | W6: '22 | X6: =M4 -> 0 | Y6: =M6 -> 0 | Z6: =M52 -> 0 | AA6: =M14/M131 -> #DIV/0!
B7: 영업이익률 | D7: =D6/D4 -> #DIV/0! | E7: =E6/E4 -> #DIV/0! | F7: =F6/F4 -> #DIV/0! | G7: =G6/G4 -> #DIV/0! | H7: =H6/H4 -> #DIV/0! | I7: =I6/I4 -> #DIV/0! | J7: =J6/J4 -> #DIV/0! | K7: =K6/K4 -> #DIV/0! | ... S7: =S6/S4 -> #DIV/0!
B8: 당기순이익 | D8: =D52 -> 0 | E8: =E52 -> 0 | F8: =F52 -> 0 | G8: =G52 -> 0 | H8: =H52 -> 0 | I8: =I52 -> 0 | J8: =J52 -> 0 | K8: =K52 -> 0 | ... S8: =S52 -> #DIV/0!
B9: EBITDA | D9: =D250 -> 0 | E9: =E250 -> 0 | F9: =F250 -> 0 | G9: =G250 -> 0 | H9: =H250 -> 0 | I9: =I250 -> 0 | J9: =J250 -> 0 | K9: =K250 -> 0 | ... S9: =S250 -> #DIV/0! | W9: '23 | X9: =N4 -> 0 | Y9: =L6 -> 0 | Z9: =L52 -> 0 | AA9: =L14/L131 -> #DIV/0!
B10: EBITDA/매출액 | D10: =D9/D4 -> #DIV/0! | E10: =E9/E4 -> #DIV/0! | F10: =F9/F4 -> #DIV/0! | G10: =G9/G4 -> #DIV/0! | H10: =H9/H4 -> #DIV/0! | I10: =I9/I4 -> #DIV/0! | J10: =J9/J4 -> #DIV/0! | K10: =K9/K4 -> #DIV/0! | ... S10: =S9/S4 -> #DIV/0!
B11: 자산총계 | D11: =D97 -> 0 | E11: =E97 -> 0 | F11: =F97 -> 0 | G11: =G97 -> 0 | H11: =H97 -> 0 | I11: =I97 -> 0 | J11: =J97 -> 0 | K11: =K97 -> 0 | ... S11: =S97 -> #DIV/0!
B12: 부동산(토지+건물) | D12: =D82+D84+D85 -> 0 | E12: =E82+E84+E85 -> 0 | F12: =F82+F84+F85 -> 0 | G12: =G82+G84+G85 -> 0 | H12: =H82+H84+H85 -> 0 | I12: =I82+I84+I85 -> 0 | J12: =J82+J84+J85 -> 0 | K12: =K82+K84+K85 -> 0 | ... S12: =S82+S84+S85 -> 0
B13: 총차입금 | D13: =D105+D114 -> 0 | E13: =E105+E114 -> 0 | F13: =F105+F114 -> 0 | G13: =G105+G114 -> 0 | H13: =H105+H114 -> 0 | I13: =I105+I114 -> 0 | J13: =J105+J114 -> 0 | K13: =K105+K114 -> 0 | ... S13: =S105+S114 -> 200
B14: 순차입금 | D14: =D105+D114-D62-D63-D90 -> 0 | E14: =E105+E114-E62-E63-E90 -> 0 | F14: =F105+F114-F62-F63-F90 -> 0 | G14: =G105+G114-G62-G63-G90 -> 0 | H14: =H105+H114-H62-H63-H90 -> 0 | I14: =I105+I114-I62-I63-I90 -> 0 | J14: =J105+J114-J62-J63-J90 -> 0 | K14: =K105+K114-K62-K63-K90 -> 0 | ... S14: =S105+S114-S62-S63-S90 -> #DIV/0!
B15: 영업활동CF | D15: =D169 -> 0 | E15: =E169 -> 0 | F15: =F169 -> 0 | G15: =G169 -> 0 | H15: =H169 -> 0 | I15: =I169 -> 0 | J15: =J169 -> 0 | K15: =K169 -> 0 | ... S15: =S169 -> #DIV/0!
B16: 유무형자산투자 | D16: =D170+D171 -> 0 | E16: =E170+E171 -> 0 | F16: =F170+F171 -> 0 | G16: =G170+G171 -> 0 | H16: =H170+H171 -> 0 | I16: =I170+I171 -> 0 | J16: =J170+J171 -> 0 | K16: =K170+K171 -> 0 | ... S16: =S170+S171 -> #DIV/0!
B17: 순차입금/EBITDA | D17: =D14/D9 -> #DIV/0! | E17: =E14/E9 -> #DIV/0! | F17: =F14/F9 -> #DIV/0! | G17: =G14/G9 -> #DIV/0! | H17: =H14/H9 -> #DIV/0! | I17: =I14/I9 -> #DIV/0! | J17: =J14/J9 -> #DIV/0! | K17: =K14/K9 -> #DIV/0! | ... N17: =N14/N9 -> #DIV/0! | O17: =O14/(O9*IF(RIGHT(O$3,2)="1Q",4,IF(RIGHT(O$3,2)="2Q",2,IF(RIGHT(O$3,2)="3Q",4/3,"0")))) -> #DIV/0! | P17: =P14/(P9*IF(RIGHT(P$3,2)="1Q",4,IF(RIGHT(P$3,2)="2Q",2,IF(RIGHT(P$3,2)="3Q",4/3,"0")))) -> #DIV/0! | Q17: =Q14/Q9 -> #DIV/0! | R17: =R14/R9 -> #DIV/0! | S17: =S14/S9 -> #DIV/0!
B18: 부채비율 | D18: =D123/D131 -> #DIV/0! | E18: =E123/E131 -> #DIV/0! | F18: =F123/F131 -> #DIV/0! | G18: =G123/G131 -> #DIV/0! | H18: =H123/H131 -> #DIV/0! | I18: =I123/I131 -> #DIV/0! | J18: =J123/J131 -> #DIV/0! | K18: =K123/K131 -> #DIV/0! | ... S18: =S123/S131 -> #DIV/0!
B19: 차입금의존도 | D19: =(D105+D114)/D97 -> #DIV/0! | E19: =(E105+E114)/E97 -> #DIV/0! | F19: =(F105+F114)/F97 -> #DIV/0! | G19: =(G105+G114)/G97 -> #DIV/0! | H19: =(H105+H114)/H97 -> #DIV/0! | I19: =(I105+I114)/I97 -> #DIV/0! | J19: =(J105+J114)/J97 -> #DIV/0! | K19: =(K105+K114)/K97 -> #DIV/0! | ... S19: =(S105+S114)/S97 -> #DIV/0!
B21: INCOME STATEMENT (억원) | D21: =D$3 -> 2014 | E21: =E$3 -> 2015 | F21: =F$3 -> 2016 | G21: =G$3 -> 2017 | H21: =H$3 -> 2018 | I21: =I$3 -> 2019 | J21: =J$3 -> 2020 | K21: =K$3 -> 2021 | ... S21: =S$3 -> 2027E
B22: 매출액(수익) | C22: A200000.IC | D22: =IFERROR(VLOOKUP($C22,FS_연결!$A:$Z,D$2,FALSE),0) -> 0 | E22: =IFERROR(VLOOKUP($C22,FS_연결!$A:$Z,E$2,FALSE),0) -> 0 | F22: =IFERROR(VLOOKUP($C22,FS_연결!$A:$Z,F$2,FALSE),0) -> 0 | G22: =IFERROR(VLOOKUP($C22,FS_연결!$A:$Z,G$2,FALSE),0) -> 0 | H22: =IFERROR(VLOOKUP($C22,FS_연결!$A:$Z,H$2,FALSE),0) -> 0 | I22: =IFERROR(VLOOKUP($C22,FS_연결!$A:$Z,I$2,FALSE),0) -> 0 | J22: =IFERROR(VLOOKUP($C22,FS_연결!$A:$Z,J$2,FALSE),0) -> 0 | K22: =IFERROR(VLOOKUP($C22,FS_연결!$A:$Z,K$2,FALSE),0) -> 0 | L22: =IFERROR(VLOOKUP($C22,FS_연결!$A:$Z,L$2,FALSE),0) -> 0 | M22: =IFERROR(VLOOKUP($C22,FS_연결!$A:$AL,M$2,FALSE),0) -> 0 | N22: =IFERROR(VLOOKUP($C22,FS_연결!$A:$AL,N$2,FALSE),0) -> 0 | O22: =IFERROR(VLOOKUP($C22,'FS_연결(분기누적)'!$A:$BS,O$2,FALSE),0) -> 0 | P22: =IFERROR(VLOOKUP($C22,'FS_연결(분기누적)'!$A:$BS,P$2,FALSE),0) -> 0 | Q22: =컨센!F15/100000 -> 1051 | R22: =컨센!G15/100000 -> 0 | S22: =컨센!H15/100000 -> 0
B23: Growth (%) | D23: - | E23: =E22/D22-1 -> #DIV/0! | F23: =F22/E22-1 -> #DIV/0! | G23: =G22/F22-1 -> #DIV/0! | H23: =H22/G22-1 -> #DIV/0! | I23: =I22/H22-1 -> #DIV/0! | J23: =J22/I22-1 -> #DIV/0! | K23: =K22/J22-1 -> #DIV/0! | L23: =L22/K22-1 -> #DIV/0! | ... N23: =N22/M22-1 -> #DIV/0! | P23: =P22/O22-1 -> #DIV/0! | Q23: =Q22/N22-1 -> #DIV/0! | R23: =R22/Q22-1 -> -1 | S23: =S22/R22-1 -> #DIV/0!
B24: 매출원가 | C24: A200360.IC | D24: =IFERROR(VLOOKUP($C24,FS_연결!$A:$Z,D$2,FALSE),0) -> 0 | E24: =IFERROR(VLOOKUP($C24,FS_연결!$A:$Z,E$2,FALSE),0) -> 0 | F24: =IFERROR(VLOOKUP($C24,FS_연결!$A:$Z,F$2,FALSE),0) -> 0 | G24: =IFERROR(VLOOKUP($C24,FS_연결!$A:$Z,G$2,FALSE),0) -> 0 | H24: =IFERROR(VLOOKUP($C24,FS_연결!$A:$Z,H$2,FALSE),0) -> 0 | I24: =IFERROR(VLOOKUP($C24,FS_연결!$A:$Z,I$2,FALSE),0) -> 0 | J24: =IFERROR(VLOOKUP($C24,FS_연결!$A:$Z,J$2,FALSE),0) -> 0 | K24: =IFERROR(VLOOKUP($C24,FS_연결!$A:$Z,K$2,FALSE),0) -> 0 | L24: =IFERROR(VLOOKUP($C24,FS_연결!$A:$Z,L$2,FALSE),0) -> 0 | M24: =IFERROR(VLOOKUP($C24,FS_연결!$A:$AL,M$2,FALSE),0) -> 0 | N24: =IFERROR(VLOOKUP($C24,FS_연결!$A:$AL,N$2,FALSE),0) -> 0 | O24: =IFERROR(VLOOKUP($C24,'FS_연결(분기누적)'!$A:$BS,O$2,FALSE),0) -> 0 | P24: =IFERROR(VLOOKUP($C24,'FS_연결(분기누적)'!$A:$BS,P$2,FALSE),0) -> 0 | Q24: =Q22*Q25 -> #DIV/0! | R24: =R22*R25 -> #DIV/0! | S24: =S22*S25 -> #DIV/0!
B25: % of sales | D25: =D24/D22 -> #DIV/0! | E25: =E24/E22 -> #DIV/0! | F25: =F24/F22 -> #DIV/0! | G25: =G24/G22 -> #DIV/0! | H25: =H24/H22 -> #DIV/0! | I25: =I24/I22 -> #DIV/0! | J25: =J24/J22 -> #DIV/0! | K25: =K24/K22 -> #DIV/0! | ... P25: =P24/P22 -> #DIV/0! | Q25: =N25 -> #DIV/0! | R25: =Q25-0.002 -> #DIV/0! | S25: =R25-0.002 -> #DIV/0!
B26: 매출총이익 | D26: =D22-D24 -> 0 | E26: =E22-E24 -> 0 | F26: =F22-F24 -> 0 | G26: =G22-G24 -> 0 | H26: =H22-H24 -> 0 | I26: =I22-I24 -> 0 | J26: =J22-J24 -> 0 | K26: =K22-K24 -> 0 | ... S26: =S22-S24 -> #DIV/0!
B27: Gross margin (%) | D27: =D26/D22 -> #DIV/0! | E27: =E26/E22 -> #DIV/0! | F27: =F26/F22 -> #DIV/0! | G27: =G26/G22 -> #DIV/0! | H27: =H26/H22 -> #DIV/0! | I27: =I26/I22 -> #DIV/0! | J27: =J26/J22 -> #DIV/0! | K27: =K26/K22 -> #DIV/0! | ... S27: =S26/S22 -> #DIV/0!
B28: 연구개발비 | C28: A201130.IC | D28: =IFERROR(VLOOKUP($C28,FS_연결!$A:$Z,D$2,FALSE),0) -> 0 | E28: =IFERROR(VLOOKUP($C28,FS_연결!$A:$Z,E$2,FALSE),0) -> 0 | F28: =IFERROR(VLOOKUP($C28,FS_연결!$A:$Z,F$2,FALSE),0) -> 0 | G28: =IFERROR(VLOOKUP($C28,FS_연결!$A:$Z,G$2,FALSE),0) -> 0 | H28: =IFERROR(VLOOKUP($C28,FS_연결!$A:$Z,H$2,FALSE),0) -> 0 | I28: =IFERROR(VLOOKUP($C28,FS_연결!$A:$Z,I$2,FALSE),0) -> 0 | J28: =IFERROR(VLOOKUP($C28,FS_연결!$A:$Z,J$2,FALSE),0) -> 0 | K28: =IFERROR(VLOOKUP($C28,FS_연결!$A:$Z,K$2,FALSE),0) -> 0 | L28: =IFERROR(VLOOKUP($C28,FS_연결!$A:$Z,L$2,FALSE),0) -> 0 | M28: =IFERROR(VLOOKUP($C28,FS_연결!$A:$AL,M$2,FALSE),0) -> 0 | N28: =IFERROR(VLOOKUP($C28,FS_연결!$A:$AL,N$2,FALSE),0) -> 0 | O28: =IFERROR(VLOOKUP($C28,'FS_연결(분기누적)'!$A:$BS,O$2,FALSE),0) -> 0 | P28: =IFERROR(VLOOKUP($C28,'FS_연결(분기누적)'!$A:$BS,P$2,FALSE),0) -> 0 | Q28: =Q29*Q$22 -> #DIV/0! | R28: =R29*R$22 -> #DIV/0! | S28: =S29*S$22 -> #DIV/0!
B29: % of sales | D29: =D28/D22 -> #DIV/0! | E29: =E28/E22 -> #DIV/0! | F29: =F28/F22 -> #DIV/0! | G29: =G28/G22 -> #DIV/0! | H29: =H28/H22 -> #DIV/0! | I29: =I28/I22 -> #DIV/0! | J29: =J28/J22 -> #DIV/0! | K29: =K28/K22 -> #DIV/0! | ... P29: =P28/P22 -> #DIV/0! | Q29: =P29 -> #DIV/0! | R29: =N29 -> #DIV/0! | S29: =L29 -> #DIV/0!
B30: 판매비와관리비(R&D제외) | D30: =D26-D28-D32 -> 0 | E30: =E26-E28-E32 -> 0 | F30: =F26-F28-F32 -> 0 | G30: =G26-G28-G32 -> 0 | H30: =H26-H28-H32 -> 0 | I30: =I26-I28-I32 -> 0 | J30: =J26-J28-J32 -> 0 | K30: =K26-K28-K32 -> 0 | ... S30: =S26-S28-S32 -> #DIV/0!
B31: % of sales | D31: =D30/D22 -> #DIV/0! | E31: =E30/E22 -> #DIV/0! | F31: =F30/F22 -> #DIV/0! | G31: =G30/G22 -> #DIV/0! | H31: =H30/H22 -> #DIV/0! | I31: =I30/I22 -> #DIV/0! | J31: =J30/J22 -> #DIV/0! | K31: =K30/K22 -> #DIV/0! | ... S31: =S30/S22 -> #DIV/0!
B32: 영업이익 | C32: A201370.IC | D32: =IFERROR(VLOOKUP($C32,FS_연결!$A:$Z,D$2,FALSE),0) -> 0 | E32: =IFERROR(VLOOKUP($C32,FS_연결!$A:$Z,E$2,FALSE),0) -> 0 | F32: =IFERROR(VLOOKUP($C32,FS_연결!$A:$Z,F$2,FALSE),0) -> 0 | G32: =IFERROR(VLOOKUP($C32,FS_연결!$A:$Z,G$2,FALSE),0) -> 0 | H32: =IFERROR(VLOOKUP($C32,FS_연결!$A:$Z,H$2,FALSE),0) -> 0 | I32: =IFERROR(VLOOKUP($C32,FS_연결!$A:$Z,I$2,FALSE),0) -> 0 | J32: =IFERROR(VLOOKUP($C32,FS_연결!$A:$Z,J$2,FALSE),0) -> 0 | K32: =IFERROR(VLOOKUP($C32,FS_연결!$A:$Z,K$2,FALSE),0) -> 0 | L32: =IFERROR(VLOOKUP($C32,FS_연결!$A:$Z,L$2,FALSE),0) -> 0 | M32: =IFERROR(VLOOKUP($C32,FS_연결!$A:$AL,M$2,FALSE),0) -> 0 | N32: =IFERROR(VLOOKUP($C32,FS_연결!$A:$AL,N$2,FALSE),0) -> 0 | O32: =IFERROR(VLOOKUP($C32,'FS_연결(분기누적)'!$A:$BS,O$2,FALSE),0) -> 0 | P32: =IFERROR(VLOOKUP($C32,'FS_연결(분기누적)'!$A:$BS,P$2,FALSE),0) -> 0 | Q32: =컨센!K15/100000 -> 12 | R32: =컨센!L15/100000 -> 0 | S32: =컨센!M15/100000 -> 0
B33: Operating profit margin (%) | D33: =D32/D22 -> #DIV/0! | E33: =E32/E22 -> #DIV/0! | F33: =F32/F22 -> #DIV/0! | G33: =G32/G22 -> #DIV/0! | H33: =H32/H22 -> #DIV/0! | I33: =I32/I22 -> #DIV/0! | J33: =J32/J22 -> #DIV/0! | K33: =K32/K22 -> #DIV/0! | ... S33: =S32/S22 -> #DIV/0!
B34: 종속기업,공동지배기업및관계기업관련손익 | C34: A202880.IC | D34: =IFERROR(VLOOKUP($C34,FS_연결!$A:$Z,D$2,FALSE),0) -> 0 | E34: =IFERROR(VLOOKUP($C34,FS_연결!$A:$Z,E$2,FALSE),0) -> 0 | F34: =IFERROR(VLOOKUP($C34,FS_연결!$A:$Z,F$2,FALSE),0) -> 0 | G34: =IFERROR(VLOOKUP($C34,FS_연결!$A:$Z,G$2,FALSE),0) -> 0 | H34: =IFERROR(VLOOKUP($C34,FS_연결!$A:$Z,H$2,FALSE),0) -> 0 | I34: =IFERROR(VLOOKUP($C34,FS_연결!$A:$Z,I$2,FALSE),0) -> 0 | J34: =IFERROR(VLOOKUP($C34,FS_연결!$A:$Z,J$2,FALSE),0) -> 0 | K34: =IFERROR(VLOOKUP($C34,FS_연결!$A:$Z,K$2,FALSE),0) -> 0 | L34: =IFERROR(VLOOKUP($C34,FS_연결!$A:$Z,L$2,FALSE),0) -> 0 | M34: =IFERROR(VLOOKUP($C34,FS_연결!$A:$AL,M$2,FALSE),0) -> 0 | N34: =IFERROR(VLOOKUP($C34,FS_연결!$A:$AL,N$2,FALSE),0) -> 0 | O34: =IFERROR(VLOOKUP($C34,'FS_연결(분기누적)'!$A:$BS,O$2,FALSE),0) -> 0 | P34: =IFERROR(VLOOKUP($C34,'FS_연결(분기누적)'!$A:$BS,P$2,FALSE),0) -> 0
B35: 금융수익 | C35: A202210.IC | D35: =IFERROR(VLOOKUP($C35,FS_연결!$A:$Z,D$2,FALSE),0) -> 0 | E35: =IFERROR(VLOOKUP($C35,FS_연결!$A:$Z,E$2,FALSE),0) -> 0 | F35: =IFERROR(VLOOKUP($C35,FS_연결!$A:$Z,F$2,FALSE),0) -> 0 | G35: =IFERROR(VLOOKUP($C35,FS_연결!$A:$Z,G$2,FALSE),0) -> 0 | H35: =IFERROR(VLOOKUP($C35,FS_연결!$A:$Z,H$2,FALSE),0) -> 0 | I35: =IFERROR(VLOOKUP($C35,FS_연결!$A:$Z,I$2,FALSE),0) -> 0 | J35: =IFERROR(VLOOKUP($C35,FS_연결!$A:$Z,J$2,FALSE),0) -> 0 | K35: =IFERROR(VLOOKUP($C35,FS_연결!$A:$Z,K$2,FALSE),0) -> 0 | L35: =IFERROR(VLOOKUP($C35,FS_연결!$A:$Z,L$2,FALSE),0) -> 0 | M35: =IFERROR(VLOOKUP($C35,FS_연결!$A:$AL,M$2,FALSE),0) -> 0 | N35: =IFERROR(VLOOKUP($C35,FS_연결!$A:$AL,N$2,FALSE),0) -> 0 | O35: =IFERROR(VLOOKUP($C35,'FS_연결(분기누적)'!$A:$BS,O$2,FALSE),0) -> 0 | P35: =IFERROR(VLOOKUP($C35,'FS_연결(분기누적)'!$A:$BS,P$2,FALSE),0) -> 0 | Q35: =Q36+Q37+Q38 -> 0 | R35: =R36+R37+R38 -> #DIV/0! | S35: =S36+S37+S38 -> #DIV/0!
B36: 이자수익 | C36: A202220.IC | D36: =IFERROR(VLOOKUP($C36,FS_연결!$A:$Z,D$2,FALSE),0) -> 0 | E36: =IFERROR(VLOOKUP($C36,FS_연결!$A:$Z,E$2,FALSE),0) -> 0 | F36: =IFERROR(VLOOKUP($C36,FS_연결!$A:$Z,F$2,FALSE),0) -> 0 | G36: =IFERROR(VLOOKUP($C36,FS_연결!$A:$Z,G$2,FALSE),0) -> 0 | H36: =IFERROR(VLOOKUP($C36,FS_연결!$A:$Z,H$2,FALSE),0) -> 0 | I36: =IFERROR(VLOOKUP($C36,FS_연결!$A:$Z,I$2,FALSE),0) -> 0 | J36: =IFERROR(VLOOKUP($C36,FS_연결!$A:$Z,J$2,FALSE),0) -> 0 | K36: =IFERROR(VLOOKUP($C36,FS_연결!$A:$Z,K$2,FALSE),0) -> 0 | L36: =IFERROR(VLOOKUP($C36,FS_연결!$A:$Z,L$2,FALSE),0) -> 0 | M36: =IFERROR(VLOOKUP($C36,FS_연결!$A:$AL,M$2,FALSE),0) -> 0 | N36: =IFERROR(VLOOKUP($C36,FS_연결!$A:$AL,N$2,FALSE),0) -> 0 | O36: =IFERROR(VLOOKUP($C36,'FS_연결(분기누적)'!$A:$BS,O$2,FALSE),0) -> 0 | P36: =IFERROR(VLOOKUP($C36,'FS_연결(분기누적)'!$A:$BS,P$2,FALSE),0) -> 0 | Q36: =Q226 -> 0 | R36: =R226 -> #DIV/0! | S36: =S226 -> #DIV/0! | W36: 구분 | X36: 23E | Y36: 24E | Z36: 25E
B37: 외환거래이익 | C37: A202240.IC | D37: =IFERROR(VLOOKUP($C37,FS_연결!$A:$Z,D$2,FALSE),0) -> 0 | E37: =IFERROR(VLOOKUP($C37,FS_연결!$A:$Z,E$2,FALSE),0) -> 0 | F37: =IFERROR(VLOOKUP($C37,FS_연결!$A:$Z,F$2,FALSE),0) -> 0 | G37: =IFERROR(VLOOKUP($C37,FS_연결!$A:$Z,G$2,FALSE),0) -> 0 | H37: =IFERROR(VLOOKUP($C37,FS_연결!$A:$Z,H$2,FALSE),0) -> 0 | I37: =IFERROR(VLOOKUP($C37,FS_연결!$A:$Z,I$2,FALSE),0) -> 0 | J37: =IFERROR(VLOOKUP($C37,FS_연결!$A:$Z,J$2,FALSE),0) -> 0 | K37: =IFERROR(VLOOKUP($C37,FS_연결!$A:$Z,K$2,FALSE),0) -> 0 | L37: =IFERROR(VLOOKUP($C37,FS_연결!$A:$Z,L$2,FALSE),0) -> 0 | M37: =IFERROR(VLOOKUP($C37,FS_연결!$A:$AL,M$2,FALSE),0) -> 0 | N37: =IFERROR(VLOOKUP($C37,FS_연결!$A:$AL,N$2,FALSE),0) -> 0 | O37: =IFERROR(VLOOKUP($C37,'FS_연결(분기누적)'!$A:$BS,O$2,FALSE),0) -> 0 | P37: =IFERROR(VLOOKUP($C37,'FS_연결(분기누적)'!$A:$BS,P$2,FALSE),0) -> 0 | W37: 시가총액 | X37: =Valuation!C27 -> 0
B38: 기타금융수익 | D38: =D35-D36-D37 -> 0 | E38: =E35-E36-E37 -> 0 | F38: =F35-F36-F37 -> 0 | G38: =G35-G36-G37 -> 0 | H38: =H35-H36-H37 -> 0 | I38: =I35-I36-I37 -> 0 | J38: =J35-J36-J37 -> 0 | K38: =K35-K36-K37 -> 0 | ... P38: =P35-P36-P37 -> 0 | Q38: 0 | R38: 0 | S38: 0 | W38: NI | X38: =Q44 -> #DIV/0! | Y38: =R44 -> #DIV/0! | Z38: =S44 -> #DIV/0!
B39: 금융원가 | C39: A202550.IC | D39: =IFERROR(VLOOKUP($C39,FS_연결!$A:$Z,D$2,FALSE),0) -> 0 | E39: =IFERROR(VLOOKUP($C39,FS_연결!$A:$Z,E$2,FALSE),0) -> 0 | F39: =IFERROR(VLOOKUP($C39,FS_연결!$A:$Z,F$2,FALSE),0) -> 0 | G39: =IFERROR(VLOOKUP($C39,FS_연결!$A:$Z,G$2,FALSE),0) -> 0 | H39: =IFERROR(VLOOKUP($C39,FS_연결!$A:$Z,H$2,FALSE),0) -> 0 | I39: =IFERROR(VLOOKUP($C39,FS_연결!$A:$Z,I$2,FALSE),0) -> 0 | J39: =IFERROR(VLOOKUP($C39,FS_연결!$A:$Z,J$2,FALSE),0) -> 0 | K39: =IFERROR(VLOOKUP($C39,FS_연결!$A:$Z,K$2,FALSE),0) -> 0 | L39: =IFERROR(VLOOKUP($C39,FS_연결!$A:$Z,L$2,FALSE),0) -> 0 | M39: =IFERROR(VLOOKUP($C39,FS_연결!$A:$AL,M$2,FALSE),0) -> 0 | N39: =IFERROR(VLOOKUP($C39,FS_연결!$A:$AL,N$2,FALSE),0) -> 0 | O39: =IFERROR(VLOOKUP($C39,'FS_연결(분기누적)'!$A:$BS,O$2,FALSE),0) -> 0 | P39: =IFERROR(VLOOKUP($C39,'FS_연결(분기누적)'!$A:$BS,P$2,FALSE),0) -> 0 | Q39: =Q40+Q41+Q42 -> #DIV/0! | R39: =R40+R41+R42 -> #DIV/0! | S39: =S40+S41+S42 -> #DIV/0! | W39: P/E | X39: =$X$37/X38 -> #DIV/0! | Y39: =$X$37/Y38 -> #DIV/0! | Z39: =$X$37/Z38 -> #DIV/0!
B40: 이자비용 | C40: A202560.IC | D40: =IFERROR(VLOOKUP($C40,FS_연결!$A:$Z,D$2,FALSE),0) -> 0 | E40: =IFERROR(VLOOKUP($C40,FS_연결!$A:$Z,E$2,FALSE),0) -> 0 | F40: =IFERROR(VLOOKUP($C40,FS_연결!$A:$Z,F$2,FALSE),0) -> 0 | G40: =IFERROR(VLOOKUP($C40,FS_연결!$A:$Z,G$2,FALSE),0) -> 0 | H40: =IFERROR(VLOOKUP($C40,FS_연결!$A:$Z,H$2,FALSE),0) -> 0 | I40: =IFERROR(VLOOKUP($C40,FS_연결!$A:$Z,I$2,FALSE),0) -> 0 | J40: =IFERROR(VLOOKUP($C40,FS_연결!$A:$Z,J$2,FALSE),0) -> 0 | K40: =IFERROR(VLOOKUP($C40,FS_연결!$A:$Z,K$2,FALSE),0) -> 0 | L40: =IFERROR(VLOOKUP($C40,FS_연결!$A:$Z,L$2,FALSE),0) -> 0 | M40: =IFERROR(VLOOKUP($C40,FS_연결!$A:$AL,M$2,FALSE),0) -> 0 | N40: =IFERROR(VLOOKUP($C40,FS_연결!$A:$AL,N$2,FALSE),0) -> 0 | O40: =IFERROR(VLOOKUP($C40,'FS_연결(분기누적)'!$A:$BS,O$2,FALSE),0) -> 0 | P40: =IFERROR(VLOOKUP($C40,'FS_연결(분기누적)'!$A:$BS,P$2,FALSE),0) -> 0 | Q40: =Q232 -> #DIV/0! | R40: =R232 -> #DIV/0! | S40: =S232 -> #DIV/0!
B41: 외환거래손실 | C41: A202570.IC | D41: =IFERROR(VLOOKUP($C41,FS_연결!$A:$Z,D$2,FALSE),0) -> 0 | E41: =IFERROR(VLOOKUP($C41,FS_연결!$A:$Z,E$2,FALSE),0) -> 0 | F41: =IFERROR(VLOOKUP($C41,FS_연결!$A:$Z,F$2,FALSE),0) -> 0 | G41: =IFERROR(VLOOKUP($C41,FS_연결!$A:$Z,G$2,FALSE),0) -> 0 | H41: =IFERROR(VLOOKUP($C41,FS_연결!$A:$Z,H$2,FALSE),0) -> 0 | I41: =IFERROR(VLOOKUP($C41,FS_연결!$A:$Z,I$2,FALSE),0) -> 0 | J41: =IFERROR(VLOOKUP($C41,FS_연결!$A:$Z,J$2,FALSE),0) -> 0 | K41: =IFERROR(VLOOKUP($C41,FS_연결!$A:$Z,K$2,FALSE),0) -> 0 | L41: =IFERROR(VLOOKUP($C41,FS_연결!$A:$Z,L$2,FALSE),0) -> 0 | M41: =IFERROR(VLOOKUP($C41,FS_연결!$A:$AL,M$2,FALSE),0) -> 0 | N41: =IFERROR(VLOOKUP($C41,FS_연결!$A:$AL,N$2,FALSE),0) -> 0 | O41: =IFERROR(VLOOKUP($C41,'FS_연결(분기누적)'!$A:$BS,O$2,FALSE),0) -> 0 | P41: =IFERROR(VLOOKUP($C41,'FS_연결(분기누적)'!$A:$BS,P$2,FALSE),0) -> 0 | W41: EV | X41: =X37+N14 -> 0
B42: 기타금융원가 | D42: =D39-D40-D41 -> 0 | E42: =E39-E40-E41 -> 0 | F42: =F39-F40-F41 -> 0 | G42: =G39-G40-G41 -> 0 | H42: =H39-H40-H41 -> 0 | I42: =I39-I40-I41 -> 0 | J42: =J39-J40-J41 -> 0 | K42: =K39-K40-K41 -> 0 | ... P42: =P39-P40-P41 -> 0 | Q42: 0 | R42: 0 | S42: 0 | W42: Sales | X42: =Q22 -> 1051 | Y42: =R22 -> 0 | Z42: =S22 -> 0
B43: 기타영업외손익 | C43: A204410.IC | D43: =IFERROR(VLOOKUP($C43,FS_연결!$A:$Z,D$2,FALSE),0) -> 0 | E43: =IFERROR(VLOOKUP($C43,FS_연결!$A:$Z,E$2,FALSE),0) -> 0 | F43: =IFERROR(VLOOKUP($C43,FS_연결!$A:$Z,F$2,FALSE),0) -> 0 | G43: =IFERROR(VLOOKUP($C43,FS_연결!$A:$Z,G$2,FALSE),0) -> 0 | H43: =IFERROR(VLOOKUP($C43,FS_연결!$A:$Z,H$2,FALSE),0) -> 0 | I43: =IFERROR(VLOOKUP($C43,FS_연결!$A:$Z,I$2,FALSE),0) -> 0 | J43: =IFERROR(VLOOKUP($C43,FS_연결!$A:$Z,J$2,FALSE),0) -> 0 | K43: =IFERROR(VLOOKUP($C43,FS_연결!$A:$Z,K$2,FALSE),0) -> 0 | L43: =IFERROR(VLOOKUP($C43,FS_연결!$A:$Z,L$2,FALSE),0) -> 0 | M43: =IFERROR(VLOOKUP($C43,FS_연결!$A:$AL,M$2,FALSE),0) -> 0 | N43: =IFERROR(VLOOKUP($C43,FS_연결!$A:$AL,N$2,FALSE),0) -> 0 | O43: =IFERROR(VLOOKUP($C43,'FS_연결(분기누적)'!$A:$BS,O$2,FALSE),0) -> 0 | P43: =IFERROR(VLOOKUP($C43,'FS_연결(분기누적)'!$A:$BS,P$2,FALSE),0) -> 0 | Q43: 30 | R43: 30 | S43: 30 | W43: EV/Sales | X43: =$X$41/X42 -> 0 | Y43: =$X$41/Y42 -> #DIV/0! | Z43: =$X$41/Z42 -> #DIV/0!
B44: 법인세비용차감전계속사업이익 | C44: A203120.IC | D44: =IFERROR(VLOOKUP($C44,FS_연결!$A:$Z,D$2,FALSE),0) -> 0 | E44: =IFERROR(VLOOKUP($C44,FS_연결!$A:$Z,E$2,FALSE),0) -> 0 | F44: =IFERROR(VLOOKUP($C44,FS_연결!$A:$Z,F$2,FALSE),0) -> 0 | G44: =IFERROR(VLOOKUP($C44,FS_연결!$A:$Z,G$2,FALSE),0) -> 0 | H44: =IFERROR(VLOOKUP($C44,FS_연결!$A:$Z,H$2,FALSE),0) -> 0 | I44: =IFERROR(VLOOKUP($C44,FS_연결!$A:$Z,I$2,FALSE),0) -> 0 | J44: =IFERROR(VLOOKUP($C44,FS_연결!$A:$Z,J$2,FALSE),0) -> 0 | K44: =IFERROR(VLOOKUP($C44,FS_연결!$A:$Z,K$2,FALSE),0) -> 0 | L44: =IFERROR(VLOOKUP($C44,FS_연결!$A:$Z,L$2,FALSE),0) -> 0 | M44: =IFERROR(VLOOKUP($C44,FS_연결!$A:$AL,M$2,FALSE),0) -> 0 | N44: =IFERROR(VLOOKUP($C44,FS_연결!$A:$AL,N$2,FALSE),0) -> 0 | O44: =IFERROR(VLOOKUP($C44,'FS_연결(분기누적)'!$A:$BS,O$2,FALSE),0) -> 0 | P44: =IFERROR(VLOOKUP($C44,'FS_연결(분기누적)'!$A:$BS,P$2,FALSE),0) -> 0 | Q44: =Q32+Q34+Q35-Q39+Q43 -> #DIV/0! | R44: =R32+R34+R35-R39+R43 -> #DIV/0! | S44: =S32+S34+S35-S39+S43 -> #DIV/0!
B45: Pretax margin (%) | D45: =D44/D22 -> #DIV/0! | E45: =E44/E22 -> #DIV/0! | F45: =F44/F22 -> #DIV/0! | G45: =G44/G22 -> #DIV/0! | H45: =H44/H22 -> #DIV/0! | I45: =I44/I22 -> #DIV/0! | J45: =J44/J22 -> #DIV/0! | K45: =K44/K22 -> #DIV/0! | ... S45: =S44/S22 -> #DIV/0!
B46: 법인세비용 | C46: A203130.IC | D46: =IFERROR(VLOOKUP($C46,FS_연결!$A:$Z,D$2,FALSE),0) -> 0 | E46: =IFERROR(VLOOKUP($C46,FS_연결!$A:$Z,E$2,FALSE),0) -> 0 | F46: =IFERROR(VLOOKUP($C46,FS_연결!$A:$Z,F$2,FALSE),0) -> 0 | G46: =IFERROR(VLOOKUP($C46,FS_연결!$A:$Z,G$2,FALSE),0) -> 0 | H46: =IFERROR(VLOOKUP($C46,FS_연결!$A:$Z,H$2,FALSE),0) -> 0 | I46: =IFERROR(VLOOKUP($C46,FS_연결!$A:$Z,I$2,FALSE),0) -> 0 | J46: =IFERROR(VLOOKUP($C46,FS_연결!$A:$Z,J$2,FALSE),0) -> 0 | K46: =IFERROR(VLOOKUP($C46,FS_연결!$A:$Z,K$2,FALSE),0) -> 0 | L46: =IFERROR(VLOOKUP($C46,FS_연결!$A:$Z,L$2,FALSE),0) -> 0 | M46: =IFERROR(VLOOKUP($C46,FS_연결!$A:$AL,M$2,FALSE),0) -> 0 | N46: =IFERROR(VLOOKUP($C46,FS_연결!$A:$AL,N$2,FALSE),0) -> 0 | O46: =IFERROR(VLOOKUP($C46,'FS_연결(분기누적)'!$A:$BS,O$2,FALSE),0) -> 0 | P46: =IFERROR(VLOOKUP($C46,'FS_연결(분기누적)'!$A:$BS,P$2,FALSE),0) -> 0 | Q46: =IF(Q44<0,0,IF(Q44>200,2*$X$48+(200-2)*$X$49+(Q44-200)*$X$50,2*$X$48+(Q44-2)*$X$49)) -> #DIV/0! | R46: =IF(R44<0,0,IF(R44>200,2*$X$48+(200-2)*$X$49+(R44-200)*$X$50,2*$X$48+(R44-2)*$X$49)) -> #DIV/0! | S46: =IF(S44<0,0,IF(S44>200,2*$X$48+(200-2)*$X$49+(S44-200)*$X$50,2*$X$48+(S44-2)*$X$49)) -> #DIV/0! | V46: 미사용 이월 결손금 잔액(24년 말 250억원) 감안 시, 향후 3년 이상 법인세 없을 것으로 전망
B47: Tax rate (%) | D47: =D46/D44 -> #DIV/0! | E47: =E46/E44 -> #DIV/0! | F47: =F46/F44 -> #DIV/0! | G47: =G46/G44 -> #DIV/0! | H47: =H46/H44 -> #DIV/0! | I47: =I46/I44 -> #DIV/0! | J47: =J46/J44 -> #DIV/0! | K47: =K46/K44 -> #DIV/0! | ... S47: =S46/S44 -> #DIV/0! | V47: 법인세율 적용 | W47: 과세표준 | X47: 적용세율
B48: 계속사업이익 | C48: A203140.IC | D48: =IFERROR(VLOOKUP($C48,FS_연결!$A:$Z,D$2,FALSE),0) -> 0 | E48: =IFERROR(VLOOKUP($C48,FS_연결!$A:$Z,E$2,FALSE),0) -> 0 | F48: =IFERROR(VLOOKUP($C48,FS_연결!$A:$Z,F$2,FALSE),0) -> 0 | G48: =IFERROR(VLOOKUP($C48,FS_연결!$A:$Z,G$2,FALSE),0) -> 0 | H48: =IFERROR(VLOOKUP($C48,FS_연결!$A:$Z,H$2,FALSE),0) -> 0 | I48: =IFERROR(VLOOKUP($C48,FS_연결!$A:$Z,I$2,FALSE),0) -> 0 | J48: =IFERROR(VLOOKUP($C48,FS_연결!$A:$Z,J$2,FALSE),0) -> 0 | K48: =IFERROR(VLOOKUP($C48,FS_연결!$A:$Z,K$2,FALSE),0) -> 0 | L48: =IFERROR(VLOOKUP($C48,FS_연결!$A:$Z,L$2,FALSE),0) -> 0 | M48: =IFERROR(VLOOKUP($C48,FS_연결!$A:$AL,M$2,FALSE),0) -> 0 | N48: =IFERROR(VLOOKUP($C48,FS_연결!$A:$AL,N$2,FALSE),0) -> 0 | O48: =IFERROR(VLOOKUP($C48,'FS_연결(분기누적)'!$A:$BS,O$2,FALSE),0) -> 0 | P48: =IFERROR(VLOOKUP($C48,'FS_연결(분기누적)'!$A:$BS,P$2,FALSE),0) -> 0 | Q48: =Q44-Q46 -> #DIV/0! | R48: =R44-R46 -> #DIV/0! | S48: =S44-S46 -> #DIV/0! | W48: 2억원 이하 | X48: 0.11
B49: Net profit margin (%) | D49: =D48/D22 -> #DIV/0! | E49: =E48/E22 -> #DIV/0! | F49: =F48/F22 -> #DIV/0! | G49: =G48/G22 -> #DIV/0! | H49: =H48/H22 -> #DIV/0! | I49: =I48/I22 -> #DIV/0! | J49: =J48/J22 -> #DIV/0! | K49: =K48/K22 -> #DIV/0! | ... S49: =S48/S22 -> #DIV/0! | W49: 2~200억원 | X49: 0.22
B50: (비지배주주지분)당기순이익 | C50: A203190.IC | D50: =IFERROR(VLOOKUP($C50,FS_연결!$A:$Z,D$2,FALSE),0) -> 0 | E50: =IFERROR(VLOOKUP($C50,FS_연결!$A:$Z,E$2,FALSE),0) -> 0 | F50: =IFERROR(VLOOKUP($C50,FS_연결!$A:$Z,F$2,FALSE),0) -> 0 | G50: =IFERROR(VLOOKUP($C50,FS_연결!$A:$Z,G$2,FALSE),0) -> 0 | H50: =IFERROR(VLOOKUP($C50,FS_연결!$A:$Z,H$2,FALSE),0) -> 0 | I50: =IFERROR(VLOOKUP($C50,FS_연결!$A:$Z,I$2,FALSE),0) -> 0 | J50: =IFERROR(VLOOKUP($C50,FS_연결!$A:$Z,J$2,FALSE),0) -> 0 | K50: =IFERROR(VLOOKUP($C50,FS_연결!$A:$Z,K$2,FALSE),0) -> 0 | L50: =IFERROR(VLOOKUP($C50,FS_연결!$A:$Z,L$2,FALSE),0) -> 0 | M50: =IFERROR(VLOOKUP($C50,FS_연결!$A:$AL,M$2,FALSE),0) -> 0 | N50: =IFERROR(VLOOKUP($C50,FS_연결!$A:$AL,N$2,FALSE),0) -> 0 | O50: =IFERROR(VLOOKUP($C50,'FS_연결(분기누적)'!$A:$BS,O$2,FALSE),0) -> 0 | P50: =IFERROR(VLOOKUP($C50,'FS_연결(분기누적)'!$A:$BS,P$2,FALSE),0) -> 0 | Q50: =Q48*Q51 -> #DIV/0! | R50: =R48*R51 -> #DIV/0! | S50: =S48*S51 -> #DIV/0! | W50: 200~3000억원 | X50: 0.242
B51: % of Net profit | D51: =D50/D48 -> #DIV/0! | E51: =E50/E48 -> #DIV/0! | F51: =F50/F48 -> #DIV/0! | G51: =G50/G48 -> #DIV/0! | H51: =H50/H48 -> #DIV/0! | I51: =I50/I48 -> #DIV/0! | J51: =J50/J48 -> #DIV/0! | K51: =K50/K48 -> #DIV/0! | ... P51: =P50/P48 -> #DIV/0! | Q51: 0 | R51: =Q51 -> 0 | S51: =R51 -> 0 | W51: 3000억원 초과분 | X51: 0.275
B52: (지배주주지분)당기순이익 | C52: A203180.IC | D52: =IFERROR(VLOOKUP($C52,FS_연결!$A:$Z,D$2,FALSE),0) -> 0 | E52: =IFERROR(VLOOKUP($C52,FS_연결!$A:$Z,E$2,FALSE),0) -> 0 | F52: =IFERROR(VLOOKUP($C52,FS_연결!$A:$Z,F$2,FALSE),0) -> 0 | G52: =IFERROR(VLOOKUP($C52,FS_연결!$A:$Z,G$2,FALSE),0) -> 0 | H52: =IFERROR(VLOOKUP($C52,FS_연결!$A:$Z,H$2,FALSE),0) -> 0 | I52: =IFERROR(VLOOKUP($C52,FS_연결!$A:$Z,I$2,FALSE),0) -> 0 | J52: =IFERROR(VLOOKUP($C52,FS_연결!$A:$Z,J$2,FALSE),0) -> 0 | K52: =IFERROR(VLOOKUP($C52,FS_연결!$A:$Z,K$2,FALSE),0) -> 0 | L52: =IFERROR(VLOOKUP($C52,FS_연결!$A:$Z,L$2,FALSE),0) -> 0 | M52: =IFERROR(VLOOKUP($C52,FS_연결!$A:$AL,M$2,FALSE),0) -> 0 | N52: =IFERROR(VLOOKUP($C52,FS_연결!$A:$AL,N$2,FALSE),0) -> 0 | O52: =IFERROR(VLOOKUP($C52,'FS_연결(분기누적)'!$A:$BS,O$2,FALSE),0) -> 0 | P52: =IFERROR(VLOOKUP($C52,'FS_연결(분기누적)'!$A:$BS,P$2,FALSE),0) -> 0 | Q52: =Q48-Q50 -> #DIV/0! | R52: =R48-R50 -> #DIV/0! | S52: =S48-S50 -> #DIV/0!
B54: # Shares outstanding (mn) | D54: =D55+D56 -> 0 | E54: =E55+E56 -> 0 | F54: =F55+F56 -> 0 | G54: =G55+G56 -> 0 | H54: =H55+H56 -> 0 | I54: =I55+I56 -> 0 | J54: =J55+J56 -> 0 | K54: =K55+K56 -> 0 | ... S54: =S55+S56 -> 0
B55: Common | C55: A120680.IC | D55: =IFERROR(VLOOKUP($C55,FS_연결!$A:$Z,D$2,FALSE)/1000,0) -> 0 | E55: =IFERROR(VLOOKUP($C55,FS_연결!$A:$Z,E$2,FALSE)/1000,0) -> 0 | F55: =IFERROR(VLOOKUP($C55,FS_연결!$A:$Z,F$2,FALSE)/1000,0) -> 0 | G55: =IFERROR(VLOOKUP($C55,FS_연결!$A:$Z,G$2,FALSE)/1000,0) -> 0 | H55: =IFERROR(VLOOKUP($C55,FS_연결!$A:$Z,H$2,FALSE)/1000,0) -> 0 | I55: =IFERROR(VLOOKUP($C55,FS_연결!$A:$Z,I$2,FALSE)/1000,0) -> 0 | J55: =IFERROR(VLOOKUP($C55,FS_연결!$A:$Z,J$2,FALSE)/1000,0) -> 0 | K55: =IFERROR(VLOOKUP($C55,FS_연결!$A:$Z,K$2,FALSE)/1000,0) -> 0 | L55: =IFERROR(VLOOKUP($C55,FS_연결!$A:$Z,L$2,FALSE)/1000,0) -> 0 | M55: =IFERROR(VLOOKUP($C55,FS_연결!$A:$AL,M$2,FALSE)/1000,0) -> 0 | N55: =IFERROR(VLOOKUP($C55,FS_연결!$A:$AL,N$2,FALSE)/1000,0) -> 0 | O55: =IFERROR(VLOOKUP($C55,'FS_연결(분기누적)'!$A:$BS,O$2,FALSE)/1000,0) -> 0 | P55: =IFERROR(VLOOKUP($C55,'FS_연결(분기누적)'!$A:$BS,P$2,FALSE)/1000,0) -> 0 | Q55: =N55 -> 0 | R55: =Q55 -> 0 | S55: =R55 -> 0
B56: Preferred | C56: A120690.IC | D56: =IFERROR(VLOOKUP($C56,FS_연결!$A:$Z,D$2,FALSE)/1000,0) -> 0 | E56: =IFERROR(VLOOKUP($C56,FS_연결!$A:$Z,E$2,FALSE)/1000,0) -> 0 | F56: =IFERROR(VLOOKUP($C56,FS_연결!$A:$Z,F$2,FALSE)/1000,0) -> 0 | G56: =IFERROR(VLOOKUP($C56,FS_연결!$A:$Z,G$2,FALSE)/1000,0) -> 0 | H56: =IFERROR(VLOOKUP($C56,FS_연결!$A:$Z,H$2,FALSE)/1000,0) -> 0 | I56: =IFERROR(VLOOKUP($C56,FS_연결!$A:$Z,I$2,FALSE)/1000,0) -> 0 | J56: =IFERROR(VLOOKUP($C56,FS_연결!$A:$Z,J$2,FALSE)/1000,0) -> 0 | K56: =IFERROR(VLOOKUP($C56,FS_연결!$A:$Z,K$2,FALSE)/1000,0) -> 0 | L56: =IFERROR(VLOOKUP($C56,FS_연결!$A:$Z,L$2,FALSE)/1000,0) -> 0 | M56: =IFERROR(VLOOKUP($C56,FS_연결!$A:$AL,M$2,FALSE)/1000,0) -> 0 | N56: =IFERROR(VLOOKUP($C56,FS_연결!$A:$AL,N$2,FALSE)/1000,0) -> 0 | O56: =IFERROR(VLOOKUP($C56,'FS_연결(분기누적)'!$A:$BS,O$2,FALSE)/1000,0) -> 0 | P56: =IFERROR(VLOOKUP($C56,'FS_연결(분기누적)'!$A:$BS,P$2,FALSE)/1000,0) -> 0 | Q56: =N56 -> 0 | R56: =Q56 -> 0 | S56: =R56 -> 0
B57: EPS | D57: =(D52-D141)*100/D55 -> #DIV/0! | E57: =(E52-E141)*100/E55 -> #DIV/0! | F57: =(F52-F141)*100/F55 -> #DIV/0! | G57: =(G52-G141)*100/G55 -> #DIV/0! | H57: =(H52-H141)*100/H55 -> #DIV/0! | I57: =(I52-I141)*100/I55 -> #DIV/0! | J57: =(J52-J141)*100/J55 -> #DIV/0! | K57: =(K52-K141)*100/K55 -> #DIV/0! | ... S57: =(S52-S141)*100/S55 -> #DIV/0!
B58: Yoy growth (%) | K58: =K57/D57-1 -> #DIV/0! | L58: =L57/K57-1 -> #DIV/0! | M58: =M57/L57-1 -> #DIV/0! | N58: =N57/M57-1 -> #DIV/0! | O58: =O57/N57-1 -> #DIV/0! | P58: =P57/O57-1 -> #DIV/0! | Q58: =Q57/N57-1 -> #DIV/0! | R58: =R57/Q57-1 -> #DIV/0! | S58: =S57/R57-1 -> #DIV/0!
Z59: (단위: 억원)
B60: BALANCE SHEET (억원) | D60: =D$3 -> 2014 | E60: =E$3 -> 2015 | F60: =F$3 -> 2016 | G60: =G$3 -> 2017 | H60: =H$3 -> 2018 | I60: =I$3 -> 2019 | J60: =J$3 -> 2020 | K60: =K$3 -> 2021 | ... S60: =S$3 -> 2027E | W60: 구분 | X60: 발행 전 | Y60: 메자닌 발행 | Z60: 발행 후
W61: 자산총계 | X61: =P11 -> 0 | Y61: 120 | Z61: =SUM(X61:Y61) -> 120
B62: 현금및현금성자산 | C62: A190650.IC | D62: =IFERROR(VLOOKUP($C62,FS_연결!$A:$Z,D$2,FALSE),0) -> 0 | E62: =IFERROR(VLOOKUP($C62,FS_연결!$A:$Z,E$2,FALSE),0) -> 0 | F62: =IFERROR(VLOOKUP($C62,FS_연결!$A:$Z,F$2,FALSE),0) -> 0 | G62: =IFERROR(VLOOKUP($C62,FS_연결!$A:$Z,G$2,FALSE),0) -> 0 | H62: =IFERROR(VLOOKUP($C62,FS_연결!$A:$Z,H$2,FALSE),0) -> 0 | I62: =IFERROR(VLOOKUP($C62,FS_연결!$A:$Z,I$2,FALSE),0) -> 0 | J62: =IFERROR(VLOOKUP($C62,FS_연결!$A:$Z,J$2,FALSE),0) -> 0 | K62: =IFERROR(VLOOKUP($C62,FS_연결!$A:$Z,K$2,FALSE),0) -> 0 | L62: =IFERROR(VLOOKUP($C62,FS_연결!$A:$Z,L$2,FALSE),0) -> 0 | M62: =IFERROR(VLOOKUP($C62,FS_연결!$A:$AL,M$2,FALSE),0) -> 0 | N62: =IFERROR(VLOOKUP($C62,FS_연결!$A:$AL,N$2,FALSE),0) -> 0 | O62: =IFERROR(VLOOKUP($C62,'FS_연결(분기누적)'!$A:$BS,O$2,FALSE),0) -> 0 | P62: =IFERROR(VLOOKUP($C62,'FS_연결(분기누적)'!$A:$BS,P$2,FALSE),0) -> 0 | Q62: =Q204 -> #DIV/0! | R62: =R204 -> #DIV/0! | S62: =S204 -> #DIV/0! | W62: 부채총계 | X62: =P123 -> 0 | Y62: =Y61 -> 120 | Z62: =SUM(X62:Y62) -> 120
B63: 단기금융자산 | D63: =SUM(D64:D70) -> 0 | E63: =SUM(E64:E70) -> 0 | F63: =SUM(F64:F70) -> 0 | G63: =SUM(G64:G70) -> 0 | H63: =SUM(H64:H70) -> 0 | I63: =SUM(I64:I70) -> 0 | J63: =SUM(J64:J70) -> 0 | K63: =SUM(K64:K70) -> 0 | ... S63: =SUM(S64:S70) -> 0 | W63: 자본총계 | X63: =X61-X62 -> 0 | Y63: - | Z63: =SUM(X63:Y63) -> 0
B64: 당기손익-공정가치측정금융자산 | C64: A114490.IC | D64: =IFERROR(VLOOKUP($C64,FS_연결!$A:$Z,D$2,FALSE),0) -> 0 | E64: =IFERROR(VLOOKUP($C64,FS_연결!$A:$Z,E$2,FALSE),0) -> 0 | F64: =IFERROR(VLOOKUP($C64,FS_연결!$A:$Z,F$2,FALSE),0) -> 0 | G64: =IFERROR(VLOOKUP($C64,FS_연결!$A:$Z,G$2,FALSE),0) -> 0 | H64: =IFERROR(VLOOKUP($C64,FS_연결!$A:$Z,H$2,FALSE),0) -> 0 | I64: =IFERROR(VLOOKUP($C64,FS_연결!$A:$Z,I$2,FALSE),0) -> 0 | J64: =IFERROR(VLOOKUP($C64,FS_연결!$A:$Z,J$2,FALSE),0) -> 0 | K64: =IFERROR(VLOOKUP($C64,FS_연결!$A:$Z,K$2,FALSE),0) -> 0 | L64: =IFERROR(VLOOKUP($C64,FS_연결!$A:$Z,L$2,FALSE),0) -> 0 | M64: =IFERROR(VLOOKUP($C64,FS_연결!$A:$AL,M$2,FALSE),0) -> 0 | N64: =IFERROR(VLOOKUP($C64,FS_연결!$A:$AL,N$2,FALSE),0) -> 0 | O64: =IFERROR(VLOOKUP($C64,'FS_연결(분기누적)'!$A:$BS,O$2,FALSE),0) -> 0 | P64: =IFERROR(VLOOKUP($C64,'FS_연결(분기누적)'!$A:$BS,P$2,FALSE),0) -> 0 | Q64: =N64 -> 0 | R64: =Q64 -> 0 | S64: =R64 -> 0 | W64: 부채비율 | X64: =X62/X63 -> #DIV/0! | Y64: - | Z64: =Z62/Z63 -> #DIV/0!
B65: 상각후원가측정유가증권 | C65: A114530.IC | D65: =IFERROR(VLOOKUP($C65,FS_연결!$A:$Z,D$2,FALSE),0) -> 0 | E65: =IFERROR(VLOOKUP($C65,FS_연결!$A:$Z,E$2,FALSE),0) -> 0 | F65: =IFERROR(VLOOKUP($C65,FS_연결!$A:$Z,F$2,FALSE),0) -> 0 | G65: =IFERROR(VLOOKUP($C65,FS_연결!$A:$Z,G$2,FALSE),0) -> 0 | H65: =IFERROR(VLOOKUP($C65,FS_연결!$A:$Z,H$2,FALSE),0) -> 0 | I65: =IFERROR(VLOOKUP($C65,FS_연결!$A:$Z,I$2,FALSE),0) -> 0 | J65: =IFERROR(VLOOKUP($C65,FS_연결!$A:$Z,J$2,FALSE),0) -> 0 | K65: =IFERROR(VLOOKUP($C65,FS_연결!$A:$Z,K$2,FALSE),0) -> 0 | L65: =IFERROR(VLOOKUP($C65,FS_연결!$A:$Z,L$2,FALSE),0) -> 0 | M65: =IFERROR(VLOOKUP($C65,FS_연결!$A:$AL,M$2,FALSE),0) -> 0 | N65: =IFERROR(VLOOKUP($C65,FS_연결!$A:$AL,N$2,FALSE),0) -> 0 | O65: =IFERROR(VLOOKUP($C65,'FS_연결(분기누적)'!$A:$BS,O$2,FALSE),0) -> 0 | P65: =IFERROR(VLOOKUP($C65,'FS_연결(분기누적)'!$A:$BS,P$2,FALSE),0) -> 0 | Q65: =N65 -> 0 | R65: =Q65 -> 0 | S65: =R65 -> 0
B66: 상각후원가측정금융자산 | C66: A114540.IC | D66: =IFERROR(VLOOKUP($C66,FS_연결!$A:$Z,D$2,FALSE),0) -> 0 | E66: =IFERROR(VLOOKUP($C66,FS_연결!$A:$Z,E$2,FALSE),0) -> 0 | F66: =IFERROR(VLOOKUP($C66,FS_연결!$A:$Z,F$2,FALSE),0) -> 0 | G66: =IFERROR(VLOOKUP($C66,FS_연결!$A:$Z,G$2,FALSE),0) -> 0 | H66: =IFERROR(VLOOKUP($C66,FS_연결!$A:$Z,H$2,FALSE),0) -> 0 | I66: =IFERROR(VLOOKUP($C66,FS_연결!$A:$Z,I$2,FALSE),0) -> 0 | J66: =IFERROR(VLOOKUP($C66,FS_연결!$A:$Z,J$2,FALSE),0) -> 0 | K66: =IFERROR(VLOOKUP($C66,FS_연결!$A:$Z,K$2,FALSE),0) -> 0 | L66: =IFERROR(VLOOKUP($C66,FS_연결!$A:$Z,L$2,FALSE),0) -> 0 | M66: =IFERROR(VLOOKUP($C66,FS_연결!$A:$AL,M$2,FALSE),0) -> 0 | N66: =IFERROR(VLOOKUP($C66,FS_연결!$A:$AL,N$2,FALSE),0) -> 0 | O66: =IFERROR(VLOOKUP($C66,'FS_연결(분기누적)'!$A:$BS,O$2,FALSE),0) -> 0 | P66: =IFERROR(VLOOKUP($C66,'FS_연결(분기누적)'!$A:$BS,P$2,FALSE),0) -> 0 | Q66: =N66 -> 0 | R66: =Q66 -> 0 | S66: =R66 -> 0 | W66: 유동비율 | X66: =P81/P113*100 -> #DIV/0!
B67: 단기매매금융자산 | C67: A113100.IC | D67: =IFERROR(VLOOKUP($C67,FS_연결!$A:$Z,D$2,FALSE),0) -> 0 | E67: =IFERROR(VLOOKUP($C67,FS_연결!$A:$Z,E$2,FALSE),0) -> 0 | F67: =IFERROR(VLOOKUP($C67,FS_연결!$A:$Z,F$2,FALSE),0) -> 0 | G67: =IFERROR(VLOOKUP($C67,FS_연결!$A:$Z,G$2,FALSE),0) -> 0 | H67: =IFERROR(VLOOKUP($C67,FS_연결!$A:$Z,H$2,FALSE),0) -> 0 | I67: =IFERROR(VLOOKUP($C67,FS_연결!$A:$Z,I$2,FALSE),0) -> 0 | J67: =IFERROR(VLOOKUP($C67,FS_연결!$A:$Z,J$2,FALSE),0) -> 0 | K67: =IFERROR(VLOOKUP($C67,FS_연결!$A:$Z,K$2,FALSE),0) -> 0 | L67: =IFERROR(VLOOKUP($C67,FS_연결!$A:$Z,L$2,FALSE),0) -> 0 | M67: =IFERROR(VLOOKUP($C67,FS_연결!$A:$AL,M$2,FALSE),0) -> 0 | N67: =IFERROR(VLOOKUP($C67,FS_연결!$A:$AL,N$2,FALSE),0) -> 0 | O67: =IFERROR(VLOOKUP($C67,'FS_연결(분기누적)'!$A:$BS,O$2,FALSE),0) -> 0 | P67: =IFERROR(VLOOKUP($C67,'FS_연결(분기누적)'!$A:$BS,P$2,FALSE),0) -> 0 | Q67: =N67 -> 0 | R67: =Q67 -> 0 | S67: =R67 -> 0
B68: 단기금융상품 | C68: A113120.IC | D68: =IFERROR(VLOOKUP($C68,FS_연결!$A:$Z,D$2,FALSE),0) -> 0 | E68: =IFERROR(VLOOKUP($C68,FS_연결!$A:$Z,E$2,FALSE),0) -> 0 | F68: =IFERROR(VLOOKUP($C68,FS_연결!$A:$Z,F$2,FALSE),0) -> 0 | G68: =IFERROR(VLOOKUP($C68,FS_연결!$A:$Z,G$2,FALSE),0) -> 0 | H68: =IFERROR(VLOOKUP($C68,FS_연결!$A:$Z,H$2,FALSE),0) -> 0 | I68: =IFERROR(VLOOKUP($C68,FS_연결!$A:$Z,I$2,FALSE),0) -> 0 | J68: =IFERROR(VLOOKUP($C68,FS_연결!$A:$Z,J$2,FALSE),0) -> 0 | K68: =IFERROR(VLOOKUP($C68,FS_연결!$A:$Z,K$2,FALSE),0) -> 0 | L68: =IFERROR(VLOOKUP($C68,FS_연결!$A:$Z,L$2,FALSE),0) -> 0 | M68: =IFERROR(VLOOKUP($C68,FS_연결!$A:$AL,M$2,FALSE),0) -> 0 | N68: =IFERROR(VLOOKUP($C68,FS_연결!$A:$AL,N$2,FALSE),0) -> 0 | O68: =IFERROR(VLOOKUP($C68,'FS_연결(분기누적)'!$A:$BS,O$2,FALSE),0) -> 0 | P68: =IFERROR(VLOOKUP($C68,'FS_연결(분기누적)'!$A:$BS,P$2,FALSE),0) -> 0 | Q68: =N68 -> 0 | R68: =Q68 -> 0 | S68: =R68 -> 0
B69: 단기매도가능금융자산 | C69: A113240.IC | D69: =IFERROR(VLOOKUP($C69,FS_연결!$A:$Z,D$2,FALSE),0) -> 0 | E69: =IFERROR(VLOOKUP($C69,FS_연결!$A:$Z,E$2,FALSE),0) -> 0 | F69: =IFERROR(VLOOKUP($C69,FS_연결!$A:$Z,F$2,FALSE),0) -> 0 | G69: =IFERROR(VLOOKUP($C69,FS_연결!$A:$Z,G$2,FALSE),0) -> 0 | H69: =IFERROR(VLOOKUP($C69,FS_연결!$A:$Z,H$2,FALSE),0) -> 0 | I69: =IFERROR(VLOOKUP($C69,FS_연결!$A:$Z,I$2,FALSE),0) -> 0 | J69: =IFERROR(VLOOKUP($C69,FS_연결!$A:$Z,J$2,FALSE),0) -> 0 | K69: =IFERROR(VLOOKUP($C69,FS_연결!$A:$Z,K$2,FALSE),0) -> 0 | L69: =IFERROR(VLOOKUP($C69,FS_연결!$A:$Z,L$2,FALSE),0) -> 0 | M69: =IFERROR(VLOOKUP($C69,FS_연결!$A:$AL,M$2,FALSE),0) -> 0 | N69: =IFERROR(VLOOKUP($C69,FS_연결!$A:$AL,N$2,FALSE),0) -> 0 | O69: =IFERROR(VLOOKUP($C69,'FS_연결(분기누적)'!$A:$BS,O$2,FALSE),0) -> 0 | P69: =IFERROR(VLOOKUP($C69,'FS_연결(분기누적)'!$A:$BS,P$2,FALSE),0) -> 0 | Q69: =N69 -> 0 | R69: =Q69 -> 0 | S69: =R69 -> 0
B70: 단기만기보유금융자산 | C70: A113250.IC | D70: =IFERROR(VLOOKUP($C70,FS_연결!$A:$Z,D$2,FALSE),0) -> 0 | E70: =IFERROR(VLOOKUP($C70,FS_연결!$A:$Z,E$2,FALSE),0) -> 0 | F70: =IFERROR(VLOOKUP($C70,FS_연결!$A:$Z,F$2,FALSE),0) -> 0 | G70: =IFERROR(VLOOKUP($C70,FS_연결!$A:$Z,G$2,FALSE),0) -> 0 | H70: =IFERROR(VLOOKUP($C70,FS_연결!$A:$Z,H$2,FALSE),0) -> 0 | I70: =IFERROR(VLOOKUP($C70,FS_연결!$A:$Z,I$2,FALSE),0) -> 0 | J70: =IFERROR(VLOOKUP($C70,FS_연결!$A:$Z,J$2,FALSE),0) -> 0 | K70: =IFERROR(VLOOKUP($C70,FS_연결!$A:$Z,K$2,FALSE),0) -> 0 | L70: =IFERROR(VLOOKUP($C70,FS_연결!$A:$Z,L$2,FALSE),0) -> 0 | M70: =IFERROR(VLOOKUP($C70,FS_연결!$A:$AL,M$2,FALSE),0) -> 0 | N70: =IFERROR(VLOOKUP($C70,FS_연결!$A:$AL,N$2,FALSE),0) -> 0 | O70: =IFERROR(VLOOKUP($C70,'FS_연결(분기누적)'!$A:$BS,O$2,FALSE),0) -> 0 | P70: =IFERROR(VLOOKUP($C70,'FS_연결(분기누적)'!$A:$BS,P$2,FALSE),0) -> 0 | Q70: =N70 -> 0 | R70: =Q70 -> 0 | S70: =R70 -> 0
B71: 매출채권 | C71: A190560.IC | D71: =IFERROR(VLOOKUP($C71,FS_연결!$A:$Z,D$2,FALSE),0) -> 0 | E71: =IFERROR(VLOOKUP($C71,FS_연결!$A:$Z,E$2,FALSE),0) -> 0 | F71: =IFERROR(VLOOKUP($C71,FS_연결!$A:$Z,F$2,FALSE),0) -> 0 | G71: =IFERROR(VLOOKUP($C71,FS_연결!$A:$Z,G$2,FALSE),0) -> 0 | H71: =IFERROR(VLOOKUP($C71,FS_연결!$A:$Z,H$2,FALSE),0) -> 0 | I71: =IFERROR(VLOOKUP($C71,FS_연결!$A:$Z,I$2,FALSE),0) -> 0 | J71: =IFERROR(VLOOKUP($C71,FS_연결!$A:$Z,J$2,FALSE),0) -> 0 | K71: =IFERROR(VLOOKUP($C71,FS_연결!$A:$Z,K$2,FALSE),0) -> 0 | L71: =IFERROR(VLOOKUP($C71,FS_연결!$A:$Z,L$2,FALSE),0) -> 0 | M71: =IFERROR(VLOOKUP($C71,FS_연결!$A:$AL,M$2,FALSE),0) -> 0 | N71: =IFERROR(VLOOKUP($C71,FS_연결!$A:$AL,N$2,FALSE),0) -> 0 | O71: =IFERROR(VLOOKUP($C71,'FS_연결(분기누적)'!$A:$BS,O$2,FALSE),0) -> 0 | P71: =IFERROR(VLOOKUP($C71,'FS_연결(분기누적)'!$A:$BS,P$2,FALSE),0) -> 0 | Q71: =Q72*Q22/365 -> #DIV/0! | R71: =R72*R22/365 -> #DIV/0! | S71: =S72*S22/365 -> #DIV/0!
B72: 회전기일 (매출액) | E72: =AVERAGE(E71,D71)/E$22*365 -> #DIV/0! | F72: =AVERAGE(F71,E71)/F$22*365 -> #DIV/0! | G72: =AVERAGE(G71,F71)/G$22*365 -> #DIV/0! | H72: =AVERAGE(H71,G71)/H$22*365 -> #DIV/0! | I72: =AVERAGE(I71,H71)/I$22*365 -> #DIV/0! | J72: =AVERAGE(J71,I71)/J$22*365 -> #DIV/0! | K72: =AVERAGE(K71,J71)/K$22*365 -> #DIV/0! | L72: =AVERAGE(L71,K71)/L$22*365 -> #DIV/0! | ... N72: =AVERAGE(N71,M71)/N$22*365 -> #DIV/0! | O72: =AVERAGE(O71,M71)/(O$22*IF(RIGHT(O$3,2)="1Q",4,IF(RIGHT(O$3,2)="2Q",2,IF(RIGHT(O$3,2)="3Q",4/3,"0"))))*365 -> #DIV/0! | P72: =AVERAGE(P71,N71)/(P$22*IF(RIGHT(P$3,2)="1Q",4,IF(RIGHT(P$3,2)="2Q",2,IF(RIGHT(P$3,2)="3Q",4/3,"0"))))*365 -> #DIV/0! | Q72: =AVERAGE(N72) -> #DIV/0! | R72: =Q72 -> #DIV/0! | S72: =R72 -> #DIV/0! | V72: 3년 평균
B73: 미수금 | C73: A190570.IC | I73: =IFERROR(VLOOKUP($C73,FS_연결!$A:$Z,I$2,FALSE),0) -> 0 | J73: =IFERROR(VLOOKUP($C73,FS_연결!$A:$Z,J$2,FALSE),0) -> 0 | K73: =IFERROR(VLOOKUP($C73,FS_연결!$A:$Z,K$2,FALSE),0) -> 0 | L73: =IFERROR(VLOOKUP($C73,FS_연결!$A:$Z,L$2,FALSE),0) -> 0 | M73: =IFERROR(VLOOKUP($C73,FS_연결!$A:$AL,M$2,FALSE),0) -> 0 | N73: =IFERROR(VLOOKUP($C73,FS_연결!$A:$AL,N$2,FALSE),0) -> 0 | O73: =IFERROR(VLOOKUP($C73,'FS_연결(분기누적)'!$A:$BS,O$2,FALSE),0) -> 0 | P73: =IFERROR(VLOOKUP($C73,'FS_연결(분기누적)'!$A:$BS,P$2,FALSE),0) -> 0 | Q73: =Q74*Q22/365 -> #DIV/0! | R73: =R74*R22/365 -> #DIV/0! | S73: =S74*S22/365 -> #DIV/0!
B74: 회전기일 (매출액) | E74: =AVERAGE(E73,D73)/E$22*365 -> #DIV/0! | F74: =AVERAGE(F73,E73)/F$22*365 -> #DIV/0! | G74: =AVERAGE(G73,F73)/G$22*365 -> #DIV/0! | H74: =AVERAGE(H73,G73)/H$22*365 -> #DIV/0! | I74: =AVERAGE(I73,H73)/I$22*365 -> #DIV/0! | J74: =AVERAGE(J73,I73)/J$22*365 -> #DIV/0! | K74: =AVERAGE(K73,J73)/K$22*365 -> #DIV/0! | L74: =AVERAGE(L73,K73)/L$22*365 -> #DIV/0! | ... N74: =AVERAGE(N73,M73)/N$22*365 -> #DIV/0! | O74: =AVERAGE(O73,M73)/(O$22*IF(RIGHT(O$3,2)="1Q",4,IF(RIGHT(O$3,2)="2Q",2,IF(RIGHT(O$3,2)="3Q",4/3,"0"))))*365 -> #DIV/0! | P74: =AVERAGE(P73,N73)/(P$22*IF(RIGHT(P$3,2)="1Q",4,IF(RIGHT(P$3,2)="2Q",2,IF(RIGHT(P$3,2)="3Q",4/3,"0"))))*365 -> #DIV/0! | Q74: =AVERAGE(N74) -> #DIV/0! | R74: =Q74 -> #DIV/0! | S74: =R74 -> #DIV/0! | V74: 잔액 0
B75: 기타단기채권(미청구공사) | C75: A190590.IC | D75: =IFERROR(VLOOKUP($C75,FS_연결!$A:$Z,D$2,FALSE),0) -> 0 | E75: =IFERROR(VLOOKUP($C75,FS_연결!$A:$Z,E$2,FALSE),0) -> 0 | F75: =IFERROR(VLOOKUP($C75,FS_연결!$A:$Z,F$2,FALSE),0) -> 0 | G75: =IFERROR(VLOOKUP($C75,FS_연결!$A:$Z,G$2,FALSE),0) -> 0 | H75: =IFERROR(VLOOKUP($C75,FS_연결!$A:$Z,H$2,FALSE),0) -> 0 | I75: =IFERROR(VLOOKUP($C75,FS_연결!$A:$Z,I$2,FALSE),0) -> 0 | J75: =IFERROR(VLOOKUP($C75,FS_연결!$A:$Z,J$2,FALSE),0) -> 0 | K75: =IFERROR(VLOOKUP($C75,FS_연결!$A:$Z,K$2,FALSE),0) -> 0 | L75: =IFERROR(VLOOKUP($C75,FS_연결!$A:$Z,L$2,FALSE),0) -> 0 | M75: =IFERROR(VLOOKUP($C75,FS_연결!$A:$AL,M$2,FALSE),0) -> 0 | N75: =IFERROR(VLOOKUP($C75,FS_연결!$A:$AL,N$2,FALSE),0) -> 0 | O75: =IFERROR(VLOOKUP($C75,'FS_연결(분기누적)'!$A:$BS,O$2,FALSE),0) -> 0 | P75: =IFERROR(VLOOKUP($C75,'FS_연결(분기누적)'!$A:$BS,P$2,FALSE),0) -> 0 | Q75: =Q76*Q22/365 -> #DIV/0! | R75: =R76*R22/365 -> #DIV/0! | S75: =S76*S22/365 -> #DIV/0!
B76: 회전기일 (매출액) | E76: =AVERAGE(E75,D75)/E$22*365 -> #DIV/0! | F76: =AVERAGE(F75,E75)/F$22*365 -> #DIV/0! | G76: =AVERAGE(G75,F75)/G$22*365 -> #DIV/0! | H76: =AVERAGE(H75,G75)/H$22*365 -> #DIV/0! | I76: =AVERAGE(I75,H75)/I$22*365 -> #DIV/0! | J76: =AVERAGE(J75,I75)/J$22*365 -> #DIV/0! | K76: =AVERAGE(K75,J75)/K$22*365 -> #DIV/0! | L76: =AVERAGE(L75,K75)/L$22*365 -> #DIV/0! | ... N76: =AVERAGE(N75,M75)/N$22*365 -> #DIV/0! | O76: =AVERAGE(O75,M75)/(O$22*IF(RIGHT(O$3,2)="1Q",4,IF(RIGHT(O$3,2)="2Q",2,IF(RIGHT(O$3,2)="3Q",4/3,"0"))))*365 -> #DIV/0! | P76: =AVERAGE(P75,N75)/(P$22*IF(RIGHT(P$3,2)="1Q",4,IF(RIGHT(P$3,2)="2Q",2,IF(RIGHT(P$3,2)="3Q",4/3,"0"))))*365 -> #DIV/0! | Q76: =AVERAGE(N76) -> #DIV/0! | R76: =Q76 -> #DIV/0! | S76: =R76 -> #DIV/0! | V76: 잔액 0
B77: 재고자산 | C77: A112840.IC | D77: =IFERROR(VLOOKUP($C77,FS_연결!$A:$Z,D$2,FALSE),0) -> 0 | E77: =IFERROR(VLOOKUP($C77,FS_연결!$A:$Z,E$2,FALSE),0) -> 0 | F77: =IFERROR(VLOOKUP($C77,FS_연결!$A:$Z,F$2,FALSE),0) -> 0 | G77: =IFERROR(VLOOKUP($C77,FS_연결!$A:$Z,G$2,FALSE),0) -> 0 | H77: =IFERROR(VLOOKUP($C77,FS_연결!$A:$Z,H$2,FALSE),0) -> 0 | I77: =IFERROR(VLOOKUP($C77,FS_연결!$A:$Z,I$2,FALSE),0) -> 0 | J77: =IFERROR(VLOOKUP($C77,FS_연결!$A:$Z,J$2,FALSE),0) -> 0 | K77: =IFERROR(VLOOKUP($C77,FS_연결!$A:$Z,K$2,FALSE),0) -> 0 | L77: =IFERROR(VLOOKUP($C77,FS_연결!$A:$Z,L$2,FALSE),0) -> 0 | M77: =IFERROR(VLOOKUP($C77,FS_연결!$A:$AL,M$2,FALSE),0) -> 0 | N77: =IFERROR(VLOOKUP($C77,FS_연결!$A:$AL,N$2,FALSE),0) -> 0 | O77: =IFERROR(VLOOKUP($C77,'FS_연결(분기누적)'!$A:$BS,O$2,FALSE),0) -> 0 | P77: =IFERROR(VLOOKUP($C77,'FS_연결(분기누적)'!$A:$BS,P$2,FALSE),0) -> 0 | Q77: =Q78*Q22/365 -> #DIV/0! | R77: =R78*R22/365 -> #DIV/0! | S77: =S78*S22/365 -> #DIV/0!
B78: 회전기일 (매출액) | E78: =AVERAGE(E77,D77)/E$22*365 -> #DIV/0! | F78: =AVERAGE(F77,E77)/F$22*365 -> #DIV/0! | G78: =AVERAGE(G77,F77)/G$22*365 -> #DIV/0! | H78: =AVERAGE(H77,G77)/H$22*365 -> #DIV/0! | I78: =AVERAGE(I77,H77)/I$22*365 -> #DIV/0! | J78: =AVERAGE(J77,I77)/J$22*365 -> #DIV/0! | K78: =AVERAGE(K77,J77)/K$22*365 -> #DIV/0! | L78: =AVERAGE(L77,K77)/L$22*365 -> #DIV/0! | ... N78: =AVERAGE(N77,M77)/N$22*365 -> #DIV/0! | O78: =AVERAGE(O77,M77)/(O$22*IF(RIGHT(O$3,2)="1Q",4,IF(RIGHT(O$3,2)="2Q",2,IF(RIGHT(O$3,2)="3Q",4/3,"0"))))*365 -> #DIV/0! | P78: =AVERAGE(P77,N77)/(P$22*IF(RIGHT(P$3,2)="1Q",4,IF(RIGHT(P$3,2)="2Q",2,IF(RIGHT(P$3,2)="3Q",4/3,"0"))))*365 -> #DIV/0! | Q78: =AVERAGE(N78) -> #DIV/0! | R78: =Q78 -> #DIV/0! | S78: =R78 -> #DIV/0! | V78: 3년 평균
B79: Others | D79: =D81-D62-D63-D71-D77 -> 0 | E79: =E81-E62-E63-E71-E77 -> 0 | F79: =F81-F62-F63-F71-F77 -> 0 | G79: =G81-G62-G63-G71-G77 -> 0 | H79: =H81-H62-H63-H71-H77-H75-H73 -> 0 | I79: =I81-I62-I63-I71-I77-I75-I73 -> 0 | J79: =J81-J62-J63-J71-J77-J75-J73 -> 0 | K79: =K81-K62-K63-K71-K77-K75-K73 -> 0 | L79: =L81-L62-L63-L71-L77-L75-L73 -> 0 | M79: =M81-M62-M63-M71-M77-M75-M73 -> 0 | N79: =N81-N62-N63-N71-N77-N75-N73 -> 0 | O79: =O81-O62-O63-O71-O77-O75-O73 -> 0 | P79: =P81-P62-P63-P71-P77-P75-P73 -> 0 | Q79: =N79 -> 0 | R79: =Q79 -> 0 | S79: =R79 -> 0
B80: 회전기일 (매출액) | E80: =AVERAGE(E79,D79)/E$22*365 -> #DIV/0! | F80: =AVERAGE(F79,E79)/F$22*365 -> #DIV/0! | G80: =AVERAGE(G79,F79)/G$22*365 -> #DIV/0! | H80: =AVERAGE(H79,G79)/H$22*365 -> #DIV/0! | I80: =AVERAGE(I79,H79)/I$22*365 -> #DIV/0! | J80: =AVERAGE(J79,I79)/J$22*365 -> #DIV/0! | K80: =AVERAGE(K79,J79)/K$22*365 -> #DIV/0! | L80: =AVERAGE(L79,K79)/L$22*365 -> #DIV/0! | ... N80: =AVERAGE(N79,M79)/N$22*365 -> #DIV/0! | O80: =AVERAGE(O79,M79)/(O$22*IF(RIGHT(O$3,2)="1Q",4,IF(RIGHT(O$3,2)="2Q",2,IF(RIGHT(O$3,2)="3Q",4/3,"0"))))*365 -> #DIV/0! | P80: =AVERAGE(P79,N79)/(P$22*IF(RIGHT(P$3,2)="1Q",4,IF(RIGHT(P$3,2)="2Q",2,IF(RIGHT(P$3,2)="3Q",4/3,"0"))))*365 -> #DIV/0! | V80: 미추정
B81: 유동자산 | C81: A112830.IC | D81: =IFERROR(VLOOKUP($C81,FS_연결!$A:$Z,D$2,FALSE),0) -> 0 | E81: =IFERROR(VLOOKUP($C81,FS_연결!$A:$Z,E$2,FALSE),0) -> 0 | F81: =IFERROR(VLOOKUP($C81,FS_연결!$A:$Z,F$2,FALSE),0) -> 0 | G81: =IFERROR(VLOOKUP($C81,FS_연결!$A:$Z,G$2,FALSE),0) -> 0 | H81: =IFERROR(VLOOKUP($C81,FS_연결!$A:$Z,H$2,FALSE),0) -> 0 | I81: =IFERROR(VLOOKUP($C81,FS_연결!$A:$Z,I$2,FALSE),0) -> 0 | J81: =IFERROR(VLOOKUP($C81,FS_연결!$A:$Z,J$2,FALSE),0) -> 0 | K81: =IFERROR(VLOOKUP($C81,FS_연결!$A:$Z,K$2,FALSE),0) -> 0 | L81: =IFERROR(VLOOKUP($C81,FS_연결!$A:$Z,L$2,FALSE),0) -> 0 | M81: =IFERROR(VLOOKUP($C81,FS_연결!$A:$AL,M$2,FALSE),0) -> 0 | N81: =IFERROR(VLOOKUP($C81,FS_연결!$A:$AL,N$2,FALSE),0) -> 0 | O81: =IFERROR(VLOOKUP($C81,'FS_연결(분기누적)'!$A:$BS,O$2,FALSE),0) -> 0 | P81: =IFERROR(VLOOKUP($C81,'FS_연결(분기누적)'!$A:$BS,P$2,FALSE),0) -> 0 | Q81: =Q62+Q63+Q71+Q73+Q77+Q79+Q75 -> #DIV/0! | R81: =R62+R63+R71+R73+R77+R79+R75 -> #DIV/0! | S81: =S62+S63+S71+S73+S77+S79+S75 -> #DIV/0!
B82: 투자부동산 | C82: A111330.IC | D82: =IFERROR(VLOOKUP($C82,FS_연결!$A:$Z,D$2,FALSE),0) -> 0 | E82: =IFERROR(VLOOKUP($C82,FS_연결!$A:$Z,E$2,FALSE),0) -> 0 | F82: =IFERROR(VLOOKUP($C82,FS_연결!$A:$Z,F$2,FALSE),0) -> 0 | G82: =IFERROR(VLOOKUP($C82,FS_연결!$A:$Z,G$2,FALSE),0) -> 0 | H82: =IFERROR(VLOOKUP($C82,FS_연결!$A:$Z,H$2,FALSE),0) -> 0 | I82: =IFERROR(VLOOKUP($C82,FS_연결!$A:$Z,I$2,FALSE),0) -> 0 | J82: =IFERROR(VLOOKUP($C82,FS_연결!$A:$Z,J$2,FALSE),0) -> 0 | K82: =IFERROR(VLOOKUP($C82,FS_연결!$A:$Z,K$2,FALSE),0) -> 0 | L82: =IFERROR(VLOOKUP($C82,FS_연결!$A:$Z,L$2,FALSE),0) -> 0 | M82: =IFERROR(VLOOKUP($C82,FS_연결!$A:$AL,M$2,FALSE),0) -> 0 | N82: =IFERROR(VLOOKUP($C82,FS_연결!$A:$AL,N$2,FALSE),0) -> 0 | O82: =IFERROR(VLOOKUP($C82,'FS_연결(분기누적)'!$A:$BS,O$2,FALSE),0) -> 0 | P82: =IFERROR(VLOOKUP($C82,'FS_연결(분기누적)'!$A:$BS,P$2,FALSE),0) -> 0 | Q82: =N82 -> 0 | R82: =Q82 -> 0 | S82: =R82 -> 0
B83: 관계기업등지분관련투자자산 | C83: A111450.IC | D83: =IFERROR(VLOOKUP($C83,FS_연결!$A:$Z,D$2,FALSE),0) -> 0 | E83: =IFERROR(VLOOKUP($C83,FS_연결!$A:$Z,E$2,FALSE),0) -> 0 | F83: =IFERROR(VLOOKUP($C83,FS_연결!$A:$Z,F$2,FALSE),0) -> 0 | G83: =IFERROR(VLOOKUP($C83,FS_연결!$A:$Z,G$2,FALSE),0) -> 0 | H83: =IFERROR(VLOOKUP($C83,FS_연결!$A:$Z,H$2,FALSE),0) -> 0 | I83: =IFERROR(VLOOKUP($C83,FS_연결!$A:$Z,I$2,FALSE),0) -> 0 | J83: =IFERROR(VLOOKUP($C83,FS_연결!$A:$Z,J$2,FALSE),0) -> 0 | K83: =IFERROR(VLOOKUP($C83,FS_연결!$A:$Z,K$2,FALSE),0) -> 0 | L83: =IFERROR(VLOOKUP($C83,FS_연결!$A:$Z,L$2,FALSE),0) -> 0 | M83: =IFERROR(VLOOKUP($C83,FS_연결!$A:$AL,M$2,FALSE),0) -> 0 | N83: =IFERROR(VLOOKUP($C83,FS_연결!$A:$AL,N$2,FALSE),0) -> 0 | O83: =IFERROR(VLOOKUP($C83,'FS_연결(분기누적)'!$A:$BS,O$2,FALSE),0) -> 0 | P83: =IFERROR(VLOOKUP($C83,'FS_연결(분기누적)'!$A:$BS,P$2,FALSE),0) -> 0 | Q83: =N83-Q172 -> 0 | R83: =Q83-R172 -> 0 | S83: =R83-S172 -> 0
B84: 유형자산 (토지) | C84: A190010.IC | D84: =IFERROR(VLOOKUP($C84,FS_연결!$A:$Z,D$2,FALSE),0) -> 0 | E84: =IFERROR(VLOOKUP($C84,FS_연결!$A:$Z,E$2,FALSE),0) -> 0 | F84: =IFERROR(VLOOKUP($C84,FS_연결!$A:$Z,F$2,FALSE),0) -> 0 | G84: =IFERROR(VLOOKUP($C84,FS_연결!$A:$Z,G$2,FALSE),0) -> 0 | H84: =IFERROR(VLOOKUP($C84,FS_연결!$A:$Z,H$2,FALSE),0) -> 0 | I84: =IFERROR(VLOOKUP($C84,FS_연결!$A:$Z,I$2,FALSE),0) -> 0 | J84: =IFERROR(VLOOKUP($C84,FS_연결!$A:$Z,J$2,FALSE),0) -> 0 | K84: =IFERROR(VLOOKUP($C84,FS_연결!$A:$Z,K$2,FALSE),0) -> 0 | L84: =IFERROR(VLOOKUP($C84,FS_연결!$A:$Z,L$2,FALSE),0) -> 0 | M84: =IFERROR(VLOOKUP($C84,FS_연결!$A:$AL,M$2,FALSE),0) -> 0 | N84: =IFERROR(VLOOKUP($C84,FS_연결!$A:$AL,N$2,FALSE),0) -> 0 | O84: =IFERROR(VLOOKUP($C84,'FS_연결(분기누적)'!$A:$BS,O$2,FALSE),0) -> 0 | P84: =IFERROR(VLOOKUP($C84,'FS_연결(분기누적)'!$A:$BS,P$2,FALSE),0) -> 0 | Q84: =N84 -> 0 | R84: =Q84 -> 0 | S84: =R84 -> 0
B85: 유형자산 (건물) | C85: A190030.IC | D85: =IFERROR(VLOOKUP($C85,FS_연결!$A:$Z,D$2,FALSE),0) -> 0 | E85: =IFERROR(VLOOKUP($C85,FS_연결!$A:$Z,E$2,FALSE),0) -> 0 | F85: =IFERROR(VLOOKUP($C85,FS_연결!$A:$Z,F$2,FALSE),0) -> 0 | G85: =IFERROR(VLOOKUP($C85,FS_연결!$A:$Z,G$2,FALSE),0) -> 0 | H85: =IFERROR(VLOOKUP($C85,FS_연결!$A:$Z,H$2,FALSE),0) -> 0 | I85: =IFERROR(VLOOKUP($C85,FS_연결!$A:$Z,I$2,FALSE),0) -> 0 | J85: =IFERROR(VLOOKUP($C85,FS_연결!$A:$Z,J$2,FALSE),0) -> 0 | K85: =IFERROR(VLOOKUP($C85,FS_연결!$A:$Z,K$2,FALSE),0) -> 0 | L85: =IFERROR(VLOOKUP($C85,FS_연결!$A:$Z,L$2,FALSE),0) -> 0 | M85: =IFERROR(VLOOKUP($C85,FS_연결!$A:$AL,M$2,FALSE),0) -> 0 | N85: =IFERROR(VLOOKUP($C85,FS_연결!$A:$AL,N$2,FALSE),0) -> 0 | O85: =IFERROR(VLOOKUP($C85,'FS_연결(분기누적)'!$A:$BS,O$2,FALSE),0) -> 0 | P85: =IFERROR(VLOOKUP($C85,'FS_연결(분기누적)'!$A:$BS,P$2,FALSE),0) -> 0 | Q85: =N85 -> 0 | R85: =Q85 -> 0 | S85: =R85 -> 0
B86: 유형자산 (토지,건물제외) | C86: A110020.IC | D86: =IFERROR(VLOOKUP($C86,FS_연결!$A:$AL,D$2,FALSE),0)-D84-D85 -> 0 | E86: =IFERROR(VLOOKUP($C86,FS_연결!$A:$AL,E$2,FALSE),0)-E84-E85 -> 0 | F86: =IFERROR(VLOOKUP($C86,FS_연결!$A:$AL,F$2,FALSE),0)-F84-F85 -> 0 | G86: =IFERROR(VLOOKUP($C86,FS_연결!$A:$AL,G$2,FALSE),0)-G84-G85 -> 0 | H86: =IFERROR(VLOOKUP($C86,FS_연결!$A:$AL,H$2,FALSE),0)-H84-H85 -> 0 | I86: =IFERROR(VLOOKUP($C86,FS_연결!$A:$AL,I$2,FALSE),0)-I84-I85 -> 0 | J86: =IFERROR(VLOOKUP($C86,FS_연결!$A:$AL,J$2,FALSE),0)-J84-J85 -> 0 | K86: =IFERROR(VLOOKUP($C86,FS_연결!$A:$AL,K$2,FALSE),0)-K84-K85 -> 0 | ... N86: =IFERROR(VLOOKUP($C86,FS_연결!$A:$AL,N$2,FALSE),0)-N84-N85 -> 0 | O86: =IFERROR(VLOOKUP($C86,'FS_연결(분기누적)'!$A:$BS,O$2,FALSE),0)-O84-O85 -> 0 | P86: =IFERROR(VLOOKUP($C86,'FS_연결(분기누적)'!$A:$BS,P$2,FALSE),0)-P84-P85 -> 0 | Q86: =Q216 -> #DIV/0! | R86: =R216 -> #DIV/0! | S86: =S216 -> #DIV/0!
B87: 리스(사용권)자산 | C87: A112370.IC | D87: =IFERROR(VLOOKUP($C87,FS_연결!$A:$Z,D$2,FALSE),0) -> 0 | E87: =IFERROR(VLOOKUP($C87,FS_연결!$A:$Z,E$2,FALSE),0) -> 0 | F87: =IFERROR(VLOOKUP($C87,FS_연결!$A:$Z,F$2,FALSE),0) -> 0 | G87: =IFERROR(VLOOKUP($C87,FS_연결!$A:$Z,G$2,FALSE),0) -> 0 | H87: =IFERROR(VLOOKUP($C87,FS_연결!$A:$Z,H$2,FALSE),0) -> 0 | I87: =IFERROR(VLOOKUP($C87,FS_연결!$A:$Z,I$2,FALSE),0) -> 0 | J87: =IFERROR(VLOOKUP($C87,FS_연결!$A:$Z,J$2,FALSE),0) -> 0 | K87: =IFERROR(VLOOKUP($C87,FS_연결!$A:$Z,K$2,FALSE),0) -> 0 | L87: =IFERROR(VLOOKUP($C87,FS_연결!$A:$Z,L$2,FALSE),0) -> 0 | M87: =IFERROR(VLOOKUP($C87,FS_연결!$A:$AL,M$2,FALSE),0) -> 0 | N87: =IFERROR(VLOOKUP($C87,FS_연결!$A:$AL,N$2,FALSE),0) -> 0 | O87: =IFERROR(VLOOKUP($C87,'FS_연결(분기누적)'!$A:$BS,O$2,FALSE),0) -> 0 | P87: =IFERROR(VLOOKUP($C87,'FS_연결(분기누적)'!$A:$BS,P$2,FALSE),0) -> 0 | Q87: =N87 -> 0 | R87: =Q87 -> 0 | S87: =R87 -> 0
B88: 무형자산 | C88: A110610.IC | D88: =IFERROR(VLOOKUP($C88,FS_연결!$A:$Z,D$2,FALSE),0) -> 0 | E88: =IFERROR(VLOOKUP($C88,FS_연결!$A:$Z,E$2,FALSE),0) -> 0 | F88: =IFERROR(VLOOKUP($C88,FS_연결!$A:$Z,F$2,FALSE),0) -> 0 | G88: =IFERROR(VLOOKUP($C88,FS_연결!$A:$Z,G$2,FALSE),0) -> 0 | H88: =IFERROR(VLOOKUP($C88,FS_연결!$A:$Z,H$2,FALSE),0) -> 0 | I88: =IFERROR(VLOOKUP($C88,FS_연결!$A:$Z,I$2,FALSE),0) -> 0 | J88: =IFERROR(VLOOKUP($C88,FS_연결!$A:$Z,J$2,FALSE),0) -> 0 | K88: =IFERROR(VLOOKUP($C88,FS_연결!$A:$Z,K$2,FALSE),0) -> 0 | L88: =IFERROR(VLOOKUP($C88,FS_연결!$A:$Z,L$2,FALSE),0) -> 0 | M88: =IFERROR(VLOOKUP($C88,FS_연결!$A:$AL,M$2,FALSE),0) -> 0 | N88: =IFERROR(VLOOKUP($C88,FS_연결!$A:$AL,N$2,FALSE),0) -> 0 | O88: =IFERROR(VLOOKUP($C88,'FS_연결(분기누적)'!$A:$BS,O$2,FALSE),0) -> 0 | P88: =IFERROR(VLOOKUP($C88,'FS_연결(분기누적)'!$A:$BS,P$2,FALSE),0) -> 0 | Q88: =N88-Q155-Q156-Q171 -> 0 | R88: =Q88-R155-R156-R171 -> 0 | S88: =R88-S155-S156-S171 -> 0
B89: 이연법인세자산 | C89: A112340.IC | D89: =IFERROR(VLOOKUP($C89,FS_연결!$A:$Z,D$2,FALSE),0) -> 0 | E89: =IFERROR(VLOOKUP($C89,FS_연결!$A:$Z,E$2,FALSE),0) -> 0 | F89: =IFERROR(VLOOKUP($C89,FS_연결!$A:$Z,F$2,FALSE),0) -> 0 | G89: =IFERROR(VLOOKUP($C89,FS_연결!$A:$Z,G$2,FALSE),0) -> 0 | H89: =IFERROR(VLOOKUP($C89,FS_연결!$A:$Z,H$2,FALSE),0) -> 0 | I89: =IFERROR(VLOOKUP($C89,FS_연결!$A:$Z,I$2,FALSE),0) -> 0 | J89: =IFERROR(VLOOKUP($C89,FS_연결!$A:$Z,J$2,FALSE),0) -> 0 | K89: =IFERROR(VLOOKUP($C89,FS_연결!$A:$Z,K$2,FALSE),0) -> 0 | L89: =IFERROR(VLOOKUP($C89,FS_연결!$A:$Z,L$2,FALSE),0) -> 0 | M89: =IFERROR(VLOOKUP($C89,FS_연결!$A:$AL,M$2,FALSE),0) -> 0 | N89: =IFERROR(VLOOKUP($C89,FS_연결!$A:$AL,N$2,FALSE),0) -> 0 | O89: =IFERROR(VLOOKUP($C89,'FS_연결(분기누적)'!$A:$BS,O$2,FALSE),0) -> 0 | P89: =IFERROR(VLOOKUP($C89,'FS_연결(분기누적)'!$A:$BS,P$2,FALSE),0) -> 0 | Q89: =N89 -> 0 | R89: =Q89 -> 0 | S89: =R89 -> 0
B90: 비유동기타금융자산 | D90: =SUM(D91:D93) -> 0 | E90: =SUM(E91:E93) -> 0 | F90: =SUM(F91:F93) -> 0 | G90: =SUM(G91:G93) -> 0 | H90: =SUM(H91:H93) -> 0 | I90: =SUM(I91:I93) -> 0 | J90: =SUM(J91:J93) -> 0 | K90: =SUM(K91:K93) -> 0 | ... S90: =SUM(S91:S93) -> 0
B91: 기타금융자산 | C91: A111640.IC | D91: =IFERROR(VLOOKUP($C91,FS_연결!$A:$Z,D$2,FALSE),0) -> 0 | E91: =IFERROR(VLOOKUP($C91,FS_연결!$A:$Z,E$2,FALSE),0) -> 0 | F91: =IFERROR(VLOOKUP($C91,FS_연결!$A:$Z,F$2,FALSE),0) -> 0 | G91: =IFERROR(VLOOKUP($C91,FS_연결!$A:$Z,G$2,FALSE),0) -> 0 | H91: =IFERROR(VLOOKUP($C91,FS_연결!$A:$Z,H$2,FALSE),0) -> 0 | I91: =IFERROR(VLOOKUP($C91,FS_연결!$A:$Z,I$2,FALSE),0) -> 0 | J91: =IFERROR(VLOOKUP($C91,FS_연결!$A:$Z,J$2,FALSE),0) -> 0 | K91: =IFERROR(VLOOKUP($C91,FS_연결!$A:$Z,K$2,FALSE),0) -> 0 | L91: =IFERROR(VLOOKUP($C91,FS_연결!$A:$Z,L$2,FALSE),0) -> 0 | M91: =IFERROR(VLOOKUP($C91,FS_연결!$A:$AL,M$2,FALSE),0) -> 0 | N91: =IFERROR(VLOOKUP($C91,FS_연결!$A:$AL,N$2,FALSE),0) -> 0 | O91: =IFERROR(VLOOKUP($C91,'FS_연결(분기누적)'!$A:$BS,O$2,FALSE),0) -> 0 | P91: =IFERROR(VLOOKUP($C91,'FS_연결(분기누적)'!$A:$BS,P$2,FALSE),0) -> 0 | Q91: =N91 -> 0 | R91: =Q91 -> 0 | S91: =R91 -> 0
B92: 당기손익-공정가치측정금융자산 | C92: A115010.IC | I92: =IFERROR(VLOOKUP($C92,FS_연결!$A:$Z,I$2,FALSE),0) -> 0 | J92: =IFERROR(VLOOKUP($C92,FS_연결!$A:$Z,J$2,FALSE),0) -> 0 | K92: =IFERROR(VLOOKUP($C92,FS_연결!$A:$Z,K$2,FALSE),0) -> 0 | L92: =IFERROR(VLOOKUP($C92,FS_연결!$A:$Z,L$2,FALSE),0) -> 0 | M92: =IFERROR(VLOOKUP($C92,FS_연결!$A:$AL,M$2,FALSE),0) -> 0 | N92: =IFERROR(VLOOKUP($C92,FS_연결!$A:$AL,N$2,FALSE),0) -> 0 | O92: =IFERROR(VLOOKUP($C92,'FS_연결(분기누적)'!$A:$BS,O$2,FALSE),0) -> 0 | P92: =IFERROR(VLOOKUP($C92,'FS_연결(분기누적)'!$A:$BS,P$2,FALSE),0) -> 0 | Q92: =N92 -> 0 | R92: =Q92 -> 0 | S92: =R92 -> 0
B93: 기타포괄손익-공정가치측정금융자산 | C93: A115020.IC | I93: =IFERROR(VLOOKUP($C93,FS_연결!$A:$Z,I$2,FALSE),0) -> 0 | J93: =IFERROR(VLOOKUP($C93,FS_연결!$A:$Z,J$2,FALSE),0) -> 0 | K93: =IFERROR(VLOOKUP($C93,FS_연결!$A:$Z,K$2,FALSE),0) -> 0 | L93: =IFERROR(VLOOKUP($C93,FS_연결!$A:$Z,L$2,FALSE),0) -> 0 | M93: =IFERROR(VLOOKUP($C93,FS_연결!$A:$AL,M$2,FALSE),0) -> 0 | N93: =IFERROR(VLOOKUP($C93,FS_연결!$A:$AL,N$2,FALSE),0) -> 0 | O93: =IFERROR(VLOOKUP($C93,'FS_연결(분기누적)'!$A:$BS,O$2,FALSE),0) -> 0 | P93: =IFERROR(VLOOKUP($C93,'FS_연결(분기누적)'!$A:$BS,P$2,FALSE),0) -> 0 | Q93: =N93 -> 0 | R93: =Q93 -> 0 | S93: =R93 -> 0
B94: 장기매출채권및기타채권 | C94: A111930.IC | I94: =IFERROR(VLOOKUP($C94,FS_연결!$A:$Z,I$2,FALSE),0) -> 0 | J94: =IFERROR(VLOOKUP($C94,FS_연결!$A:$Z,J$2,FALSE),0) -> 0 | K94: =IFERROR(VLOOKUP($C94,FS_연결!$A:$Z,K$2,FALSE),0) -> 0 | L94: =IFERROR(VLOOKUP($C94,FS_연결!$A:$Z,L$2,FALSE),0) -> 0 | M94: =IFERROR(VLOOKUP($C94,FS_연결!$A:$AL,M$2,FALSE),0) -> 0 | N94: =IFERROR(VLOOKUP($C94,FS_연결!$A:$AL,N$2,FALSE),0) -> 0 | O94: =IFERROR(VLOOKUP($C94,'FS_연결(분기누적)'!$A:$BS,O$2,FALSE),0) -> 0 | P94: =IFERROR(VLOOKUP($C94,'FS_연결(분기누적)'!$A:$BS,P$2,FALSE),0) -> 0 | Q94: =N94 -> 0 | R94: =Q94 -> 0 | S94: =R94 -> 0
B95: Others | D95: =D96-SUM(D82:D90)-D94 -> 0 | E95: =E96-SUM(E82:E90)-E94 -> 0 | F95: =F96-SUM(F82:F90)-F94 -> 0 | G95: =G96-SUM(G82:G90)-G94 -> 0 | H95: =H96-SUM(H82:H90)-H94 -> 0 | I95: =I96-SUM(I82:I90)-I94 -> 0 | J95: =J96-SUM(J82:J90)-J94 -> 0 | K95: =K96-SUM(K82:K90)-K94 -> 0 | ... P95: =P96-SUM(P82:P90)-P94 -> 0 | Q95: =N95 -> 0 | R95: =Q95 -> 0 | S95: =R95 -> 0
B96: 비유동자산 | C96: A110010.IC | D96: =IFERROR(VLOOKUP($C96,FS_연결!$A:$Z,D$2,FALSE),0) -> 0 | E96: =IFERROR(VLOOKUP($C96,FS_연결!$A:$Z,E$2,FALSE),0) -> 0 | F96: =IFERROR(VLOOKUP($C96,FS_연결!$A:$Z,F$2,FALSE),0) -> 0 | G96: =IFERROR(VLOOKUP($C96,FS_연결!$A:$Z,G$2,FALSE),0) -> 0 | H96: =IFERROR(VLOOKUP($C96,FS_연결!$A:$Z,H$2,FALSE),0) -> 0 | I96: =IFERROR(VLOOKUP($C96,FS_연결!$A:$Z,I$2,FALSE),0) -> 0 | J96: =IFERROR(VLOOKUP($C96,FS_연결!$A:$Z,J$2,FALSE),0) -> 0 | K96: =IFERROR(VLOOKUP($C96,FS_연결!$A:$Z,K$2,FALSE),0) -> 0 | L96: =IFERROR(VLOOKUP($C96,FS_연결!$A:$Z,L$2,FALSE),0) -> 0 | M96: =IFERROR(VLOOKUP($C96,FS_연결!$A:$AL,M$2,FALSE),0) -> 0 | N96: =IFERROR(VLOOKUP($C96,FS_연결!$A:$AL,N$2,FALSE),0) -> 0 | O96: =IFERROR(VLOOKUP($C96,'FS_연결(분기누적)'!$A:$BS,O$2,FALSE),0) -> 0 | P96: =IFERROR(VLOOKUP($C96,'FS_연결(분기누적)'!$A:$BS,P$2,FALSE),0) -> 0 | Q96: =Q82+Q83+Q86+Q88+Q89+Q95+Q90+Q84+Q94+Q87+Q85 -> #DIV/0! | R96: =R82+R83+R86+R88+R89+R95+R90+R84+R94+R87+R85 -> #DIV/0! | S96: =S82+S83+S86+S88+S89+S95+S90+S84+S94+S87+S85 -> #DIV/0!
B97: 자산총계 | C97: A110000.IC | D97: =D81+D96 -> 0 | E97: =E81+E96 -> 0 | F97: =F81+F96 -> 0 | G97: =G81+G96 -> 0 | H97: =H81+H96 -> 0 | I97: =I81+I96 -> 0 | J97: =J81+J96 -> 0 | K97: =K81+K96 -> 0 | ... S97: =S81+S96 -> #DIV/0!
B98: 매입채무 | C98: A132010.IC | D98: =IFERROR(VLOOKUP($C98,FS_연결!$A:$Z,D$2,FALSE),0) -> 0 | E98: =IFERROR(VLOOKUP($C98,FS_연결!$A:$Z,E$2,FALSE),0) -> 0 | F98: =IFERROR(VLOOKUP($C98,FS_연결!$A:$Z,F$2,FALSE),0) -> 0 | G98: =IFERROR(VLOOKUP($C98,FS_연결!$A:$Z,G$2,FALSE),0) -> 0 | H98: =IFERROR(VLOOKUP($C98,FS_연결!$A:$Z,H$2,FALSE),0) -> 0 | I98: =IFERROR(VLOOKUP($C98,FS_연결!$A:$Z,I$2,FALSE),0) -> 0 | J98: =IFERROR(VLOOKUP($C98,FS_연결!$A:$Z,J$2,FALSE),0) -> 0 | K98: =IFERROR(VLOOKUP($C98,FS_연결!$A:$Z,K$2,FALSE),0) -> 0 | L98: =IFERROR(VLOOKUP($C98,FS_연결!$A:$Z,L$2,FALSE),0) -> 0 | M98: =IFERROR(VLOOKUP($C98,FS_연결!$A:$AL,M$2,FALSE),0) -> 0 | N98: =IFERROR(VLOOKUP($C98,FS_연결!$A:$AL,N$2,FALSE),0) -> 0 | O98: =IFERROR(VLOOKUP($C98,'FS_연결(분기누적)'!$A:$BS,O$2,FALSE),0) -> 0 | P98: =IFERROR(VLOOKUP($C98,'FS_연결(분기누적)'!$A:$BS,P$2,FALSE),0) -> 0 | Q98: =Q99*Q22/365 -> #DIV/0! | R98: =R99*R22/365 -> #DIV/0! | S98: =S99*S22/365 -> #DIV/0!
B99: 회전기일 (매출액) | E99: =AVERAGE(E98,D98)/E$22*365 -> #DIV/0! | F99: =AVERAGE(F98,E98)/F$22*365 -> #DIV/0! | G99: =AVERAGE(G98,F98)/G$22*365 -> #DIV/0! | H99: =AVERAGE(H98,G98)/H$22*365 -> #DIV/0! | I99: =AVERAGE(I98,H98)/I$22*365 -> #DIV/0! | J99: =AVERAGE(J98,I98)/J$22*365 -> #DIV/0! | K99: =AVERAGE(K98,J98)/K$22*365 -> #DIV/0! | L99: =AVERAGE(L98,K98)/L$22*365 -> #DIV/0! | ... N99: =AVERAGE(N98,M98)/N$22*365 -> #DIV/0! | O99: =AVERAGE(O98,M98)/(O$22*IF(RIGHT(O$3,2)="1Q",4,IF(RIGHT(O$3,2)="2Q",2,IF(RIGHT(O$3,2)="3Q",4/3,"0"))))*365 -> #DIV/0! | P99: =AVERAGE(P98,N98)/(P$22*IF(RIGHT(P$3,2)="1Q",4,IF(RIGHT(P$3,2)="2Q",2,IF(RIGHT(P$3,2)="3Q",4/3,"0"))))*365 -> #DIV/0! | Q99: =AVERAGE(L99:N99) -> #DIV/0! | R99: =Q99 -> #DIV/0! | S99: =R99 -> #DIV/0! | V99: 3년 평균
B100: 유동계약부채 | C100: A115270.IC | D100: =IFERROR(VLOOKUP($C100,FS_연결!$A:$Z,D$2,FALSE),0) -> 0 | E100: =IFERROR(VLOOKUP($C100,FS_연결!$A:$Z,E$2,FALSE),0) -> 0 | F100: =IFERROR(VLOOKUP($C100,FS_연결!$A:$Z,F$2,FALSE),0) -> 0 | G100: =IFERROR(VLOOKUP($C100,FS_연결!$A:$Z,G$2,FALSE),0) -> 0 | H100: =IFERROR(VLOOKUP($C100,FS_연결!$A:$Z,H$2,FALSE),0) -> 0 | I100: =IFERROR(VLOOKUP($C100,FS_연결!$A:$Z,I$2,FALSE),0) -> 0 | J100: =IFERROR(VLOOKUP($C100,FS_연결!$A:$Z,J$2,FALSE),0) -> 0 | K100: =IFERROR(VLOOKUP($C100,FS_연결!$A:$Z,K$2,FALSE),0) -> 0 | L100: =IFERROR(VLOOKUP($C100,FS_연결!$A:$Z,L$2,FALSE),0) -> 0 | M100: =IFERROR(VLOOKUP($C100,FS_연결!$A:$AL,M$2,FALSE),0) -> 0 | N100: =IFERROR(VLOOKUP($C100,FS_연결!$A:$AL,N$2,FALSE),0) -> 0 | O100: =IFERROR(VLOOKUP($C100,'FS_연결(분기누적)'!$A:$BS,O$2,FALSE),0) -> 0 | P100: =IFERROR(VLOOKUP($C100,'FS_연결(분기누적)'!$A:$BS,P$2,FALSE),0) -> 0 | Q100: =N100 -> 0 | R100: =Q100 -> 0 | S100: =R100 -> 0
B101: 미지급금 | C101: A132070.IC | D101: =IFERROR(VLOOKUP($C101,FS_연결!$A:$Z,D$2,FALSE),0) -> 0 | E101: =IFERROR(VLOOKUP($C101,FS_연결!$A:$Z,E$2,FALSE),0) -> 0 | F101: =IFERROR(VLOOKUP($C101,FS_연결!$A:$Z,F$2,FALSE),0) -> 0 | G101: =IFERROR(VLOOKUP($C101,FS_연결!$A:$Z,G$2,FALSE),0) -> 0 | H101: =IFERROR(VLOOKUP($C101,FS_연결!$A:$Z,H$2,FALSE),0) -> 0 | I101: =IFERROR(VLOOKUP($C101,FS_연결!$A:$Z,I$2,FALSE),0) -> 0 | J101: =IFERROR(VLOOKUP($C101,FS_연결!$A:$Z,J$2,FALSE),0) -> 0 | K101: =IFERROR(VLOOKUP($C101,FS_연결!$A:$Z,K$2,FALSE),0) -> 0 | L101: =IFERROR(VLOOKUP($C101,FS_연결!$A:$Z,L$2,FALSE),0) -> 0 | M101: =IFERROR(VLOOKUP($C101,FS_연결!$A:$AL,M$2,FALSE),0) -> 0 | N101: =IFERROR(VLOOKUP($C101,FS_연결!$A:$AL,N$2,FALSE),0) -> 0 | O101: =IFERROR(VLOOKUP($C101,'FS_연결(분기누적)'!$A:$BS,O$2,FALSE),0) -> 0 | P101: =IFERROR(VLOOKUP($C101,'FS_연결(분기누적)'!$A:$BS,P$2,FALSE),0) -> 0 | Q101: =N101 -> 0 | R101: =Q101 -> 0 | S101: =R101 -> 0
B102: 선수금 | C102: A132350.IC | D102: =IFERROR(VLOOKUP($C102,FS_연결!$A:$Z,D$2,FALSE),0) -> 0 | E102: =IFERROR(VLOOKUP($C102,FS_연결!$A:$Z,E$2,FALSE),0) -> 0 | F102: =IFERROR(VLOOKUP($C102,FS_연결!$A:$Z,F$2,FALSE),0) -> 0 | G102: =IFERROR(VLOOKUP($C102,FS_연결!$A:$Z,G$2,FALSE),0) -> 0 | H102: =IFERROR(VLOOKUP($C102,FS_연결!$A:$Z,H$2,FALSE),0) -> 0 | I102: =IFERROR(VLOOKUP($C102,FS_연결!$A:$Z,I$2,FALSE),0) -> 0 | J102: =IFERROR(VLOOKUP($C102,FS_연결!$A:$Z,J$2,FALSE),0) -> 0 | K102: =IFERROR(VLOOKUP($C102,FS_연결!$A:$Z,K$2,FALSE),0) -> 0 | L102: =IFERROR(VLOOKUP($C102,FS_연결!$A:$Z,L$2,FALSE),0) -> 0 | M102: =IFERROR(VLOOKUP($C102,FS_연결!$A:$AL,M$2,FALSE),0) -> 0 | N102: =IFERROR(VLOOKUP($C102,FS_연결!$A:$AL,N$2,FALSE),0) -> 0 | O102: =IFERROR(VLOOKUP($C102,'FS_연결(분기누적)'!$A:$BS,O$2,FALSE),0) -> 0 | P102: =IFERROR(VLOOKUP($C102,'FS_연결(분기누적)'!$A:$BS,P$2,FALSE),0) -> 0 | Q102: =N102 -> 0 | R102: =Q102 -> 0 | S102: =R102 -> 0
...

Sheet Valuation
B1: 주식수 계산
B3: 주주명 | C3: 메자닌 발행 전 | E3: 금차 메자닌 전환 후 | G3: 금차 메자닌 전환 후 (Call 30%) | I3: 최대 Refixing | K3: 최대 Refixing (call 30%, refixing 70%)
C4: 주식수(주) | D4: 지분율 | E4: 주식수(주) | F4: 지분율 | G4: 주식수(주) | H4: 지분율 | I4: 주식수(주) | J4: 지분율(%) | K4: 주식수(주) | L4: 지분율(%)
B5: 뮤추얼그로우쓰 | C5: 23460780 | D5: =C5/C$12 -> 0.55381541 | E5: =C5 -> 23460780 | F5: =E5/E$12 -> 0.50568182 | G5: =E5+$C$17*MIN($G$14,D5) -> 24670457 | H5: =G5/G$12 -> 0.53175563 | I5: =E5 -> 23460780 | J5: =I5/I$12 -> 0.50568182 | K5: =I5+$D$17*MIN($G$14,D5) -> 24670457 | L5: =K5/K$12 -> 0.53175563
B6: 기타특관자 | C6: 117203 | D6: =C6/C$12 -> 0.0027666952 | E6: =C6 -> 117203 | F6: =E6/E$12 -> 0.0025262343 | G6: =E6 -> 117203 | H6: =G6/G$12 -> 0.0025262343 | I6: =E6 -> 117203 | J6: =I6/I$12 -> 0.0025262343 | K6: =C6 -> 117203 | L6: =K6/K$12 -> 0.0025262343
B7: 자기주식 | C7: 1064 | D7: =C7/C$12 -> 2.5116795e-05 | E7: =C7 -> 1064 | F7: =E7/E$12 -> 2.2933827e-05 | G7: =E7 -> 1064 | H7: =G7/G$12 -> 2.2933827e-05 | I7: =G7 -> 1064 | J7: =I7/I$12 -> 2.2933827e-05 | K7: =I7 -> 1064 | L7: =K7/K$12 -> 2.2933827e-05
B8: 기타주주 | C8: 18783046 | D8: =C8/C$12 -> 0.44339278 | E8: =C8 -> 18783046 | F8: =E8/E$12 -> 0.40485632 | G8: =E8 -> 18783046 | H8: =G8/G$12 -> 0.40485632 | I8: =E8 -> 18783046 | J8: =I8/I$12 -> 0.40485632 | K8: =I8 -> 18783046 | L8: =K8/K$12 -> 0.40485632
B9: CB(당사) | C9: - | D9: - | E9: =C18 -> 403225 | F9: =E9/E$12 -> 0.0086912521 | G9: =E9*(1-$G$14) -> 282257.5 | H9: =G9/G$12 -> 0.0060838765 | I9: =D18 -> 403225 | J9: =I9/I$12 -> 0.0086912521 | K9: =I9*(1-$G$14) -> 282257.5 | L9: =K9/K$12 -> 0.0060838765
B10: CB(공동투자자) | C10: - | D10: - | E10: =C19 -> 3629033 | F10: =E10/E$12 -> 0.078221441 | G10: =E10*(1-$G$14) -> 2540323.1 | H10: =G10/G$12 -> 0.054755009 | I10: =D19 -> 3629033 | J10: =I10/I$12 -> 0.078221441 | K10: =I10*(1-$G$14) -> 2540323.1 | L10: =K10/K$12 -> 0.054755009
B11: =F17 -> 기발행 미상환 전환사채 | C11: - | D11: - | E11: =G17 -> 0 | F11: =E11/E$12 -> 0 | G11: =E11 -> 0 | H11: =G11/G$12 -> 0 | I11: =E11 -> 0 | J11: =I11/I$12 -> 0 | K11: =I11 -> 0 | L11: =K11/K$12 -> 0
B12: 합 계 | C12: 42362093 | D12: =SUM(D5:D11) -> 1 | E12: =SUM(E5:E11) -> 46394351 | F12: =SUM(F5:F11) -> 1 | G12: =SUM(G5:G11) -> 46394351 | H12: =SUM(H5:H11) -> 1 | I12: =SUM(I5:I11) -> 46394351 | J12: =SUM(J5:J11) -> 1 | K12: =SUM(K5:K11) -> 46394351 | L12: =K12/K$12 -> 1
B14: 전환가액 | C14: 4960 | D14: =C14*D16 -> 4960 | F14: Call | G14: 0.3 | I14: 발행규모 | J14: 200
B15: 할인/할증 | F15: YTC | G15: 0.001 | I15: 당사 | J15: 20
B16: 액면 | C16: =J14*100000000 -> 20000000000 | D16: 1 | F16: YTP | G16: 0
B17: 주식수 | C17: =ROUNDDOWN(C16/C14,0) -> 4032258 | D17: =ROUNDDOWN(C16/D14,0) -> 4032258 | F17: 기발행 미상환 전환사채 | G17: 0
B18: =I15 -> 당사 | C18: =ROUNDDOWN(C17*J15/J14,0) -> 403225 | D18: =ROUNDDOWN(D17*J15/J14,0) -> 403225
B19: 이외 | C19: =C17-C18 -> 3629033 | D19: =D17-D18 -> 3629033 | I19: 청약수수료
B21: 수익률 계산
B23: 밸류에이션 | C23: 발행 전 | D23: PER | E23: PER (리픽싱) | F23: Put 행사
C24: '24년 | D24: 27년 | E24: 27년 | F24: 27년
B25: 매출액 (억원)
B26: PSR Multiple (배)
B27: 당기순이익 (억원) | D27: 151 | E27: =D27 -> 151
B28: PER Multiple (배) | D28: 20 | E28: =D28 -> 20
B29: 시총 (억원) | C29: =C30*C31/10^8 -> 5867.1499 | D29: =D27*D28 -> 3020 | E29: =E27*E28 -> 3020
B30: 상장주식수(희석포함, 주) | C30: =C12 -> 42362093 | D30: =$E$12 -> 46394351 | E30: =$K$12 -> 46394351
B31: (예상)주가 | C31: 13850 | D31: =D29/D30*100000000 -> 6509.4132 | E31: =E29/E30*100000000 -> 6509.4132
B32: 당조합주식수 | D32: =G9 -> 282257.5 | E32: =K9 -> 282257.5
B33: MoIC (배) | D33: =I42 -> 1.2192656 | E33: =I49 -> 1.2192656 | F33: =I56 -> 1
B34: IRR (%) | D34: =H42 -> 0.10420362 | E34: =H49 -> 0.10420362 | F34: =H56 -> 2.9802322e-09
B36: Gross IRR
A37: 1 | B37: =D23 -> PER | D37: 투자
B38: =D24 -> 27년 | C38: (단위: 백만원) | D38: =D$45 -> 45930 | E38: =E$45 -> 46295 | F38: =F$45 -> 46660 | H38: 비고 | I38: MoIC
C39: 투자/회수 | D39: =D46 -> -2000 | E39: - | F39: =D31*D32/1000000 -> 1837.3307
C40: 청약수수료 | D40: =D39*$J$19 -> 0 | F40: -
C41: Call | D41: - | E41: - | F41: =-D46*$G$14*(1+$G$15)^((F38-D38)/365) -> 601.2006 | H41: Call Option 30%
C42: Gross IRR | D42: =SUM(D39:D41) -> -2000 | E42: =SUM(E39:E41) -> 0 | F42: =SUM(F39:F41) -> 2438.5313 | H42: =XIRR(D42:G42,D$38:G$38) -> 0.10420362 | I42: =-(F42+G42)/(D42) -> 1.2192656
A44: 2 | B44: =E23 -> PER (리픽싱) | D44: 투자
B45: =E24 -> 27년 | C45: (단위: 백만원) | D45: 45930 | E45: =EOMONTH(D45,12) -> 46295 | F45: =EOMONTH(E45,12) -> 46660 | H45: 비고 | I45: MoIC
C46: 투자/회수 | D46: =-$J$15*100 -> -2000 | F46: =E31*E32/1000000 -> 1837.3307
C47: 청약수수료 | D47: =D46*$J$19 -> 0
C48: Call | F48: =-D53*$G$14*(1+$G$15)^((F38-D38)/365) -> 601.2006 | H48: Call Option 30%
C49: Gross IRR | D49: =SUM(D46:D48) -> -2000 | E49: =SUM(E46:E48) -> 0 | F49: =SUM(F46:F48) -> 2438.5313 | G49: =SUM(G46:G48) -> 0 | H49: =XIRR(D49:G49,D$45:G$45) -> 0.10420362 | I49: =-(F49+G49)/(D49) -> 1.2192656
A51: 3 | B51: =F23 -> Put 행사 | D51: 투자
B52: =F24 -> 27년 | C52: (단위: 백만원) | D52: =D$45 -> 45930 | E52: =E$45 -> 46295 | F52: =F$45 -> 46660 | G52: =EOMONTH(F52,6) -> 46843 | H52: 비고 | I52: MoIC
C53: 투자/회수 | D53: =D46 -> -2000 | G53: =-D53*(1+G16)^2 -> 2000
C54: 청약수수료 | D54: =D53*$J$19 -> 0
C55: Call
C56: Gross IRR | D56: =SUM(D53:D55) -> -2000 | E56: =SUM(E53:E55) -> 0 | F56: =SUM(F53:F55) -> 0 | G56: =SUM(G53:G55) -> 2000 | H56: =XIRR(D56:G56,D$52:G$52) -> 2.9802322e-09 | I56: =-(F56+G56)/(D56) -> 1

Sheet back
B2: 매출 | C2: 18 | D2: 19 | E2: 20 | F2: 21 | G2: 22 | H2: 23 | I2: 24 | J2: 24.1H | K2: 25.1H
B3: 아스팔트 | C3: 2409 | D3: 2410 | E3: 2340 | F3: 2752 | G3: 3553 | H3: 3412 | I3: 3789 | J3: 1871 | K3: 1722
B4: 합성수지 | C4: 1028 | D4: 1018 | E4: 989 | F4: 1281 | G4: 1441 | H4: 1352 | I4: 1425 | J4: 706 | K4: 754
B5: 케미칼 | C5: 1421 | D5: 1339 | E5: 1476 | F5: 2233 | G5: 2465 | H5: 2003 | I5: 1963 | J5: 985 | K5: 1024
B6: 기타 | C6: -45 | D6: 87 | E6: 35 | F6: 23 | G6: 20 | H6: 25 | I6: 35 | J6: 17 | K6: 10
C7: =SUM(C3:C6) -> 4813 | D7: =SUM(D3:D6) -> 4854 | E7: =SUM(E3:E6) -> 4840 | F7: =SUM(F3:F6) -> 6289 | G7: =SUM(G3:G6) -> 7479 | H7: =SUM(H3:H6) -> 6792 | I7: =SUM(I3:I6) -> 7212 | J7: =SUM(J3:J6) -> 3579 | K7: =SUM(K3:K6) -> 3510
B9: 영업이익 | C9: 18 | D9: 19 | E9: 20 | F9: 21 | G9: 22 | H9: 23 | I9: 24 | J9: 24.1H | K9: 25.1H
B10: 아스팔트 | C10: 100 | D10: 116 | E10: 133 | F10: 78 | G10: 98 | H10: 95 | I10: 51 | J10: 34 | K10: 16
B11: 합성수지 | C11: 14 | D11: 21 | E11: 33 | F11: 33 | G11: 31 | H11: 25 | I11: 32 | J11: 19 | K11: 14
B12: 케미칼 | C12: 19 | D12: 14 | E12: 22 | F12: 66 | G12: 35 | H12: 18 | I12: 27 | J12: 15 | K12: 11
B13: 기타 | C13: -50 | D13: =-91+1 -> -90 | E13: =-31+17 -> -14 | F13: =-28+7 -> -21 | G13: =9+7 -> 16 | H13: =11+3 -> 14 | I13: =18+11 -> 29 | J13: 14 | K13: 0
C14: =SUM(C10:C13) -> 83 | D14: =SUM(D10:D13) -> 61 | E14: =SUM(E10:E13) -> 174 | F14: =SUM(F10:F13) -> 156 | G14: =SUM(G10:G13) -> 180 | H14: =SUM(H10:H13) -> 152 | I14: =SUM(I10:I13) -> 139 | J14: =SUM(J10:J13) -> 82 | K14: =SUM(K10:K13) -> 41
B16: 이익률 | C16: 18 | D16: 19 | E16: 20 | F16: 21 | G16: 22 | H16: 23 | I16: 24 | J16: 24.1H | K16: 25.1H
B17: 아스팔트 | C17: =C10/C3 -> 0.041511 | D17: =D10/D3 -> 0.04813278 | E17: =E10/E3 -> 0.056837607 | F17: =F10/F3 -> 0.028343023 | G17: =G10/G3 -> 0.027582325 | H17: =H10/H3 -> 0.027842907 | I17: =I10/I3 -> 0.013460016 | J17: =J10/J3 -> 0.0181721 | K17: =K10/K3 -> 0.0092915215
B18: 합성수지 | C18: =C11/C4 -> 0.013618677 | D18: =D11/D4 -> 0.020628684 | E18: =E11/E4 -> 0.033367037 | F18: =F11/F4 -> 0.025761124 | G18: =G11/G4 -> 0.021512838 | H18: =H11/H4 -> 0.018491124 | I18: =I11/I4 -> 0.02245614 | J18: =J11/J4 -> 0.026912181 | K18: =K11/K4 -> 0.018567639
B19: 케미칼 | C19: =C12/C5 -> 0.013370866 | D19: =D12/D5 -> 0.010455564 | E19: =E12/E5 -> 0.014905149 | F19: =F12/F5 -> 0.02955665 | G19: =G12/G5 -> 0.014198783 | H19: =H12/H5 -> 0.0089865202 | I19: =I12/I5 -> 0.013754457 | J19: =J12/J5 -> 0.015228426 | K19: =K12/K5 -> 0.010742188
B20: 기타 | C20: =C13/C6 -> 1.1111111 | D20: =D13/D6 -> -1.0344828 | E20: =E13/E6 -> -0.4 | F20: =F13/F6 -> -0.91304348 | G20: =G13/G6 -> 0.8 | H20: =H13/H6 -> 0.56 | I20: =I13/I6 -> 0.82857143 | J20: =J13/J6 -> 0.82352941 | K20: =K13/K6 -> 0
C21: =C14/C7 -> 0.017244962 | D21: =D14/D7 -> 0.012566955 | E21: =E14/E7 -> 0.035950413 | F21: =F14/F7 -> 0.024805215 | G21: =G14/G7 -> 0.024067389 | H21: =H14/H7 -> 0.02237927 | I21: =I14/I7 -> 0.019273433 | J21: =J14/J7 -> 0.022911428 | K21: =K14/K7 -> 0.011680912
B23: 매출증가율 | C23: 18 | D23: 19 | E23: 20 | F23: 21 | G23: 22 | H23: 23 | I23: 24 | J23: 24.1H | K23: 25.1H
B24: 아스팔트 | D24: =D3/C3-1 -> 0.00041511 | E24: =E3/D3-1 -> -0.029045643 | F24: =F3/E3-1 -> 0.17606838 | G24: =G3/F3-1 -> 0.29106105 | H24: =H3/G3-1 -> -0.039684773 | I24: =I3/H3-1 -> 0.11049238 | K24: =K3/J3-1 -> -0.079636558
B25: 합성수지 | D25: =D4/C4-1 -> -0.0097276265 | E25: =E4/D4-1 -> -0.02848723 | F25: =F4/E4-1 -> 0.29524772 | G25: =G4/F4-1 -> 0.12490242 | H25: =H4/G4-1 -> -0.061762665 | I25: =I4/H4-1 -> 0.053994083 | K25: =K4/J4-1 -> 0.067988669
B26: 케미칼 | D26: =D5/C5-1 -> -0.057705841 | E26: =E5/D5-1 -> 0.10231516 | F26: =F5/E5-1 -> 0.51287263 | G26: =G5/F5-1 -> 0.1038961 | H26: =H5/G5-1 -> -0.18742394 | I26: =I5/H5-1 -> -0.019970045 | K26: =K5/J5-1 -> 0.039593909
B28: 계 | D28: =D7/C7-1 -> 0.0085185955 | E28: =E7/D7-1 -> -0.0028842192 | F28: =F7/E7-1 -> 0.29938017 | G28: =G7/F7-1 -> 0.18921927 | H28: =H7/G7-1 -> -0.0918572 | I28: =I7/H7-1 -> 0.061837456 | K28: =K7/J7-1 -> -0.019279128
C30: 18 | D30: 19 | E30: 20 | F30: 21 | G30: 22 | H30: 23 | I30: 24
B31: 국내매출 | C31: 4286.5951 | D31: 4303.2597 | E31: 4349.8956 | F31: 5596.0991 | G31: 6597.037 | H31: 5984.8223 | I31: 6346.0463
B32: 아시아 | C32: 470.18062 | D32: 492.38852 | E32: 479.1897 | F32: 691.42036 | G32: 869.19111 | H32: 745.75948 | I32: 755.29528
B33: 오세아니아 | C33: 17.956721 | D33: 17.937962 | E33: 7.8467825 | F33: - | G33: 13.131743 | H33: 60.461114 | I33: 109.00421
B34: 유럽 | C34: 36.626231 | D34: 39.630897 | E34: 3.2000557 | F34: 0.35034731 | G34: - | H34: 0.77425537 | I34: 0.09782649
B35: 아메리카 | C35: 1.6230392 | D35: 0.6489387 | E35: - | F35: 0.23411324 | G35: - | H35: 0.28774016 | I35: 1.3190851
B36: 아프리카 | C36: 0 | D36: 0 | E36: - | F36: 1.0200126 | G36: - | H36: 0.22948164 | I36: -
B37: 합계 | C37: =SUM(C31:C36) -> 4812.9817 | D37: =SUM(D31:D36) -> 4853.866 | E37: =SUM(E31:E36) -> 4840.1322 | F37: =SUM(F31:F36) -> 6289.1239 | G37: =SUM(G31:G36) -> 7479.3599 | H37: =SUM(H31:H36) -> 6792.3344 | I37: =SUM(I31:I36) -> 7211.7627
B38: 국내 비중 | C38: =C31/C37 -> 0.89063191 | D38: =D31/D37 -> 0.88656335 | E38: =E31/E37 -> 0.89871423 | F38: =F31/F37 -> 0.88980582 | G38: =G31/G37 -> 0.8820323 | H38: =H31/H37 -> 0.88111421 | I38: =I31/I37 -> 0.87995773
B41: 흥국증권 | C41: 25 | D41: 26 | E41: 27
B42: 매출액 | C42: =컨센!F15/100000 -> 1051 | D42: =컨센!G15/100000 -> 0 | E42: =컨센!H15/100000 -> 0
B43: 영업이익 | C43: =컨센!K15/100000 -> 12 | D43: =컨센!L15/100000 -> 0 | E43: =컨센!M15/100000 -> 0
B44: 당기순이익 | C44: =컨센!P15/100000 -> 8 | D44: =컨센!Q15/100000 -> 0 | E44: =컨센!R15/100000 -> 0

Sheet 컨센
A1: Refresh | B1: Last Update : 2025-11-06 17:20:04
A3: 에이팩트 | C3: Consensus Structure
A4: Code | B4: ='#보고서'!B2 -> A200470 | C4: 3M | D4: Descending
A5: Consensus Date | B5: CPD-1TD [20251105] | C5: Korean
D7: E610300 | E7: E612504 | F7: E121000.M | G7: E121000.M | H7: E121000.M | I7: E121000.M | J7: E121000.M | K7: E121500.M | L7: E121500.M | M7: E121500.M | N7: E121500.M | O7: E121500.M | P7: E122710.M | Q7: E122710.M | R7: E122710.M | S7: E122710.M | T7: E122710.M
F8: 2025AS | G8: 2026AS | H8: 2027AS | I8: 2028AS | J8: 2029AS | K8: 2025AS | L8: 2026AS | M8: 2027AS | N8: 2028AS | O8: 2029AS | P8: 2025AS | Q8: 2026AS | R8: 2027AS | S8: 2028AS | T8: 2029AS | BK8: T_PER
B9: 20251105 | D9: 목표주가 | E9: 목표주가변경방향 | F9: 매출액 | G9: 매출액 | H9: 매출액 | I9: 매출액 | J9: 매출액 | K9: 영업이익 | L9: 영업이익 | M9: 영업이익 | N9: 영업이익 | O9: 영업이익 | P9: 당기순이익(지배) | Q9: 당기순이익(지배) | R9: 당기순이익(지배) | S9: 당기순이익(지배) | T9: 당기순이익(지배) | BK9: 2018 | BL9: 2019
B10: Consensus Data | F10: 105100000 | K10: 1200000 | P10: 800000 | BK10: =$BG10/($BE10/[2]EM!$B$3) -> #DIV/0! | BL10: =$BG10/($BF10/[2]EM!$B$3) -> #DIV/0!
B11: High | D11: =IF(COUNT($D$15:$D$15)=0,"",MAX($D$15:$D$15)) | E11: =IF(COUNT($E$15:$E$15)=0,"",MAX($E$15:$E$15)) | F11: 105100000 | G11: =IF(COUNT($G$15:$G$15)=0,"",MAX($G$15:$G$15)) | H11: =IF(COUNT($H$15:$H$15)=0,"",MAX($H$15:$H$15)) | I11: =IF(COUNT($I$15:$I$15)=0,"",MAX($I$15:$I$15)) | J11: =IF(COUNT($J$15:$J$15)=0,"",MAX($J$15:$J$15)) | K11: 1200000 | L11: =IF(COUNT($L$15:$L$15)=0,"",MAX($L$15:$L$15)) | M11: =IF(COUNT($M$15:$M$15)=0,"",MAX($M$15:$M$15)) | N11: =IF(COUNT($N$15:$N$15)=0,"",MAX($N$15:$N$15)) | O11: =IF(COUNT($O$15:$O$15)=0,"",MAX($O$15:$O$15)) | P11: 800000 | Q11: =IF(COUNT($Q$15:$Q$15)=0,"",MAX($Q$15:$Q$15)) | R11: =IF(COUNT($R$15:$R$15)=0,"",MAX($R$15:$R$15)) | S11: =IF(COUNT($S$15:$S$15)=0,"",MAX($S$15:$S$15)) | T11: =IF(COUNT($T$15:$T$15)=0,"",MAX($T$15:$T$15)) | W11: =IF(COUNT($W$14:$W$15)=0,"",MAX($W$14:$W$15)) | X11: =IF(COUNT($X$14:$X$15)=0,"",MAX($X$14:$X$15)) | Y11: =IF(COUNT($Y$14:$Y$15)=0,"",MAX($Y$14:$Y$15)) | Z11: =IF(COUNT($Z$14:$Z$15)=0,"",MAX($Z$14:$Z$15)) | AA11: =IF(COUNT($AA$14:$AA$15)=0,"",MAX($AA$14:$AA$15)) | AB11: =IF(COUNT($AB$14:$AB$15)=0,"",MAX($AB$14:$AB$15)) | AC11: =IF(COUNT($AC$14:$AC$15)=0,"",MAX($AC$14:$AC$15)) | AD11: =IF(COUNT($AD$14:$AD$15)=0,"",MAX($AD$14:$AD$15)) | AE11: =IF(COUNT($AE$14:$AE$15)=0,"",MAX($AE$14:$AE$15)) | AF11: =IF(COUNT($AF$14:$AF$15)=0,"",MAX($AF$14:$AF$15)) | AG11: =IF(COUNT($AG$14:$AG$15)=0,"",MAX($AG$14:$AG$15)) | AH11: =IF(COUNT($AH$14:$AH$15)=0,"",MAX($AH$14:$AH$15)) | AI11: =IF(COUNT($AI$14:$AI$15)=0,"",MAX($AI$14:$AI$15)) | AJ11: =IF(COUNT($AJ$14:$AJ$15)=0,"",MAX($AJ$14:$AJ$15)) | AK11: =IF(COUNT($AK$14:$AK$15)=0,"",MAX($AK$14:$AK$15)) | AL11: =IF(COUNT($AL$14:$AL$15)=0,"",MAX($AL$14:$AL$15)) | AM11: =IF(COUNT($AM$14:$AM$15)=0,"",MAX($AM$14:$AM$15)) | AN11: =IF(COUNT($AN$14:$AN$15)=0,"",MAX($AN$14:$AN$15)) | AO11: =IF(COUNT($AO$14:$AO$15)=0,"",MAX($AO$14:$AO$15)) | AP11: =IF(COUNT($AP$14:$AP$15)=0,"",MAX($AP$14:$AP$15)) | AQ11: =IF(COUNT($AQ$14:$AQ$15)=0,"",MAX($AQ$14:$AQ$15)) | AR11: =IF(COUNT($AR$14:$AR$15)=0,"",MAX($AR$14:$AR$15)) | AS11: =IF(COUNT($AS$14:$AS$15)=0,"",MAX($AS$14:$AS$15)) | AT11: =IF(COUNT($AT$14:$AT$15)=0,"",MAX($AT$14:$AT$15)) | AU11: =IF(COUNT($AU$14:$AU$15)=0,"",MAX($AU$14:$AU$15)) | AV11: =IF(COUNT($AV$14:$AV$15)=0,"",MAX($AV$14:$AV$15)) | AW11: =IF(COUNT($AW$14:$AW$15)=0,"",MAX($AW$14:$AW$15)) | AX11: =IF(COUNT($AX$14:$AX$15)=0,"",MAX($AX$14:$AX$15)) | AY11: =IF(COUNT($AY$14:$AY$15)=0,"",MAX($AY$14:$AY$15)) | AZ11: =IF(COUNT($AZ$14:$AZ$15)=0,"",MAX($AZ$14:$AZ$15)) | BA11: =IF(COUNT($BA$14:$BA$15)=0,"",MAX($BA$14:$BA$15)) | BB11: =IF(COUNT($BB$14:$BB$15)=0,"",MAX($BB$14:$BB$15)) | BC11: =IF(COUNT($BC$14:$BC$15)=0,"",MAX($BC$14:$BC$15)) | BD11: =IF(COUNT($BD$14:$BD$15)=0,"",MAX($BD$14:$BD$15)) | BE11: =IF(COUNT($BE$14:$BE$15)=0,"",MAX($BE$14:$BE$15)) | BF11: =IF(COUNT($BF$14:$BF$15)=0,"",MAX($BF$14:$BF$15)) | BG11: =IF(COUNT($BG$14:$BG$15)=0,"",MAX($BG$14:$BG$15)) | BH11: =IF(COUNT($BH$14:$BH$15)=0,"",MAX($BH$14:$BH$15)) | BK11: =$BG11/($BE11/[2]EM!$B$3) -> #VALUE! | BL11: =$BG11/($BF11/[2]EM!$B$3) -> #VALUE!
B12: Median | F12: =IF(COUNT($F$15:$F$15)=0,"",MEDIAN($F$15:$F$15)) -> 105100000 | K12: =IF(COUNT($K$15:$K$15)=0,"",MEDIAN($K$15:$K$15)) -> 1200000 | P12: =IF(COUNT($P$15:$P$15)=0,"",MEDIAN($P$15:$P$15)) -> 800000 | BK12: =$BG12/($BE12/[2]EM!$B$3) -> #DIV/0! | BL12: =$BG12/($BF12/[2]EM!$B$3) -> #DIV/0!
B13: Low | D13: =IF(COUNT($D$15:$D$15)=0,"",MIN($D$15:$D$15)) | E13: =IF(COUNT($E$15:$E$15)=0,"",MIN($E$15:$E$15)) | F13: 105100000 | G13: =IF(COUNT($G$15:$G$15)=0,"",MIN($G$15:$G$15)) | H13: =IF(COUNT($H$15:$H$15)=0,"",MIN($H$15:$H$15)) | I13: =IF(COUNT($I$15:$I$15)=0,"",MIN($I$15:$I$15)) | J13: =IF(COUNT($J$15:$J$15)=0,"",MIN($J$15:$J$15)) | K13: 1200000 | L13: =IF(COUNT($L$15:$L$15)=0,"",MIN($L$15:$L$15)) | M13: =IF(COUNT($M$15:$M$15)=0,"",MIN($M$15:$M$15)) | N13: =IF(COUNT($N$15:$N$15)=0,"",MIN($N$15:$N$15)) | O13: =IF(COUNT($O$15:$O$15)=0,"",MIN($O$15:$O$15)) | P13: 800000 | Q13: =IF(COUNT($Q$15:$Q$15)=0,"",MIN($Q$15:$Q$15)) | R13: =IF(COUNT($R$15:$R$15)=0,"",MIN($R$15:$R$15)) | S13: =IF(COUNT($S$15:$S$15)=0,"",MIN($S$15:$S$15)) | T13: =IF(COUNT($T$15:$T$15)=0,"",MIN($T$15:$T$15)) | W13: =IF(COUNT($W$14:$W$15)=0,"",MIN($W$14:$W$15)) | X13: =IF(COUNT($X$14:$X$15)=0,"",MIN($X$14:$X$15)) | Y13: =IF(COUNT($Y$14:$Y$15)=0,"",MIN($Y$14:$Y$15)) | Z13: =IF(COUNT($Z$14:$Z$15)=0,"",MIN($Z$14:$Z$15)) | AA13: =IF(COUNT($AA$14:$AA$15)=0,"",MIN($AA$14:$AA$15)) | AB13: =IF(COUNT($AB$14:$AB$15)=0,"",MIN($AB$14:$AB$15)) | AC13: =IF(COUNT($AC$14:$AC$15)=0,"",MIN($AC$14:$AC$15)) | AD13: =IF(COUNT($AD$14:$AD$15)=0,"",MIN($AD$14:$AD$15)) | AE13: =IF(COUNT($AE$14:$AE$15)=0,"",MIN($AE$14:$AE$15)) | AF13: =IF(COUNT($AF$14:$AF$15)=0,"",MIN($AF$14:$AF$15)) | AG13: =IF(COUNT($AG$14:$AG$15)=0,"",MIN($AG$14:$AG$15)) | AH13: =IF(COUNT($AH$14:$AH$15)=0,"",MIN($AH$14:$AH$15)) | AI13: =IF(COUNT($AI$14:$AI$15)=0,"",MIN($AI$14:$AI$15)) | AJ13: =IF(COUNT($AJ$14:$AJ$15)=0,"",MIN($AJ$14:$AJ$15)) | AK13: =IF(COUNT($AK$14:$AK$15)=0,"",MIN($AK$14:$AK$15)) | AL13: =IF(COUNT($AL$14:$AL$15)=0,"",MIN($AL$14:$AL$15)) | AM13: =IF(COUNT($AM$14:$AM$15)=0,"",MIN($AM$14:$AM$15)) | AN13: =IF(COUNT($AN$14:$AN$15)=0,"",MIN($AN$14:$AN$15)) | AO13: =IF(COUNT($AO$14:$AO$15)=0,"",MIN($AO$14:$AO$15)) | AP13: =IF(COUNT($AP$14:$AP$15)=0,"",MIN($AP$14:$AP$15)) | AQ13: =IF(COUNT($AQ$14:$AQ$15)=0,"",MIN($AQ$14:$AQ$15)) | AR13: =IF(COUNT($AR$14:$AR$15)=0,"",MIN($AR$14:$AR$15)) | AS13: =IF(COUNT($AS$14:$AS$15)=0,"",MIN($AS$14:$AS$15)) | AT13: =IF(COUNT($AT$14:$AT$15)=0,"",MIN($AT$14:$AT$15)) | AU13: =IF(COUNT($AU$14:$AU$15)=0,"",MIN($AU$14:$AU$15)) | AV13: =IF(COUNT($AV$14:$AV$15)=0,"",MIN($AV$14:$AV$15)) | AW13: =IF(COUNT($AW$14:$AW$15)=0,"",MIN($AW$14:$AW$15)) | AX13: =IF(COUNT($AX$14:$AX$15)=0,"",MIN($AX$14:$AX$15)) | AY13: =IF(COUNT($AY$14:$AY$15)=0,"",MIN($AY$14:$AY$15)) | AZ13: =IF(COUNT($AZ$14:$AZ$15)=0,"",MIN($AZ$14:$AZ$15)) | BA13: =IF(COUNT($BA$14:$BA$15)=0,"",MIN($BA$14:$BA$15)) | BB13: =IF(COUNT($BB$14:$BB$15)=0,"",MIN($BB$14:$BB$15)) | BC13: =IF(COUNT($BC$14:$BC$15)=0,"",MIN($BC$14:$BC$15)) | BD13: =IF(COUNT($BD$14:$BD$15)=0,"",MIN($BD$14:$BD$15)) | BE13: =IF(COUNT($BE$14:$BE$15)=0,"",MIN($BE$14:$BE$15)) | BF13: =IF(COUNT($BF$14:$BF$15)=0,"",MIN($BF$14:$BF$15)) | BG13: =IF(COUNT($BG$14:$BG$15)=0,"",MIN($BG$14:$BG$15)) | BH13: =IF(COUNT($BH$14:$BH$15)=0,"",MIN($BH$14:$BH$15)) | BK13: =$BG13/($BE13/[2]EM!$B$3) -> #VALUE! | BL13: =$BG13/($BF13/[2]EM!$B$3) -> #VALUE!
A14: Date | B14: Security | C14: Analyst
A15: 45932 | B15: 키움증권 | C15: 오현진 | F15: 105100000 | K15: 1200000 | P15: 800000 | BK15: =$BG15/($BE15/[2]EM!$B$3) -> #DIV/0! | BL15: =$BG15/($BF15/[2]EM!$B$3) -> #DIV/0!
A16: ※ 당일 입력된 추정치의 영향으로 컨센서스 값과 개별 추정치의 평균 값이 달라질 수 있음 | BK16: =$BG16/($BE16/[2]EM!$B$3) -> #DIV/0! | BL16: =$BG16/($BF16/[2]EM!$B$3) -> #DIV/0!
BK17: =$BG17/($BE17/[2]EM!$B$3) -> #DIV/0! | BL17: =$BG17/($BF17/[2]EM!$B$3) -> #DIV/0!
BK18: =$BG18/($BE18/[2]EM!$B$3) -> #DIV/0! | BL18: =$BG18/($BF18/[2]EM!$B$3) -> #DIV/0!
BK19: =$BG19/($BE19/[2]EM!$B$3) -> #DIV/0! | BL19: =$BG19/($BF19/[2]EM!$B$3) -> #DIV/0!
BK20: =$BG20/($BE20/[2]EM!$B$3) -> #DIV/0! | BL20: =$BG20/($BF20/[2]EM!$B$3) -> #DIV/0!
BK21: =$BG21/($BE21/[2]EM!$B$3) -> #DIV/0! | BL21: =$BG21/($BF21/[2]EM!$B$3) -> #DIV/0!
BK22: =$BG22/($BE22/[2]EM!$B$3) -> #DIV/0! | BL22: =$BG22/($BF22/[2]EM!$B$3) -> #DIV/0!
BK23: =$BG23/($BE23/[2]EM!$B$3) -> #DIV/0! | BL23: =$BG23/($BF23/[2]EM!$B$3) -> #DIV/0!

Sheet 주가
A1: Refresh | B1: Last Update : 2025-11-06 17:20:06
A2: 0
A3: Time Series (Company)
A4: Frequency | B4: D | C4: Descending | D4: 1 | N4: 100000000
A5: Period(From) | B5: 20100102 | C5: Korean | D5: 0
A6: Period(To) | B6: CPD-1TD [20251105] | D6: 0 | M6: =AVERAGE(M15:M1222) -> 14.282649
M7: =_xlfn.STDEV.P(M15:M1222) -> 18.601631
A8: Code | B8: ='#보고서'!$B$2 -> A200470 | C8: ='#보고서'!$B$2 -> A200470 | D8: ='#보고서'!$B$2 -> A200470 | E8: ='#보고서'!$B$2 -> A200470 | F8: ='#보고서'!$B$2 -> A200470 | G8: ='#보고서'!$B$2 -> A200470 | H8: ='#보고서'!$B$2 -> A200470 | I8: ='#보고서'!$B$2 -> A200470 | ... N8: ='#보고서'!$B$2 -> A200470
A9: Name | B9: 에이팩트 | C9: 에이팩트 | D9: 에이팩트 | E9: 에이팩트 | F9: 에이팩트 | G9: 에이팩트 | H9: 에이팩트 | I9: 에이팩트 | J9: 에이팩트 | K9: 에이팩트 | L9: 에이팩트 | M9: 에이팩트 | N9: 에이팩트
A10: Item Code | B10: S102300 | C10: S101500 | D10: S100300 | E10: S100305 | F10: R105100 | G10: R105120 | H10: S502600.M | I10: S502700.M | J10: S503100.M | K10: S503300.M | L10: S101760.M | M10: S500100.M | N10: S101400
A11: Unit | B11: KRW 100mn | C11: Shares | D11: Local/Shares | E11: Local/Shares | F11: Txt | G11: % | H11: X | I11: X | J11: X | K11: X | L11: Shares | M11: CPD-1TD | N11: CPD-1TD
A12: Base Date | H12: Not Lagging | I12: Not Lagging | M12: X | N12: Local
M13: Not Lagging
A14: D A T E | B14: 시가총액(전체) | C14: 상장주식수 | D14: 수정주가 | E14: 수정주가(평가가격) | F14: 최대주주명 | G14: 최대주주보유보통주지분율 | H14: P/E(MAIN, TTM) | I14: P/B(MAIN, TTM) | J14: P/E(Fwd.12M) | K14: P/B(Fwd.12M) | L14: 액면조정자기주식수 | M14: P/E(FY0) | N14: 거래대금(전체)
A15: 45966 | B15: 2111.75 | C15: 42362093 | D15: 4985 | E15: 4985 | F15: 뮤츄얼그로우쓰 | G15: 55.33 | L15: 1064 | M15: -4.16 | N15: 3931699960
A16: 45965 | B16: 2207.07 | C16: 42362093 | D16: 5210 | E16: 5210 | F16: 뮤츄얼그로우쓰 | G16: 55.33 | L16: 1064 | M16: -4.35 | N16: 3838381830
A17: 45964 | B17: 2185.88 | C17: 42362093 | D17: 5160 | E17: 5160 | F17: 뮤츄얼그로우쓰 | G17: 55.33 | L17: 1064 | M17: -4.31 | N17: 3058594900
A18: 45961 | B18: 2219.77 | C18: 42362093 | D18: 5240 | E18: 5240 | F18: 뮤츄얼그로우쓰 | G18: 55.33 | L18: 1064 | M18: -4.38 | N18: 1946766280
A19: 45960 | B19: 2274.84 | C19: 42362093 | D19: 5370 | E19: 5370 | F19: 뮤츄얼그로우쓰 | G19: 55.33 | L19: 1064 | M19: -4.49 | N19: 4504936555
A20: 45959 | B20: 2168.94 | C20: 42362093 | D20: 5120 | E20: 5120 | F20: 뮤츄얼그로우쓰 | G20: 55.33 | L20: 1064 | M20: -4.28 | N20: 1815821510
A21: 45958 | B21: 2143.52 | C21: 42362093 | D21: 5060 | E21: 5060 | F21: 뮤츄얼그로우쓰 | G21: 55.33 | L21: 1064 | M21: -4.23 | N21: 1494487360
A22: 45957 | B22: 2160.47 | C22: 42362093 | D22: 5100 | E22: 5100 | F22: 뮤츄얼그로우쓰 | G22: 55.33 | L22: 1064 | M22: -4.26 | N22: 3192716225
A23: 45954 | B23: 2181.65 | C23: 42362093 | D23: 5150 | E23: 5150 | F23: 뮤츄얼그로우쓰 | G23: 55.33 | L23: 1064 | M23: -4.3 | N23: 2628807700
A24: 45953 | B24: 2224.01 | C24: 42362093 | D24: 5250 | E24: 5250 | F24: 뮤츄얼그로우쓰 | G24: 55.33 | L24: 1064 | M24: -4.39 | N24: 2588052090
A25: 45952 | B25: 2219.77 | C25: 42362093 | D25: 5240 | E25: 5240 | F25: 뮤츄얼그로우쓰 | G25: 55.33 | L25: 1064 | M25: -4.38 | N25: 2960578380
A26: 45951 | B26: 2245.19 | C26: 42362093 | D26: 5300 | E26: 5300 | F26: 뮤츄얼그로우쓰 | G26: 55.33 | L26: 1064 | M26: -4.43 | N26: 3769980045
... A40: 45931 | B40: 2130.81 | C40: 42362093 | D40: 5030 | E40: 5030 | F40: 뮤츄얼그로우쓰 | G40: 55.33 | L40: 1064 | M40: -4.2 | N40: 6491008595
A41: 45930 | B41: 2003.73 | C41: 42362093 | D41: 4730 | E41: 4730 | F41: 뮤츄얼그로우쓰 | G41: 55.33 | H41: -5.23 | I41: 3.93 | L41: 1064 | M41: -3.95 | N41: 2444447468
A42: 45929 | B42: 1963.48 | C42: 42362093 | D42: 4635 | E42: 4635 | F42: 뮤츄얼그로우쓰 | G42: 55.33 | H42: -5.12 | I42: 3.85 | L42: 1064 | M42: -3.87 | N42: 2701860409
A43: 45926 | B43: 1935.95 | C43: 42362093 | D43: 4570 | E43: 4570 | F43: 뮤츄얼그로우쓰 | G43: 55.33 | H43: -5.05 | I43: 3.8 | L43: 1064 | M43: -3.82 | N43: 1840457199
A44: 45925 | B44: 1929.59 | C44: 42362093 | D44: 4555 | E44: 4555 | F44: 뮤츄얼그로우쓰 | G44: 55.33 | H44: -5.03 | I44: 3.79 | L44: 1064 | M44: -3.8 | N44: 1715412805
A45: 45924 | B45: 1944.42 | C45: 42362093 | D45: 4590 | E45: 4590 | F45: 뮤츄얼그로우쓰 | G45: 55.33 | H45: -5.07 | I45: 3.82 | L45: 1064 | M45: -3.83 | N45: 2964061288
A46: 45923 | B46: 1919 | C46: 42362093 | D46: 4530 | E46: 4530 | F46: 뮤츄얼그로우쓰 | G46: 55.33 | H46: -5.01 | I46: 3.77 | L46: 1064 | M46: -3.78 | N46: 5201565818
A47: 45922 | B47: 2014.32 | C47: 42362093 | D47: 4755 | E47: 4755 | F47: 뮤츄얼그로우쓰 | G47: 55.33 | H47: -5.25 | I47: 3.95 | L47: 1064 | M47: -3.97 | N47: 12369866984
A48: 45919 | B48: 1810.98 | C48: 42362093 | D48: 4275 | E48: 4275 | F48: 뮤츄얼그로우쓰 | G48: 55.33 | H48: -4.72 | I48: 3.55 | L48: 1064 | M48: -3.57 | N48: 6309956107
A49: 45918 | B49: 1707.19 | C49: 42362093 | D49: 4030 | E49: 4030 | F49: 뮤츄얼그로우쓰 | G49: 55.33 | H49: -4.45 | I49: 3.35 | L49: 1064 | M49: -3.37 | N49: 7727552812
A50: 45917 | B50: 1520.8 | C50: 42362093 | D50: 3590 | E50: 3590 | F50: 뮤츄얼그로우쓰 | G50: 55.33 | H50: -3.97 | I50: 2.98 | L50: 1064 | M50: -3 | N50: 4992560201
A51: 45916 | B51: 1467.85 | C51: 42362093 | D51: 3465 | E51: 3465 | F51: 뮤츄얼그로우쓰 | G51: 55.33 | H51: -3.83 | I51: 2.88 | L51: 1064 | M51: -2.89 | N51: 2141078892
A52: 45915 | B52: 1444.55 | C52: 42362093 | D52: 3410 | E52: 3410 | F52: 뮤츄얼그로우쓰 | G52: 55.33 | H52: -3.77 | I52: 2.83 | L52: 1064 | M52: -2.85 | N52: 3437894616
... A417: 45404 | B417: 2401.93 | C417: 42362093 | D417: 5670 | E417: 5670 | F417: 뮤츄얼그로우쓰 | G417: 55.33 | H417: -12.16 | I417: 2.52 | L417: 1064 | M417: -14.42 | N417: 7534684210
A418: 45401 | B418: 2380.75 | C418: 42362093 | D418: 5620 | E418: 5620 | F418: 뮤츄얼그로우쓰 | G418: 55.33 | H418: -12.05 | I418: 2.5 | M418: -14.29 | N418: 13555010470
A419: 45400 | B419: 2478.18 | C419: 42362093 | D419: 5850 | E419: 5850 | F419: 뮤츄얼그로우쓰 | G419: 55.33 | H419: -12.55 | I419: 2.6 | M419: -14.88 | N419: 26753280560
A420: 45399 | B420: 2262.14 | C420: 42362093 | D420: 5340 | E420: 5340 | F420: 뮤츄얼그로우쓰 | G420: 55.33 | H420: -11.45 | I420: 2.37 | M420: -13.58 | N420: 64989970100
A421: 45398 | B421: 2088.45 | C421: 42362093 | D421: 4930 | E421: 4930 | F421: 뮤츄얼그로우쓰 | G421: 55.33 | H421: -10.57 | I421: 2.19 | M421: -12.54 | N421: 6900097865
A422: 45397 | B422: 2190.12 | C422: 42362093 | D422: 5170 | E422: 5170 | F422: 뮤츄얼그로우쓰 | G422: 55.33 | H422: -11.09 | I422: 2.3 | M422: -13.15 | N422: 4356896805
A423: 45394 | B423: 2181.65 | C423: 42362093 | D423: 5150 | E423: 5150 | F423: 뮤츄얼그로우쓰 | G423: 55.33 | H423: -11.05 | I423: 2.29 | M423: -13.1 | N423: 5206612260
A424: 45393 | B424: 2211.3 | C424: 42362093 | D424: 5220 | E424: 5220 | F424: 뮤츄얼그로우쓰 | G424: 55.33 | H424: -11.2 | I424: 2.32 | M424: -13.28 | N424: 15260756320
A425: 45392 | B425: 2105.4 | C425: 42362093 | D425: 4970 | E425: 4970 | F425: 뮤츄얼그로우쓰 | G425: 55.33 | H425: -10.66 | I425: 2.21 | M425: -12.64 | N425: 13889501465
A426: 45391 | B426: 2105.4 | C426: 42362093 | D426: 4970 | E426: 4970 | F426: 뮤츄얼그로우쓰 | G426: 55.33 | H426: -10.66 | I426: 2.21 | M426: -12.64 | N426: 13889501465
A427: 45390 | B427: 2329.92 | C427: 42362093 | D427: 5500 | E427: 5500 | F427: 뮤츄얼그로우쓰 | G427: 55.33 | H427: -11.8 | I427: 2.44 | M427: -13.99 | N427: 34171868940
A428: 45387 | B428: 2372.28 | C428: 42362093 | D428: 5600 | E428: 5600 | F428: 뮤츄얼그로우쓰 | G428: 55.33 | H428: -12.01 | I428: 2.49 | M428: -14.24 | N428: 12447974690
A429: 45386 | B429: 2545.96 | C429: 42362093 | D429: 6010 | E429: 6010 | F429: 뮤츄얼그로우쓰 | G429: 55.33 | H429: -12.89 | I429: 2.67 | M429: -15.29 | N429: 15739710690
A430: 45385 | B430: 2660.34 | C430: 42362093 | D430: 6280 | E430: 6280 | F430: 뮤츄얼그로우쓰 | G430: 55.33 | H430: -13.47 | I430: 2.79 | M430: -15.97 | N430: 48100068402
A431: 45384 | B431: 2668.81 | C431: 42362093 | D431: 6300 | E431: 6300 | F431: 뮤츄얼그로우쓰 | G431: 55.33 | H431: -13.51 | I431: 2.8 | L431: 1441382 | M431: -16.02 | N431: 70310079480
A432: 45383 | B432: 2524.78 | C432: 42362093 | D432: 5960 | E432: 5960 | F432: 뮤츄얼그로우쓰 | G432: 55.33 | H432: -12.78 | I432: 2.65 | L432: 1441382 | M432: -15.16 | N432: 33330225650
A433: 45380 | B433: 2482.42 | C433: 42362093 | D433: 5860 | E433: 5860 | F433: 뮤츄얼그로우쓰 | G433: 55.33 | H433: -14.91 | I433: 2.44 | L433: 1441382 | M433: -14.91 | N433: 155479469410
A434: 45379 | B434: 2389.22 | C434: 42362093 | D434: 5640 | E434: 5640 | F434: 뮤츄얼그로우쓰 | G434: 55.33 | H434: -14.35 | I434: 2.35 | L434: 1441382 | M434: -14.35 | N434: 103148617650
A435: 45378 | B435: 2274.84 | C435: 42362093 | D435: 5370 | E435: 5370 | F435: 뮤츄얼그로우쓰 | G435: 55.33 | H435: -13.66 | I435: 2.24 | L435: 1441382 | M435: -13.66 | N435: 12323796550
A436: 45377 | B436: 2232.48 | C436: 42362093 | D436: 5270 | E436: 5270 | F436: 뮤츄얼그로우쓰 | G436: 55.33 | H436: -13.4 | I436: 2.2 | L436: 1441382 | M436: -13.4 | N436: 6832837190
A437: 45376 | B437: 2168.94 | C437: 42362093 | D437: 5120 | E437: 5120 | F437: 뮤츄얼그로우쓰 | G437: 55.33 | H437: -13.02 | I437: 2.14 | L437: 1441382 | M437: -13.02 | N437: 5668190960
A438: 45373 | B438: 2215.54 | C438: 42362093 | D438: 5230 | E438: 5230 | F438: 뮤츄얼그로우쓰 | G438: 55.33 | H438: -13.3 | I438: 2.18 | L438: 1441382 | M438: -13.3 | N438: 6058010190
A439: 45372 | B439: 2236.72 | C439: 42362093 | D439: 5280 | E439: 5280 | F439: 뮤츄얼그로우쓰 | G439: 55.33 | H439: -13.43 | I439: 2.2 | L439: 1441382 | M439: -13.43 | N439: 25113354200
A440: 45371 | B440: 2329.92 | C440: 42362093 | D440: 5500 | E440: 5500 | F440: 뮤츄얼그로우쓰 | G440: 55.33 | H440: -13.99 | I440: 2.29 | L440: 1441382 | M440: -13.99 | N440: 33821252040
A441: 45370 | B441: 2325.68 | C441: 42362093 | D441: 5490 | E441: 5490 | F441: 뮤츄얼그로우쓰 | G441: 55.33 | H441: -13.96 | I441: 2.29 | L441: 1441382 | M441: -13.96 | N441: 18799263730
A442: 45369 | B442: 2414.64 | C442: 42362093 | D442: 5700 | E442: 5700 | F442: 뮤츄얼그로우쓰 | G442: 55.33 | H442: -14.5 | I442: 2.38 | L442: 1441382 | M442: -14.5 | N442: 37139609220
... A587: 45166 | B587: 1584.34 | C587: 42362093 | D587: 3740 | E587: 3740 | F587: 뮤츄얼그로우쓰 | G587: 55.33 | H587: -16.92 | I587: 1.45 | L587: 1441382 | M587: 36.29 | N587: 28251843465
A588: 45163 | B588: 1406.42 | C588: 42362093 | D588: 3320 | E588: 3320 | F588: 뮤츄얼그로우쓰 | G588: 55.33 | H588: -15.02 | I588: 1.29 | J588: 12.79 | K588: 1.02 | L588: 1441382 | M588: 32.22 | N588: 4626029390
A589: 45162 | B589: 1311.11 | C589: 42362093 | D589: 3095 | E589: 3095 | F589: 뮤츄얼그로우쓰 | G589: 55.33 | H589: -14 | I589: 1.2 | J589: 11.92 | K589: 0.95 | L589: 1441382 | M589: 30.03 | N589: 692912075
A590: 45161 | B590: 1287.81 | C590: 42362093 | D590: 3040 | E590: 3040 | F590: 뮤츄얼그로우쓰 | G590: 55.33 | H590: -13.75 | I590: 1.18 | J590: 11.71 | K590: 0.93 | L590: 1441382 | M590: 29.5 | N590: 289799580
A591: 45160 | B591: 1289.93 | C591: 42362093 | D591: 3045 | E591: 3045 | F591: 뮤츄얼그로우쓰 | G591: 55.33 | H591: -13.78 | I591: 1.18 | J591: 11.73 | K591: 0.93 | L591: 1441382 | M591: 29.55 | N591: 345228970
A592: 45159 | B592: 1308.99 | C592: 42362093 | D592: 3090 | E592: 3090 | F592: 뮤츄얼그로우쓰 | G592: 55.33 | H592: -13.98 | I592: 1.2 | J592: 11.9 | K592: 0.95 | L592: 1441382 | M592: 29.98 | N592: 293583040
A593: 45156 | B593: 1336.52 | C593: 42362093 | D593: 3155 | E593: 3155 | F593: 뮤츄얼그로우쓰 | G593: 55.33 | H593: -14.27 | I593: 1.22 | J593: 12.15 | K593: 0.97 | L593: 1441382 | M593: 30.61 | N593: 448898075
A594: 45155 | B594: 1328.05 | C594: 42362093 | D594: 3135 | E594: 3135 | F594: 뮤츄얼그로우쓰 | G594: 55.33 | H594: -14.18 | I594: 1.22 | J594: 12.07 | K594: 0.96 | L594: 1441382 | M594: 30.42 | N594: 481260780
A595: 45154 | B595: 1319.58 | C595: 42362093 | D595: 3115 | E595: 3115 | F595: 뮤츄얼그로우쓰 | G595: 55.33 | H595: -14.09 | I595: 1.21 | J595: 12 | K595: 0.96 | L595: 1441382 | M595: 30.23 | N595: 820611135
A596: 45153 | B596: 1347.11 | C596: 42362093 | D596: 3180 | E596: 3180 | F596: 뮤츄얼그로우쓰 | G596: 55.33 | H596: -14.39 | I596: 1.23 | J596: 12.25 | K596: 0.98 | L596: 1441382 | M596: 30.86 | N596: 387770705
A597: 45152 | B597: 1347.11 | C597: 42362093 | D597: 3180 | E597: 3180 | F597: 뮤츄얼그로우쓰 | G597: 55.33 | H597: -14.39 | I597: 1.23 | J597: 12.25 | K597: 0.98 | L597: 1441382 | M597: 30.86 | N597: 387770705
A598: 45149 | B598: 1402.19 | C598: 42362093 | D598: 3310 | E598: 3310 | F598: 뮤츄얼그로우쓰 | G598: 55.33 | H598: -14.98 | I598: 1.28 | J598: 12.75 | K598: 1.02 | L598: 1441382 | M598: 32.12 | N598: 307492505
A599: 45148 | B599: 1381 | C599: 42362093 | D599: 3260 | E599: 3260 | F599: 뮤츄얼그로우쓰 | G599: 55.33 | H599: -14.75 | I599: 1.26 | J599: 12.55 | K599: 1 | L599: 1441382 | M599: 31.63 | N599: 836728025
... A627: 45110 | B627: 1681.78 | C627: 42362093 | D627: 3970 | E627: 3970 | F627: 뮤츄얼그로우쓰 | G627: 55.33 | H627: -17.96 | I627: 1.54 | J627: 15.29 | K627: 1.23 | L627: 1441382 | M627: 38.52 | N627: 2499287385
A628: 45107 | B628: 1673.3 | C628: 42362093 | D628: 3950 | E628: 3950 | F628: 뮤츄얼그로우쓰 | G628: 55.33 | H628: -48.1 | I628: 1.45 | L628: 1441382 | M628: 38.33 | N628: 2878406585
A629: 45106 | B629: 1624.59 | C629: 42362093 | D629: 3835 | E629: 3835 | F629: 뮤츄얼그로우쓰 | G629: 55.33 | H629: -46.7 | I629: 1.4 | L629: 1441262 | M629: 37.21 | N629: 3138731360
A630: 45105 | B630: 1647.89 | C630: 42362093 | D630: 3890 | E630: 3890 | F630: 뮤츄얼그로우쓰 | G630: 55.33 | H630: -47.37 | I630: 1.42 | L630: 1441262 | M630: 37.75 | N630: 6047815415
A631: 45104 | B631: 1554.69 | C631: 42362093 | D631: 3670 | E631: 3670 | F631: 뮤츄얼그로우쓰 | G631: 55.33 | H631: -44.69 | I631: 1.34 | L631: 1441262 | M631: 35.61 | N631: 5536851875
A632: 45103 | B632: 1465.73 | C632: 42362093 | D632: 3460 | E632: 3460 | F632: 뮤츄얼그로우쓰 | G632: 55.33 | H632: -42.13 | I632: 1.27 | L632: 1441262 | M632: 33.57 | N632: 2947337390
A633: 45100 | B633: 1393.71 | C633: 42362093 | D633: 3290 | E633: 3290 | F633: 뮤츄얼그로우쓰 | G633: 55.33 | H633: -40.06 | I633: 1.2 | L633: 1441262 | M633: 31.92 | N633: 281052580
A634: 45099 | B634: 1404.3 | C634: 42362093 | D634: 3315 | E634: 3315 | F634: 뮤츄얼그로우쓰 | G634: 55.33 | H634: -40.37 | I634: 1.21 | L634: 1441262 | M634: 32.17 | N634: 289733035
A635: 45098 | B635: 1385.24 | C635: 42362093 | D635: 3270 | E635: 3270 | F635: 뮤츄얼그로우쓰 | G635: 55.33 | H635: -39.82 | I635: 1.2 | L635: 1441262 | M635: 31.73 | N635: 592838795
A636: 45097 | B636: 1412.78 | C636: 42362093 | D636: 3335 | E636: 3335 | F636: 뮤츄얼그로우쓰 | G636: 55.33 | H636: -40.61 | I636: 1.22 | L636: 1441262 | M636: 32.36 | N636: 563535805
A637: 45096 | B637: 1429.72 | C637: 42362093 | D637: 3375 | E637: 3375 | F637: 뮤츄얼그로우쓰 | G637: 55.33 | H637: -41.1 | I637: 1.23 | L637: 1441262 | M637: 32.75 | N637: 946026785
A638: 45093 | B638: 1442.43 | C638: 42362093 | D638: 3405 | E638: 3405 | F638: 뮤츄얼그로우쓰 | G638: 55.33 | H638: -41.46 | I638: 1.25 | L638: 1441262 | M638: 33.04 | N638: 1576502665
A639: 45092 | B639: 1444.55 | C639: 42362093 | D639: 3410 | E639: 3410 | F639: 뮤츄얼그로우쓰 | G639: 55.33 | H639: -41.52 | I639: 1.25 | L639: 1441262 | M639: 33.09 | N639: 1837312980
... A757: 44928 | B757: 1031.52 | C757: 42362093 | D757: 2435 | E757: 2435 | F757: 뮤츄얼그로우쓰 | G757: 55.33 | H757: 85.66 | I757: 0.87 | L757: 1440755 | M757: 23.63 | N757: 104883815
A758: 44925 | B758: 1048.46 | C758: 42362093 | D758: 2475 | E758: 2475 | F758: 뮤츄얼그로우쓰 | G758: 55.33 | H758: 12.61 | I758: 0.9 | J758: 3.23 | K758: 0.96 | L758: 1440755 | M758: 24.21 | N758: 200602590
A759: 44924 | B759: 1048.46 | C759: 42362093 | D759: 2475 | E759: 2475 | F759: 뮤츄얼그로우쓰 | G759: 55.33 | H759: 12.61 | I759: 0.9 | J759: 3.23 | K759: 0.96 | L759: 1440755 | M759: 24.21 | N759: 200602590
A760: 44923 | B760: 1097.18 | C760: 42362093 | D760: 2590 | E760: 2590 | F760: 뮤츄얼그로우쓰 | G760: 55.33 | H760: 13.2 | I760: 0.94 | J760: 3.38 | K760: 1.01 | L760: 1440755 | M760: 25.33 | N760: 92985800
A761: 44922 | B761: 1124.71 | C761: 42362093 | D761: 2655 | E761: 2655 | F761: 뮤츄얼그로우쓰 | G761: 55.33 | H761: 13.53 | I761: 0.96 | J761: 3.46 | K761: 1.03 | L761: 1440755 | M761: 25.97 | N761: 473848420
A762: 44921 | B762: 1069.64 | C762: 42362093 | D762: 2525 | E762: 2525 | F762: 뮤츄얼그로우쓰 | G762: 55.33 | H762: 12.87 | I762: 0.92 | J762: 3.29 | K762: 0.98 | L762: 1440755 | M762: 24.7 | N762: 255498430
A763: 44918 | B763: 1069.64 | C763: 42362093 | D763: 2525 | E763: 2525 | F763: 뮤츄얼그로우쓰 | G763: 55.33 | H763: 12.87 | I763: 0.92 | J763: 3.29 | K763: 0.98 | L763: 1440755 | M763: 24.7 | N763: 328139400
A764: 44917 | B764: 1124.71 | C764: 42362093 | D764: 2655 | E764: 2655 | F764: 뮤츄얼그로우쓰 | G764: 55.33 | H764: 13.53 | I764: 0.96 | J764: 3.46 | K764: 1.03 | L764: 1440755 | M764: 25.97 | N764: 116687305
A765: 44916 | B765: 1114.12 | C765: 42362093 | D765: 2630 | E765: 2630 | F765: 뮤츄얼그로우쓰 | G765: 55.33 | H765: 13.4 | I765: 0.95 | J765: 3.43 | K765: 1.02 | L765: 1440755 | M765: 25.72 | N765: 118589125
...

Sheet Sheet1
A1: 날짜 | B1: 주가 | C1: 거래대금(전체) | E1: 날짜 | F1: 주가 | G1: 거래량(억원)
A2: 45966 | B2: 4985 | C2: 3931699960 | E2: 45966 | F2: 4985 | G2: =C2/10^8 -> 39.317
A3: 45965 | B3: 5210 | C3: 3838381830 | E3: 45965 | F3: 5210 | G3: =C3/10^8 -> 38.383818
A4: 45964 | B4: 5160 | C4: 3058594900 | E4: 45964 | F4: 5160 | G4: =C4/10^8 -> 30.585949
A5: 45961 | B5: 5240 | C5: 1946766280 | E5: 45961 | F5: 5240 | G5: =C5/10^8 -> 19.467663
A6: 45960 | B6: 5370 | C6: 4504936555 | E6: 45960 | F6: 5370 | G6: =C6/10^8 -> 45.049366
A7: 45959 | B7: 5120 | C7: 1815821510 | E7: 45959 | F7: 5120 | G7: =C7/10^8 -> 18.158215
A8: 45958 | B8: 5060 | C8: 1494487360 | E8: 45958 | F8: 5060 | G8: =C8/10^8 -> 14.944874
A9: 45957 | B9: 5100 | C9: 3192716225 | E9: 45957 | F9: 5100 | G9: =C9/10^8 -> 31.927162
A10: 45954 | B10: 5150 | C10: 2628807700 | E10: 45954 | F10: 5150 | G10: =C10/10^8 -> 26.288077
A11: 45953 | B11: 5250 | C11: 2588052090 | E11: 45953 | F11: 5250 | G11: =C11/10^8 -> 25.880521
A12: 45952 | B12: 5240 | C12: 2960578380 | E12: 45952 | F12: 5240 | G12: =C12/10^8 -> 29.605784
A13: 45951 | B13: 5300 | C13: 3769980045 | E13: 45951 | F13: 5300 | G13: =C13/10^8 -> 37.6998
... A1788: 43466 | B1788: 2709 | C1788: 474839150 | E1788: 43466 | F1788: 2709 | G1788: =C1788/10^8 -> 4.7483915
A1789: 43465 | B1789: 2709 | C1789: 474839150
A1790: 43462 | B1790: 2709 | C1790: 474839150
A1791: 43461 | B1791: 2611 | C1791: 402484215
A1792: 43460 | B1792: 2577 | C1792: 811484720
A1793: 43459 | B1793: 2679 | C1793: 376261175
A1794: 43458 | B1794: 2679 | C1794: 376261175
A1795: 43455 | B1795: 2713 | C1795: 359925435
A1796: 43454 | B1796: 2726 | C1796: 318738365
A1797: 43453 | B1797: 2750 | C1797: 545550450
A1798: 43452 | B1798: 2716 | C1798: 851027905
A1799: 43451 | B1799: 2672 | C1799: 1583951700
A1800: 43448 | B1800: 2811 | C1800: 777466560
... A2833: 42003 | B2833: 1424 | C2833: 6290356095

Sheet PEER
A1: Refresh | B1: Last Update : 2025-11-06 17:20:17
A3: Peer Analysis (To Select)
A4: Account Type | B4: All Listed | C4: Korean
